Workbook
Name Beta: Assumptions!$B$47
Name CostOfEquity: Assumptions!$B$48
Name CurrentPrice: DCF!$B$27
Name DilutedShares: Assumptions!$B$58
Name EnterpriseValue: DCF!$B$22
Name EPS_FY25A: IS!$F$43
Name EPS_FY28E: IS!$I$43
Name EPS_FY29E: IS!$J$43
Name EPS_Range: IS!$B$43:$J$43
Name EquityValue: DCF!$B$24
Name ERP: Assumptions!$B$46
Name FCF_FY25A: CFS!$F$21
Name FCF_FY26E: CFS!$G$21
Name FCF_FY28E: CFS!$I$21
Name FCF_FY29E: CFS!$J$21
Name FCF_Range: CFS!$B$21:$J$21
Name FocusYear: Dashboard!$B$18
Name GeographyFilter: Dashboard!$B$24
Name GrossMargin_Range: Ratios!$B$7:$J$7
Name GrossProfit_FY25A: IS!$F$21
Name GrossProfit_FY28E: IS!$I$21
Name GrossProfit_FY29E: IS!$J$21
Name ImpliedPrice: DCF!$B$26
Name NetIncome_FY25A: IS!$F$38
Name NetIncome_FY26E: IS!$G$38
Name NetIncome_FY28E: IS!$I$38
Name NetIncome_FY29E: IS!$J$38
Name NetIncome_Range: IS!$B$38:$J$38
Name NetMargin_Range: Ratios!$B$9:$J$9
Name OpIncome_FY25A: IS!$F$28
Name OpIncome_FY28E: IS!$I$28
Name OpIncome_FY29E: IS!$J$28
Name OpIncome_Range: IS!$B$28:$J$28
Name OpMargin_Range: Ratios!$B$8:$J$8
Name ProductsRev_Range: IS!$B$8:$J$8
Name Revenue_FY25A: IS!$F$14
Name Revenue_FY26E: IS!$G$14
Name Revenue_FY27E: IS!$H$14
Name Revenue_FY28E: IS!$I$14
Name Revenue_FY29E: IS!$J$14
Name Revenue_Range: IS!$B$14:$J$14
Name RiskFreeRate: Assumptions!$B$45
Name Scenario: Dashboard!$B$15
Name SegmentView: Dashboard!$B$21
Name ServicesRev_Range: IS!$B$13:$J$13
Name TerminalGrowth: Assumptions!$B$55
Name Upside: DCF!$B$28
Name WACC: Assumptions!$B$54

Sheet Dashboard
B2: APPLE INC. (AAPL) FINANCIAL DASHBOARD
B3: OVERVIEW OF REVENUE, COSTS, PROFITABILITY & KEY INVESTOR METRICS
C7: 💲 TOTAL REVENUE FY26E | G7: 📊 NET INCOME FY26E | K7: 💰 FREE CASH FLOW FY26E | O7: 🏆 TOP SEGMENT | S7: 📈 DILUTED EPS FY26E
C8: ="$"&TEXT(IS!G14/1000,"0.0")&"B" -> $450.3B | G8: ="$"&TEXT(IS!G38/1000,"0.0")&"B" -> $143.4B | K8: ="$"&TEXT(CFS!G21/1000,"0.0")&"B" -> $144.1B | O8: iPhone | S8: ="$"&TEXT(IS!G43,"0.00") -> $9.94
C9: ="▲ "&TEXT(IS!G14/IS!F14-1,"+0.0%;-0.0%")&" vs FY25A" -> ▲ +8.2% vs FY25A | G9: ="▲ "&TEXT(IS!G38/IS!F38-1,"+0.0%;-0.0%")&" vs FY25A" -> ▲ +28.0% vs FY25A | K9: ="▲ "&TEXT(CFS!G21/CFS!F21-1,"+0.0%;-0.0%")&" vs FY25A" -> ▲ +45.9% vs FY25A | O9: ="$"&TEXT(G80/1000,"0.0")&"B ("&TEXT(G80/G$90,"0.0%")&" of mix)" -> $209.6B (50.4% of mix) | S9: ="▲ "&TEXT(IS!G43/IS!F43-1,"+0.0%;-0.0%")&" vs FY25A" -> ▲ +33.2% vs FY25A
B12: FILTERS & CONTROLS | D12: REVENUE TREND & GROWTH % | M12: $M, FY21A–FY28E | N12: REVENUE BY GEOGRAPHY FY25A | U12: $416B
B14: SCENARIO
B15: =Assumptions!B62 -> Bull | C15: ▾
B17: FOCUS YEAR
B18: FY27E | C18: ▾
B20: SEGMENT VIEW
B21: Services | C21: ▾
B23: GEOGRAPHY
B24: Americas | C24: ▾
B27: Click ▾ to filter
B28: Charts respond live | D28: REVENUE BY SEGMENT FY25A | H28: REVENUE BY GEOGRAPHY FY25A | M28: $B / % mix | N28: TOP 5 PRODUCT LINES BY REVENUE FY25A
H30: REGION | L30: REVENUE | M30: MIX
H31: Americas | K31: =REPT("█",ROUND(M31*40,0)) -> █████████████████ | L31: =IS!F52/1000 -> 178.353 | M31: =IS!F52/IS!F57 -> 0.42856731
H32: Europe | K32: =REPT("█",ROUND(M32*40,0)) -> ███████████ | L32: =IS!F53/1000 -> 111.032 | M32: =IS!F53/IS!F57 -> 0.26680059
H33: Greater China | K33: =REPT("█",ROUND(M33*40,0)) -> ██████ | L33: =IS!F54/1000 -> 64.377 | M33: =IS!F54/IS!F57 -> 0.15469253
H34: Rest of APAC | K34: =REPT("█",ROUND(M34*40,0)) -> ███ | L34: =IS!F56/1000 -> 33.696 | M34: =IS!F56/IS!F57 -> 0.080968664
H35: Japan | K35: =REPT("█",ROUND(M35*40,0)) -> ███ | L35: =IS!F55/1000 -> 28.703 | M35: =IS!F55/IS!F57 -> 0.068970903
H37: Total | L37: =IS!F57/1000 -> 416.161 | M37: =L37/L37 -> 1
D45: P&L CASCADE BY FISCAL YEAR | M45: $M | N45: PROFITABILITY MARGINS TREND | U45: % by FY
D47: LINE ITEM | G47: FY23A | H47: FY24A | I47: FY25A | J47: FY26E | K47: FY27E | L47: FY28E | M47: FY29E
D48: Total Revenue | G48: =IS!D14 -> 383285 | H48: =IS!E14 -> 391035 | I48: =IS!F14 -> 416161 | J48: =IS!G14 -> 450257.23 | K48: =IS!H14 -> 487661.72 | L48: =IS!I14 -> 528747.75 | M48: =IS!J14 -> 573935.26
D49: (-) Cost of Sales | G49: =-(IS!D18+IS!D19) -> -214137 | H49: =-(IS!E18+IS!E19) -> -210352 | I49: =-(IS!F18+IS!F19) -> -220960 | J49: =-(IS!G18+IS!G19) -> -221238.01 | K49: =-(IS!H18+IS!H19) -> -236960.57 | L49: =-(IS!I18+IS!I19) -> -253959.02 | M49: =-(IS!J18+IS!J19) -> -272355.16
D50: Gross Profit | G50: =IS!D21 -> 169148 | H50: =IS!E21 -> 180683 | I50: =IS!F21 -> 195201 | J50: =IS!G21 -> 229019.22 | K50: =IS!H21 -> 250701.15 | L50: =IS!I21 -> 274788.73 | M50: =IS!J21 -> 301580.1
D51: (-) R&D Expense | G51: =-IS!D25 -> -29915 | H51: =-IS!E25 -> -31370 | I51: =-IS!F25 -> -34550 | J51: =-IS!G25 -> -36277.5 | K51: =-IS!H25 -> -38091.375 | L51: =-IS!I25 -> -39995.944 | M51: =-IS!J25 -> -41995.741
D52: (-) SG&A Expense | G52: =-IS!D26 -> -24932 | H52: =-IS!E26 -> -26097 | I52: =-IS!F26 -> -27601 | J52: =-IS!G26 -> -28429.03 | K52: =-IS!H26 -> -29281.901 | L52: =-IS!I26 -> -30160.358 | M52: =-IS!J26 -> -31065.169
D53: Operating Income | G53: =IS!D28 -> 114301 | H53: =IS!E28 -> 123216 | I53: =IS!F28 -> 133050 | J53: =IS!G28 -> 164312.69 | K53: =IS!H28 -> 183327.87 | L53: =IS!I28 -> 204632.43 | M53: =IS!J28 -> 228519.19
D54: (-) Income Tax | G54: =-IS!D36 -> -16741 | H54: =-IS!E36 -> -29749 | I54: =-IS!F36 -> -20719 | J54: =-IS!G36 -> -21425.65 | K54: =-IS!H36 -> -23897.624 | L54: =-IS!I36 -> -26667.216 | M54: =-IS!J36 -> -29772.494
D55: Net Income | G55: =IS!D38 -> 96995 | H55: =IS!E38 -> 93736 | I55: =IS!F38 -> 112010 | J55: =IS!G38 -> 143387.04 | K55: =IS!H38 -> 159930.25 | L55: =IS!I38 -> 178465.22 | M55: =IS!J38 -> 199246.69
D56: Diluted EPS ($) | G56: =IS!D43 -> 6.13 | H56: =IS!E43 -> 6.08 | I56: =IS!F43 -> 7.46 | J56: =IS!G43 -> 9.9358043 | K56: =IS!H43 -> 11.585546 | L56: =IS!I43 -> 13.70132 | M56: =IS!J43 -> 16.436705
D57: Free Cash Flow | G57: =CFS!D21 -> 99584 | H57: =CFS!E21 -> 108807 | I57: =CFS!F21 -> 98767 | J57: =CFS!G21 -> 144092.79 | K57: =CFS!H21 -> 157782.04 | L57: =CFS!I21 -> 195986.33 | M57: =CFS!J21 -> 227302.89
D62: REVENUE BY PRODUCT LINE FY25A | J62: FREE CASH FLOW BY FY | O62: $B | P62: KEY INVESTOR INSIGHTS
P64: 🟢 | Q64: ="Gross margin expanding "&TEXT(Ratios!B7,"0.0%")&" → "&TEXT(Ratios!I7,"0.0%") -> Gross margin expanding 41.8% → 52.0%
B65: Region | C65: FY21A | D65: FY22A | E65: FY23A | F65: FY24A | G65: FY25A | H65: FY26E | I65: FY27E | J65: FY28E | Q65: Services mix shift and own-silicon advantage compounding.
B66: Americas | C66: 153306 | D66: 169658 | E66: 162560 | F66: 167045 | G66: 178353 | H66: =G66*(1+H$71) -> 186378.88 | I66: =H66*(1+I$71) -> 193834.04 | J66: =I66*(1+J$71) -> 200618.23
B67: Europe | C67: 89307 | D67: 95118 | E67: 94294 | F67: 101328 | G67: 111032 | H67: =G67*(1+H$72) -> 117693.92 | I67: =H67*(1+I$72) -> 123578.62 | J67: =I67*(1+J$72) -> 129139.65 | P67: 💡 | Q67: ="Services revenue tripling FY21–FY29: $"&TEXT(C84/1000,"0")&"B → $"&TEXT(K84/1000,"0")&"B" -> Services revenue tripling FY21–FY29: $68B → $153B
B68: Greater China | C68: 68366 | D68: 74200 | E68: 72559 | F68: 66952 | G68: 64377 | H68: =G68*(1+H$73) -> 63089.46 | I68: =H68*(1+I$73) -> 63404.907 | J68: =I68*(1+J$73) -> 64673.005 | Q68: =""&TEXT((K84/C84)^(1/8)-1,"0.0%")&" CAGR, "&TEXT(K84/K90,"0.0%")&" of FY29E mix." -> 10.6% CAGR, 30.7% of FY29E mix.
B69: Japan | C69: 28482 | D69: 25977 | E69: 24257 | F69: 25052 | G69: 28703 | H69: =G69*(1+H$74) -> 30425.18 | I69: =H69*(1+I$74) -> 31794.313 | J69: =I69*(1+J$74) -> 32907.114
B70: Rest of APAC | C70: 26356 | D70: 29375 | E70: 29615 | F70: 30658 | G70: 33696 | H70: =G70*(1+H$75) -> 35717.76 | I70: =H70*(1+I$75) -> 37503.648 | J70: =I70*(1+J$75) -> 39191.312 | P70: 🟢 | Q70: ="FCF rebound to $"&TEXT(CFS!G21/1000,"0")&"B in FY26E" -> FCF rebound to $144B in FY26E
B71: Americas g% | H71: 0.045 | I71: 0.04 | J71: 0.035 | Q71: ="+"&TEXT(CFS!G21/CFS!F21-1,"0%")&" YoY on working capital normalization." -> +46% YoY on working capital normalization.
B72: Europe g% | H72: 0.06 | I72: 0.05 | J72: 0.045
B73: Greater China g% | H73: -0.02 | I73: 0.005 | J73: 0.02 | P73: ⚠️ | Q73: ="Greater China revenue softening" -> Greater China revenue softening
B74: Japan g% | H74: 0.06 | I74: 0.045 | J74: 0.035 | Q74: ="from $"&TEXT(D68/1000,"0")&"B (FY22A) to $"&TEXT(G68/1000,"0")&"B (FY25A), -"&TEXT(1-G68/D68,"0%")&" decline." -> from $74B (FY22A) to $64B (FY25A), -13% decline.
B75: RoAPAC g% | H75: 0.06 | I75: 0.05 | J75: 0.045
B76: Total | C76: =SUM(C66:C70) -> 365817 | D76: =SUM(D66:D70) -> 394328 | E76: =SUM(E66:E70) -> 383285 | F76: =SUM(F66:F70) -> 391035 | G76: =SUM(G66:G70) -> 416161 | H76: =SUM(H66:H70) -> 433305.21 | I76: =SUM(I66:I70) -> 450115.52 | J76: =SUM(J66:J70) -> 466529.32
B79: Product Line | C79: FY21A | D79: FY22A | E79: FY23A | F79: FY24A | G79: FY25A | H79: FY26E | I79: FY27E | J79: FY28E | K79: FY29E
B80: iPhone | C80: 191973 | D80: 205489 | E80: 200583 | F80: 201183 | G80: 209586 | H80: =G80*(1+H$85) -> 216921.51 | I80: =H80*(1+I$85) -> 223429.16 | J80: =I80*(1+J$85) -> 229014.88 | K80: =J80*(1+K$85) -> 234740.26
B81: Mac | C81: 35190 | D81: 40177 | E81: 29357 | F81: 29984 | G81: 33708 | H81: =G81*(1+H$86) -> 35393.4 | I81: =H81*(1+I$86) -> 36986.103 | J81: =I81*(1+J$86) -> 38465.547 | K81: =J81*(1+K$86) -> 40004.169
B82: iPad | C82: 31862 | D82: 29292 | E82: 28300 | F82: 26694 | G82: 28023 | H82: =G82*(1+H$87) -> 29003.805 | I82: =H82*(1+I$87) -> 29873.919 | J82: =I82*(1+J$87) -> 30620.767 | K82: =J82*(1+K$87) -> 31386.286
B83: Wearables | C83: 38367 | D83: 41241 | E83: 39845 | F83: 37005 | G83: 35686 | H83: =G83*(1+H$88) -> 36399.72 | I83: =H83*(1+I$88) -> 37491.712 | J83: =I83*(1+J$88) -> 38991.38 | K83: =J83*(1+K$88) -> 40551.035
B84: Services | C84: 68425 | D84: 78129 | E84: 85200 | F84: 96169 | G84: 109158 | H84: =G84*(1+H$89) -> 121711.17 | I84: =H84*(1+I$89) -> 132665.18 | J84: =I84*(1+J$89) -> 142615.06 | K84: =J84*(1+K$89) -> 153311.19
B85: iPhone g% | H85: 0.035 | I85: 0.03 | J85: 0.025 | K85: 0.025
B86: Mac g% | H86: 0.05 | I86: 0.045 | J86: 0.04 | K86: 0.04
B87: iPad g% | H87: 0.035 | I87: 0.03 | J87: 0.025 | K87: 0.025
B88: Wearables g% | H88: 0.02 | I88: 0.03 | J88: 0.04 | K88: 0.04
B89: Services g% | H89: 0.115 | I89: 0.09 | J89: 0.075 | K89: 0.075
B90: Total | C90: =SUM(C80:C84) -> 365817 | D90: =SUM(D80:D84) -> 394328 | E90: =SUM(E80:E84) -> 383285 | F90: =SUM(F80:F84) -> 391035 | G90: =SUM(G80:G84) -> 416161 | H90: =SUM(H80:H84) -> 439429.6 | I90: =SUM(I80:I84) -> 460446.06 | J90: =SUM(J80:J84) -> 479707.64 | K90: =SUM(K80:K84) -> 499992.94
C92: FY21A | D92: FY22A | E92: FY23A | F92: FY24A | G92: FY25A | H92: FY26E | I92: FY27E | J92: FY28E | K92: FY29E
B93: Products ($B) | C93: =IS!B8/1000 -> 297.392 | D93: =IS!C8/1000 -> 316.199 | E93: =IS!D8/1000 -> 298.085 | F93: =IS!E8/1000 -> 294.866 | G93: =IS!F8/1000 -> 307.003 | H93: =IS!G8/1000 -> 325.81711 | I93: =IS!H8/1000 -> 345.79999 | J93: =IS!I8/1000 -> 367.02537 | K93: =IS!J8/1000 -> 389.57174
B94: Services ($B) | C94: =IS!B13/1000 -> 68.425 | D94: =IS!C13/1000 -> 78.129 | E94: =IS!D13/1000 -> 85.2 | F94: =IS!E13/1000 -> 96.169 | G94: =IS!F13/1000 -> 109.158 | H94: =IS!G13/1000 -> 124.44012 | I94: =IS!H13/1000 -> 141.86174 | J94: =IS!I13/1000 -> 161.72238 | K94: =IS!J13/1000 -> 184.36351
B95: Growth % | D95: =IS!C14/IS!B14-1 -> 0.077937876 | E95: =IS!D14/IS!C14-1 -> -0.028004605 | F95: =IS!E14/IS!D14-1 -> 0.020219941 | G95: =IS!F14/IS!E14-1 -> 0.064255118 | H95: =IS!G14/IS!F14-1 -> 0.081930383 | I95: =IS!H14/IS!G14-1 -> 0.083073613 | J95: =IS!I14/IS!H14-1 -> 0.084251084 | K95: =IS!J14/IS!I14-1 -> 0.085461359
B97: Region | C97: FY25A ($B)
B98: Americas | C98: =F66/1000 -> 167.045
B99: Europe | C99: =F67/1000 -> 101.328
B100: Greater China | C100: =F68/1000 -> 66.952
B101: Japan | C101: =F69/1000 -> 25.052
B102: Rest of APAC | C102: =F70/1000 -> 30.658
B104: Segment | C104: FY25A ($B)
B105: Products | C105: =IS!F8/1000 -> 307.003
B106: Services | C106: =IS!F13/1000 -> 109.158
B108: Product | C108: FY25A ($B)
B109: iPad | C109: =F82/1000 -> 26.694
B110: Mac | C110: =F81/1000 -> 29.984
B111: Wearables | C111: =F83/1000 -> 37.005
B112: Services | C112: =F84/1000 -> 96.169
B113: iPhone | C113: =F80/1000 -> 201.183
C115: FY21A | D115: FY22A | E115: FY23A | F115: FY24A | G115: FY25A | H115: FY26E | I115: FY27E | J115: FY28E | K115: FY29E
B116: Gross % | C116: =Ratios!B7 -> 0.4177936 | D116: =Ratios!C7 -> 0.43309631 | E116: =Ratios!D7 -> 0.4413113 | F116: =Ratios!E7 -> 0.4620635 | G116: =Ratios!F7 -> 0.46905164 | H116: =Ratios!G7 -> 0.50864086 | I116: =Ratios!H7 -> 0.51408822 | J116: =Ratios!I7 -> 0.51969721 | K116: =Ratios!J7 -> 0.52546013
B117: Operating % | C117: =Ratios!B8 -> 0.29782378 | D117: =Ratios!C8 -> 0.30288744 | E117: =Ratios!D8 -> 0.29821412 | F117: =Ratios!E8 -> 0.31510223 | G117: =Ratios!F8 -> 0.319708 | H117: =Ratios!G8 -> 0.36493072 | I117: =Ratios!H8 -> 0.37593246 | J117: =Ratios!I8 -> 0.38701333 | K117: =Ratios!J8 -> 0.39816196
B118: Net % | C118: =Ratios!B9 -> 0.25881793 | D118: =Ratios!C9 -> 0.25309641 | E118: =Ratios!D9 -> 0.25306234 | F118: =Ratios!E9 -> 0.23971256 | G118: =Ratios!F9 -> 0.26915064 | H118: =Ratios!G9 -> 0.31845584 | I118: =Ratios!H9 -> 0.32795326 | J118: =Ratios!I9 -> 0.3375243 | K118: =Ratios!J9 -> 0.34715883
B119: FCF % | C119: =Ratios!B31 -> 0.25409699 | D119: =Ratios!C31 -> 0.28261498 | E119: =Ratios!D31 -> 0.25981711 | F119: =Ratios!E31 -> 0.27825386 | G119: =Ratios!F31 -> 0.23732882 | H119: =Ratios!G31 -> 0.32002327 | I119: =Ratios!H31 -> 0.32354814 | J119: =Ratios!I31 -> 0.3706613 | K119: =Ratios!J31 -> 0.39604275
B121: Product | C121: FY24A | D121: FY25A | E121: FY26E
B122: iPhone | C122: =E80/1000 -> 200.583 | D122: =F80/1000 -> 201.183 | E122: =G80/1000 -> 209.586
B123: Services | C123: =E84/1000 -> 85.2 | D123: =F84/1000 -> 96.169 | E123: =G84/1000 -> 109.158
B124: Wearables | C124: =E83/1000 -> 39.845 | D124: =F83/1000 -> 37.005 | E124: =G83/1000 -> 35.686
B125: Mac | C125: =E81/1000 -> 29.357 | D125: =F81/1000 -> 29.984 | E125: =G81/1000 -> 33.708
B126: iPad | C126: =E82/1000 -> 28.3 | D126: =F82/1000 -> 26.694 | E126: =G82/1000 -> 28.023
C128: FY21A | D128: FY22A | E128: FY23A | F128: FY24A | G128: FY25A | H128: FY26E | I128: FY27E | J128: FY28E | K128: FY29E
B129: FCF ($B) | C129: =CFS!B21/1000 -> 92.953 | D129: =CFS!C21/1000 -> 111.443 | E129: =CFS!D21/1000 -> 99.584 | F129: =CFS!E21/1000 -> 108.807 | G129: =CFS!F21/1000 -> 98.767 | H129: =CFS!G21/1000 -> 144.09279 | I129: =CFS!H21/1000 -> 157.78204 | J129: =CFS!I21/1000 -> 195.98633 | K129: =CFS!J21/1000 -> 227.30289

Sheet Cover
B1: APPLE INC. (NASDAQ: AAPL)
B2: Investment Analyst Model | 3-Statement Forecast + DCF Valuation
B5: MODEL OVERVIEW
B7: Issuer | C7: Apple Inc. (NASDAQ: AAPL)
B8: Sector | C8: Technology — Consumer Electronics & Services
B9: Reporting period | C9: Fiscal years ending last Saturday of September
B10: Historicals | C10: FY2021 – FY2025 (5 years actuals from 10-K filings)
B11: Projections | C11: FY2026E – FY2029E (4 years forecast)
B12: Methodology | C12: Top-down driver-based: segment revenue → gross margin → OpEx → BS roll-forwards
B13: Valuation | C13: DCF using WACC ~8.5%, terminal growth 2.5%, with 5×5 sensitivity table; 4-year explicit forecast + terminal at year 5
B14: Tax assumption | C14: Normalized 15.0% effective rate (FY24 actual elevated by $10.2B EU State Aid charge)
B15: Capital return | C15: ~95% of FCF returned to shareholders via buybacks + dividends (Apple stated policy)
B17: WORKBOOK STRUCTURE
B19: Cover | C19: This page
B20: Assumptions | C20: All forecast drivers — segment growth rates, margins, tax, WACC inputs (BLUE = editable)
B21: IS | C21: Income Statement FY21A–FY29E — top-down build from segment revenue
B22: BS | C22: Balance Sheet FY21A–FY29E — working capital days-based, full roll-forwards
B23: CFS | C23: Cash Flow Statement FY21A–FY29E — indirect method, ties to BS change in cash
B24: Ratios | C24: Profitability, returns, leverage, working capital ratios
B25: DCF | C25: Enterprise value, equity value, implied share price + WACC × g sensitivity
B26: Dashboard | C26: Executive view — KPIs, valuation summary, key charts
B27: Data Refs | C27: All 50+ named ranges documented (name, refers to, used in)
B29: COLOR CONVENTIONS (IB STANDARD)
B31: BLUE | C31: Hardcoded inputs (historicals from 10-K + assumption drivers)
B32: BLACK | C32: Formulas (calculated from inputs and other formulas)
B33: GREEN | C33: Cross-sheet links (pulled from another sheet)
B34: RED | C34: Audit checks (must equal zero) and error flags
B36: DATA SOURCES
B38: 10-K FY2025 | C38: Filed Oct 31, 2025 — covers FY2023A, FY2024A, FY2025A
B39: 10-K FY2022 | C39: Filed Oct 28, 2022 — covers FY2020, FY2021A, FY2022A
B40: SEC EDGAR | C40: https://www.sec.gov/cgi-bin/browse-edgar?action=getcompany&CIK=0000320193
B43: PREPARED BY
B44: Alven Emmanuel | CPA, Financial Data Scientist | Nairobi, Kenya
B45: Fiverr: alvenemmanuel | GitHub: @alvenyuka

Sheet Assumptions
A1: ASSUMPTIONS | Forecast Drivers
A4: USD Millions | B4: FY2021A | C4: FY2022A | D4: FY2023A | E4: FY2024A | F4: FY2025A | G4: FY2026E | H4: FY2027E | I4: FY2028E | J4: FY2029E
B5: Sep 25, 2021 | C5: Sep 24, 2022 | D5: Sep 30, 2023 | E5: Sep 28, 2024 | F5: Sep 27, 2025 | G5: Sep 26, 2026 | H5: Sep 25, 2027 | I5: Sep 30, 2028 | J5: Sep 30, 2029
A7: REVENUE GROWTH DRIVERS | Segment-Level
A8: Products revenue YoY growth | B8: ="" | C8: =IS!C8/IS!B8-1 -> 0.063239764 | D8: =IS!D8/IS!C8-1 -> -0.057286709 | E8: =IS!E8/IS!D8-1 -> -0.010798933 | F8: =IS!F8/IS!E8-1 -> 0.04116107 | G8: =CHOOSE(MATCH(Scenario,{"Bear","Base","Bull"},0),$B$65,$C$65,$D$65) -> 0.061283147 | H8: =CHOOSE(MATCH(Scenario,{"Bear","Base","Bull"},0),$B$65,$C$65,$D$65) -> 0.061283147 | I8: =CHOOSE(MATCH(Scenario,{"Bear","Base","Bull"},0),$B$65,$C$65,$D$65) -> 0.061283147 | J8: =CHOOSE(MATCH(Scenario,{"Bear","Base","Bull"},0),$B$65,$C$65,$D$65) -> 0.061283147
A9: iPhone | C9: =IS!C9/IS!B9-1 -> 0.070405734 | D9: =IS!D9/IS!C9-1 -> -0.023874757 | E9: =IS!E9/IS!D9-1 -> 0.0029912804 | F9: =IS!F9/IS!E9-1 -> 0.041767943 | G9: =CHOOSE(MATCH(Scenario,{"Bear","Base","Bull"},0),$B$66,$C$66,$D$66) -> 0.06 | H9: =CHOOSE(MATCH(Scenario,{"Bear","Base","Bull"},0),$B$66,$C$66,$D$66) -> 0.06 | I9: =CHOOSE(MATCH(Scenario,{"Bear","Base","Bull"},0),$B$66,$C$66,$D$66) -> 0.06 | J9: =CHOOSE(MATCH(Scenario,{"Bear","Base","Bull"},0),$B$66,$C$66,$D$66) -> 0.06
A10: Mac | C10: =IS!C10/IS!B10-1 -> 0.1417164 | D10: =IS!D10/IS!C10-1 -> -0.26930831 | E10: =IS!E10/IS!D10-1 -> 0.021357768 | F10: =IS!F10/IS!E10-1 -> 0.12419957 | G10: =CHOOSE(MATCH(Scenario,{"Bear","Base","Bull"},0),$B$67,$C$67,$D$67) -> 0.08 | H10: =CHOOSE(MATCH(Scenario,{"Bear","Base","Bull"},0),$B$67,$C$67,$D$67) -> 0.08 | I10: =CHOOSE(MATCH(Scenario,{"Bear","Base","Bull"},0),$B$67,$C$67,$D$67) -> 0.08 | J10: =CHOOSE(MATCH(Scenario,{"Bear","Base","Bull"},0),$B$67,$C$67,$D$67) -> 0.08
A11: iPad | C11: =IS!C11/IS!B11-1 -> -0.080660348 | D11: =IS!D11/IS!C11-1 -> -0.033865902 | E11: =IS!E11/IS!D11-1 -> -0.056749117 | F11: =IS!F11/IS!E11-1 -> 0.049786469 | G11: =CHOOSE(MATCH(Scenario,{"Bear","Base","Bull"},0),$B$68,$C$68,$D$68) -> 0.05 | H11: =CHOOSE(MATCH(Scenario,{"Bear","Base","Bull"},0),$B$68,$C$68,$D$68) -> 0.05 | I11: =CHOOSE(MATCH(Scenario,{"Bear","Base","Bull"},0),$B$68,$C$68,$D$68) -> 0.05 | J11: =CHOOSE(MATCH(Scenario,{"Bear","Base","Bull"},0),$B$68,$C$68,$D$68) -> 0.05
A12: Wearables, Home & Accessories | C12: =IS!C12/IS!B12-1 -> 0.074908124 | D12: =IS!D12/IS!C12-1 -> -0.03384981 | E12: =IS!E12/IS!D12-1 -> -0.071276195 | F12: =IS!F12/IS!E12-1 -> -0.035643832 | G12: =CHOOSE(MATCH(Scenario,{"Bear","Base","Bull"},0),$B$69,$C$69,$D$69) -> 0.06 | H12: =CHOOSE(MATCH(Scenario,{"Bear","Base","Bull"},0),$B$69,$C$69,$D$69) -> 0.06 | I12: =CHOOSE(MATCH(Scenario,{"Bear","Base","Bull"},0),$B$69,$C$69,$D$69) -> 0.06 | J12: =CHOOSE(MATCH(Scenario,{"Bear","Base","Bull"},0),$B$69,$C$69,$D$69) -> 0.06
A13: Services revenue YoY growth | B13: ="" | C13: =IS!C13/IS!B13-1 -> 0.14181951 | D13: =IS!D13/IS!C13-1 -> 0.090504166 | E13: =IS!E13/IS!D13-1 -> 0.12874413 | F13: =IS!F13/IS!E13-1 -> 0.13506431 | G13: =CHOOSE(MATCH(Scenario,{"Bear","Base","Bull"},0),$B$70,$C$70,$D$70) -> 0.14 | H13: =CHOOSE(MATCH(Scenario,{"Bear","Base","Bull"},0),$B$70,$C$70,$D$70) -> 0.14 | I13: =CHOOSE(MATCH(Scenario,{"Bear","Base","Bull"},0),$B$70,$C$70,$D$70) -> 0.14 | J13: =CHOOSE(MATCH(Scenario,{"Bear","Base","Bull"},0),$B$70,$C$70,$D$70) -> 0.14
A15: MARGIN DRIVERS | Segment-Level Gross Margins
A16: Products gross margin % | B16: =(IS!B8-IS!B18)/IS!B8 -> 0.35349303 | C16: =(IS!C8-IS!C18)/IS!C8 -> 0.3628348 | D16: =(IS!D8-IS!D18)/IS!D8 -> 0.36500663 | E16: =(IS!E8-IS!E18)/IS!E8 -> 0.37180618 | F16: =(IS!F8-IS!F18)/IS!F8 -> 0.3677065 | G16: =CHOOSE(MATCH(Scenario,{"Bear","Base","Bull"},0),$B$71,$C$71,$D$71) -> 0.405 | H16: =CHOOSE(MATCH(Scenario,{"Bear","Base","Bull"},0),$B$71,$C$71,$D$71) -> 0.405 | I16: =CHOOSE(MATCH(Scenario,{"Bear","Base","Bull"},0),$B$71,$C$71,$D$71) -> 0.405 | J16: =CHOOSE(MATCH(Scenario,{"Bear","Base","Bull"},0),$B$71,$C$71,$D$71) -> 0.405
A17: Services gross margin % | B17: =(IS!B13-IS!B19)/IS!B13 -> 0.69725977 | C17: =(IS!C13-IS!C19)/IS!C13 -> 0.71745447 | D17: =(IS!D13-IS!D19)/IS!D13 -> 0.70827465 | E17: =(IS!E13-IS!E19)/IS!E13 -> 0.73880356 | F17: =(IS!F13-IS!F19)/IS!F13 -> 0.75408124 | G17: =CHOOSE(MATCH(Scenario,{"Bear","Base","Bull"},0),$B$72,$C$72,$D$72) -> 0.78 | H17: =CHOOSE(MATCH(Scenario,{"Bear","Base","Bull"},0),$B$72,$C$72,$D$72) -> 0.78 | I17: =CHOOSE(MATCH(Scenario,{"Bear","Base","Bull"},0),$B$72,$C$72,$D$72) -> 0.78 | J17: =CHOOSE(MATCH(Scenario,{"Bear","Base","Bull"},0),$B$72,$C$72,$D$72) -> 0.78
A19: OPERATING EXPENSE DRIVERS | R&D + SG&A YoY Growth
A20: R&D expense YoY growth | B20: ="" | C20: =IS!C25/IS!B25-1 -> 0.19791001 | D20: =IS!D25/IS!C25-1 -> 0.13957564 | E20: =IS!E25/IS!D25-1 -> 0.048637807 | F20: =IS!F25/IS!E25-1 -> 0.10137074 | G20: =CHOOSE(MATCH(Scenario,{"Bear","Base","Bull"},0),$B$73,$C$73,$D$73) -> 0.05 | H20: =CHOOSE(MATCH(Scenario,{"Bear","Base","Bull"},0),$B$73,$C$73,$D$73) -> 0.05 | I20: =CHOOSE(MATCH(Scenario,{"Bear","Base","Bull"},0),$B$73,$C$73,$D$73) -> 0.05 | J20: =CHOOSE(MATCH(Scenario,{"Bear","Base","Bull"},0),$B$73,$C$73,$D$73) -> 0.05
A21: SG&A expense YoY growth | B21: ="" | C21: =IS!C26/IS!B26-1 -> 0.14203796 | D21: 5 | E21: =IS!E26/IS!D26-1 -> 0.046727098 | F21: =IS!F26/IS!E26-1 -> 0.057631145 | G21: =CHOOSE(MATCH(Scenario,{"Bear","Base","Bull"},0),$B$74,$C$74,$D$74) -> 0.03 | H21: =CHOOSE(MATCH(Scenario,{"Bear","Base","Bull"},0),$B$74,$C$74,$D$74) -> 0.03 | I21: =CHOOSE(MATCH(Scenario,{"Bear","Base","Bull"},0),$B$74,$C$74,$D$74) -> 0.03 | J21: =CHOOSE(MATCH(Scenario,{"Bear","Base","Bull"},0),$B$74,$C$74,$D$74) -> 0.03
A23: OTHER INCOME STATEMENT DRIVERS
A24: Other income / (expense), $M | B24: =IS!B34 -> 258 | C24: =IS!C34 -> -334 | D24: =IS!D34 -> -565 | E24: =IS!E34 -> 269 | F24: =IS!F34 -> -321 | G24: =CHOOSE(MATCH(Scenario,{"Bear","Base","Bull"},0),$B$83,$C$83,$D$83) -> 500 | H24: =CHOOSE(MATCH(Scenario,{"Bear","Base","Bull"},0),$B$83,$C$83,$D$83) -> 500 | I24: =CHOOSE(MATCH(Scenario,{"Bear","Base","Bull"},0),$B$83,$C$83,$D$83) -> 500 | J24: =CHOOSE(MATCH(Scenario,{"Bear","Base","Bull"},0),$B$83,$C$83,$D$83) -> 500
A25: Effective tax rate | B25: =IS!B36/IS!B35 -> 0.13302261 | C25: =IS!C36/IS!C35 -> 0.16204462 | D25: =IS!D36/IS!D35 -> 0.14719174 | E25: =IS!E36/IS!E35 -> 0.24091185 | F25: =IS!F36/IS!F35 -> 0.15610002 | G25: =CHOOSE(MATCH(Scenario,{"Bear","Base","Bull"},0),$B$75,$C$75,$D$75) -> 0.13 | H25: =CHOOSE(MATCH(Scenario,{"Bear","Base","Bull"},0),$B$75,$C$75,$D$75) -> 0.13 | I25: =CHOOSE(MATCH(Scenario,{"Bear","Base","Bull"},0),$B$75,$C$75,$D$75) -> 0.13 | J25: =CHOOSE(MATCH(Scenario,{"Bear","Base","Bull"},0),$B$75,$C$75,$D$75) -> 0.13
A27: BALANCE SHEET DRIVERS | Working Capital Days
A28: Days sales outstanding (DSO) | B28: =BS!C7/IS!B14*365 -> 26.219312 | C28: =BS!D7/IS!C14*365 -> 26.087825 | D28: =BS!E7/IS!D14*365 -> 28.100291 | E28: =BS!F7/IS!E14*365 -> 31.185572 | F28: =BS!G7/IS!F14*365 -> 34.886991 | G28: 30 | H28: 30 | I28: 30 | J28: 30
A29: Days inventory outstanding (DIO) | B29: =BS!C8/IS!B20*365 -> 11.276593 | C29: =BS!D8/IS!C20*365 -> 8.0756981 | D29: =BS!E8/IS!D20*365 -> 10.791292 | E29: =BS!F8/IS!E20*365 -> 12.642571 | F29: =BS!G8/IS!F20*365 -> 9.4454652 | G29: 10 | H29: 10 | I29: 10 | J29: 10
A30: Days payable outstanding (DPO) | B30: =BS!C21/IS!B20*365 -> 93.851071 | C30: =BS!D21/IS!C20*365 -> 104.68528 | D30: =BS!E21/IS!D20*365 -> 106.72147 | E30: =BS!F21/IS!E20*365 -> 119.65848 | F30: =BS!G21/IS!F20*365 -> 115.40052 | G30: 115 | H30: 115 | I30: 115 | J30: 115
A32: Share-based compensation as % of revenue | B32: =CFS!B12/IS!B14 -> 0.021611899 | C32: =CFS!C12/IS!C14 -> 0.022920006 | D32: =CFS!D12/IS!D14 -> 0.028263564 | E32: =CFS!E12/IS!E14 -> 0.029889908 | F32: =CFS!F12/IS!F14 -> 0.030908711 | G32: 0.031 | H32: 0.031 | I32: 0.031 | J32: 0.031
A33: Other current liabilities as % of revenue | B33: =BS!C22/IS!B14 -> 0.12982721 | C33: =BS!D22/IS!C14 -> 0.15430048 | D33: =BS!E22/IS!D14 -> 0.15348631 | E33: =BS!F22/IS!E14 -> 0.20024806 | F33: =BS!G22/IS!F14 -> 0.1957824 | G33: 0.17 | H33: 0.17 | I33: 0.17 | J33: 0.17
A34: Deferred revenue as % of services revenue | B34: =BS!C23/IS!B13 -> 0.11124589 | C34: =BS!D23/IS!C13 -> 0.10126842 | D34: =BS!E23/IS!D13 -> 0.094612676 | E34: =BS!F23/IS!E13 -> 0.085776082 | F34: =BS!G23/IS!F13 -> 0.075569358 | G34: 0.078 | H34: 0.078 | I34: 0.078 | J34: 0.078
A35: Vendor non-trade receivables as % of COGS | B35: =BS!C9/IS!B20 -> 0.11845188 | C35: =BS!D9/IS!C20 -> 0.14649334 | D35: =BS!E9/IS!D20 -> 0.14699468 | E35: =BS!F9/IS!E20 -> 0.15608599 | F35: =BS!G9/IS!F20 -> 0.12874728 | G35: 0.135 | H35: 0.135 | I35: 0.135 | J35: 0.135
A36: CAPEX & DEPRECIATION DRIVERS
A37: CapEx as % of revenue | B37: =-CFS!B19/IS!B14 -> 0.030302036 | C37: =-CFS!C19/IS!C14 -> 0.027155059 | D37: =-CFS!D19/IS!D14 -> 0.028592301 | E37: =-CFS!E19/IS!E14 -> 0.024158963 | F37: =-CFS!F19/IS!F14 -> 0.030553079 | G37: =CHOOSE(MATCH(Scenario,{"Bear","Base","Bull"},0),$B$76,$C$76,$D$76) -> 0.022 | H37: =CHOOSE(MATCH(Scenario,{"Bear","Base","Bull"},0),$B$76,$C$76,$D$76) -> 0.022 | I37: =CHOOSE(MATCH(Scenario,{"Bear","Base","Bull"},0),$B$76,$C$76,$D$76) -> 0.022 | J37: =CHOOSE(MATCH(Scenario,{"Bear","Base","Bull"},0),$B$76,$C$76,$D$76) -> 0.022
A38: Depreciation & amortization, $M | B38: =CFS!B10 -> 11284 | C38: =CFS!C10 -> 11104 | D38: =CFS!D10 -> 11519 | E38: =CFS!E10 -> 11445 | F38: =CFS!F10 -> 11698 | G38: =CHOOSE(MATCH(Scenario,{"Bear","Base","Bull"},0),$B$84,$C$84,$D$84)*IS!G14 -> 11256.431 | H38: =CHOOSE(MATCH(Scenario,{"Bear","Base","Bull"},0),$B$84,$C$84,$D$84)*IS!H14 -> 12191.543 | I38: =CHOOSE(MATCH(Scenario,{"Bear","Base","Bull"},0),$B$84,$C$84,$D$84)*IS!I14 -> 13218.694 | J38: =CHOOSE(MATCH(Scenario,{"Bear","Base","Bull"},0),$B$84,$C$84,$D$84)*IS!J14 -> 14348.381
A40: CAPITAL RETURN POLICY | Per Apple's Stated Plan
A41: Capital return as % of FCF | B41: =(-CFS!B24-CFS!B25)/CFS!B21 -> 1.0805246 | C41: =(-CFS!C24-CFS!C25)/CFS!C21 -> 0.93539298 | D41: =(-CFS!D24-CFS!D25)/CFS!D21 -> 0.92961721 | E41: =(-CFS!E24-CFS!E25)/CFS!E21 -> 1.0126462 | F41: =(-CFS!F24-CFS!F25)/CFS!F21 -> 1.0745694 | G41: =CHOOSE(MATCH(Scenario,{"Bear","Base","Bull"},0),$B$81,$C$81,$D$81) -> 1.05 | H41: =CHOOSE(MATCH(Scenario,{"Bear","Base","Bull"},0),$B$81,$C$81,$D$81) -> 1.05 | I41: =CHOOSE(MATCH(Scenario,{"Bear","Base","Bull"},0),$B$81,$C$81,$D$81) -> 1.05 | J41: =CHOOSE(MATCH(Scenario,{"Bear","Base","Bull"},0),$B$81,$C$81,$D$81) -> 1.05
A42: Dividends as % of capital return | B42: =-CFS!B24/(-CFS!B24-CFS!B25) -> 0.14403911 | C42: =-CFS!C24/(-CFS!C24-CFS!C25) -> 0.14236927 | D42: =-CFS!D24/(-CFS!D24-CFS!D25) -> 0.16230084 | E42: =-CFS!E24/(-CFS!E24-CFS!E25) -> 0.13826089 | F42: =-CFS!F24/(-CFS!F24-CFS!F25) -> 0.14530019 | G42: =CHOOSE(MATCH(Scenario,{"Bear","Base","Bull"},0),$B$82,$C$82,$D$82) -> 0.12 | H42: =CHOOSE(MATCH(Scenario,{"Bear","Base","Bull"},0),$B$82,$C$82,$D$82) -> 0.12 | I42: =CHOOSE(MATCH(Scenario,{"Bear","Base","Bull"},0),$B$82,$C$82,$D$82) -> 0.12 | J42: =CHOOSE(MATCH(Scenario,{"Bear","Base","Bull"},0),$B$82,$C$82,$D$82) -> 0.12
A44: WACC & DCF VALUATION INPUTS
A45: Risk-free rate | B45: =CHOOSE(MATCH(Scenario,{"Bear","Base","Bull"},0),$B$79,$C$79,$D$79) -> 0.04
A46: Equity risk premium | B46: =CHOOSE(MATCH(Scenario,{"Bear","Base","Bull"},0),$B$80,$C$80,$D$80) -> 0.045
A47: Beta (Apple) | B47: =CHOOSE(MATCH(Scenario,{"Bear","Base","Bull"},0),$B$77,$C$77,$D$77) -> 0.95
A48: Cost of equity | B48: =B45+B47*B46 -> 0.08275
A49: Pre-tax cost of debt | B49: 0.04
A50: Tax rate (for WACC) | B50: 0.15
A51: After-tax cost of debt | B51: =B49*(1-B50) -> 0.034
A52: Target debt / capital | B52: 0.1
A53: Target equity / capital | B53: =1-B52 -> 0.9
A54: WACC | B54: =B48*B53+B51*B52 -> 0.077875
A55: Terminal growth rate (g) | B55: =CHOOSE(MATCH(Scenario,{"Bear","Base","Bull"},0),$B$78,$C$78,$D$78) -> 0.03
A57: VALUATION INPUTS
A58: Diluted shares outstanding (M) | B58: 15004.7
A59: Current share price (USD) | B59: 232.5
A61: SCENARIO ENGINE | Forecast Case Toggle
A62: Active scenario → | B62: Bull | C62: ← Change this dropdown. All FY26–FY28 drivers update; IS/BS/CFS/DCF/Dashboard re-flow.
A64: Driver | B64: Bear | C64: Base | D64: Bull | E64: Unit | F64: Notes
A65: Products revenue growth (avg) | B65: =(IS!$F$9*(1+B66)+IS!$F$10*(1+B67)+IS!$F$11*(1+B68)+IS!$F$12*(1+B69))/IS!$F$8-1 -> -0.0042792416 | C65: =(IS!$F$9*(1+C66)+IS!$F$10*(1+C67)+IS!$F$11*(1+C68)+IS!$F$12*(1+C69))/IS!$F$8-1 -> 0.030120748 | D65: =(IS!$F$9*(1+D66)+IS!$F$10*(1+D67)+IS!$F$11*(1+D68)+IS!$F$12*(1+D69))/IS!$F$8-1 -> 0.061283147 | E65: % | F65: Applied to G8:I8 (per-year overrides preserved as Base values)
A66: iPhone YoY growth | B66: 0 | C66: 0.03 | D66: 0.06 | E66: %
A67: Mac YoY growth | B67: 0.02 | C67: 0.05 | D67: 0.08 | E67: %
A68: iPad YoY growth | B68: -0.02 | C68: 0.02 | D68: 0.05 | E68: %
A69: Wearables YoY growth | B69: -0.04 | C69: 0.02 | D69: 0.06 | E69: %
A70: Services revenue growth (avg) | B70: 0.06 | C70: 0.105 | D70: 0.14 | E70: % | F70: Applied to G9:I9
A71: Products gross margin (avg) | B71: 0.36 | C71: 0.385 | D71: 0.405 | E71: % | F71: Applied to G12:I12
A72: Services gross margin (avg) | B72: 0.74 | C72: 0.76 | D72: 0.78 | E72: % | F72: Applied to G13:I13
A73: R&D expense growth | B73: 0.1 | C73: 0.075 | D73: 0.05 | E73: % | F73: Applied to G16:I16 (Bear = higher spend)
A74: SG&A expense growth | B74: 0.07 | C74: 0.045 | D74: 0.03 | E74: % | F74: Applied to G17:I17
A75: Effective tax rate | B75: 0.18 | C75: 0.15 | D75: 0.13 | E75: % | F75: Applied to G21:I21
A76: CapEx % of revenue | B76: 0.035 | C76: 0.028 | D76: 0.022 | E76: % | F76: Applied to G29:I29
A77: Beta | B77: 1.25 | C77: 1.1 | D77: 0.95 | E77: x | F77: Drives WACC at B39
A78: Terminal growth rate (g) | B78: 0.02 | C78: 0.025 | D78: 0.03 | E78: % | F78: Drives DCF terminal at B47
A79: Risk-free rate | B79: 0.05 | C79: 0.045 | D79: 0.04 | E79: % | F79: Drives WACC at B37
A80: Equity risk premium | B80: 0.055 | C80: 0.05 | D80: 0.045 | E80: % | F80: Drives WACC at B38
A81: Capital return as % of FCF | B81: 0.85 | C81: 0.95 | D81: 1.05 | E81: %
A82: Dividends as % of capital return | B82: 0.18 | C82: 0.15 | D82: 0.12 | E82: %
A83: Other income $M | B83: -500 | C83: 0 | D83: 500 | E83: $M
A84: D&A as % of revenue | B84: 0.032 | C84: 0.028 | D84: 0.025 | E84: %
A86: BS STRUCTURAL & DEBT SCHEDULE | Scenario-Flexed Inputs
A87: Driver | B87: FY26E Bear | C87: FY26E Base | D87: FY26E Bull | E87: FY27E Bear | F87: FY27E Base | G87: FY27E Bull | H87: FY28E Bear | I87: FY28E Base | J87: FY28E Bull | K87: FY29E Bear | L87: FY29E Base | M87: FY29E Bull
A88: Short-term marketable securities | B88: 42000 | C88: 40000 | D88: 38000 | E88: 44000 | F88: 42000 | G88: 40000 | H88: 46000 | I88: 44000 | J88: 42000 | K88: 46000 | L88: 44000 | M88: 42000
A89: Other current assets | B89: -9000 | C89: -9200 | D89: -9400 | E89: -9500 | F89: -9700 | G89: -9900 | H89: -10200 | I89: -10400 | J89: -10600 | K89: -10200 | L89: -10400 | M89: -10600
A90: Other non-current assets | B90: 116000 | C90: 117000 | D90: 118000 | E90: 123000 | F90: 124000 | G90: 125000 | H90: 130000 | I90: 131000 | J90: 132000 | K90: 130000 | L90: 131000 | M90: 132000
A91: Commercial paper | B91: -1500 | C91: -2800 | D91: -4000 | E91: -1000 | F91: -2100 | G91: -3300 | H91: -2200 | I91: -3400 | J91: -4500 | K91: -2200 | L91: -3400 | M91: -4500
A92: Current portion of LT debt | B92: 2500 | C92: 2000 | D92: 1500 | E92: 500 | F92: 0 | G92: 0 | H92: 500 | I92: 0 | J92: 0 | K92: 500 | L92: 0 | M92: 0
A93: Long-term debt | B93: 70000 | C93: 65000 | D93: 60000 | E93: 60000 | F93: 55000 | G93: 50000 | H93: 50000 | I93: 45000 | J93: 40000 | K93: 50000 | L93: 45000 | M93: 40000
A94: Other non-current liabilities | B94: 33000 | C94: 32000 | D94: 31000 | E94: 32000 | F94: 31000 | G94: 30000 | H94: 31000 | I94: 30000 | J94: 29000 | K94: 31000 | L94: 30000 | M94: 29000
A95: Accumulated other comp. inc/(loss) | B95: 200 | C95: 157 | D95: 100 | E95: 200 | F95: 149 | G95: 80 | H95: 200 | I95: 137 | J95: 60 | K95: 200 | L95: 137 | M95: 60

Sheet IS
A1: INCOME STATEMENT | FY2021A – FY2029E
A2: Top-down build: segment revenue × segment GM → gross profit → OpEx → operating income → net income
A4: USD Millions | B4: FY2021A | C4: FY2022A | D4: FY2023A | E4: FY2024A | F4: FY2025A | G4: FY2026E | H4: FY2027E | I4: FY2028E | J4: FY2029E
B5: Sep 25, 2021 | C5: Sep 24, 2022 | D5: Sep 30, 2023 | E5: Sep 28, 2024 | F5: Sep 27, 2025 | G5: Sep 26, 2026 | H5: Sep 25, 2027 | I5: Sep 30, 2028 | J5: Sep 30, 2029
A7: REVENUE
A8: Products revenue | B8: 297392 | C8: 316199 | D8: 298085 | E8: 294866 | F8: 307003 | G8: =SUM(G9:G12) -> 325817.11 | H8: =SUM(H9:H12) -> 345799.99 | I8: =SUM(I9:I12) -> 367025.37 | J8: =SUM(J9:J12) -> 389571.74
A9: iPhone | B9: 191973 | C9: 205489 | D9: 200583 | E9: 201183 | F9: 209586 | G9: =F9*(1+Assumptions!G9) -> 222161.16 | H9: =G9*(1+Assumptions!H9) -> 235490.83 | I9: =H9*(1+Assumptions!I9) -> 249620.28 | J9: =I9*(1+Assumptions!J9) -> 264597.5
A10: Mac | B10: 35190 | C10: 40177 | D10: 29357 | E10: 29984 | F10: 33708 | G10: =F10*(1+Assumptions!G10) -> 36404.64 | H10: =G10*(1+Assumptions!H10) -> 39317.011 | I10: =H10*(1+Assumptions!I10) -> 42462.372 | J10: =I10*(1+Assumptions!J10) -> 45859.362
A11: iPad | B11: 31862 | C11: 29292 | D11: 28300 | E11: 26694 | F11: 28023 | G11: =F11*(1+Assumptions!G11) -> 29424.15 | H11: =G11*(1+Assumptions!H11) -> 30895.358 | I11: =H11*(1+Assumptions!I11) -> 32440.125 | J11: =I11*(1+Assumptions!J11) -> 34062.132
A12: Wearables, Home & Accessories | B12: 38367 | C12: 41241 | D12: 39845 | E12: 37005 | F12: 35686 | G12: =F12*(1+Assumptions!G12) -> 37827.16 | H12: =G12*(1+Assumptions!H12) -> 40096.79 | I12: =H12*(1+Assumptions!I12) -> 42502.597 | J12: =I12*(1+Assumptions!J12) -> 45052.753
A13: Services revenue | B13: 68425 | C13: 78129 | D13: 85200 | E13: 96169 | F13: 109158 | G13: =F13*(1+Assumptions!G13) -> 124440.12 | H13: =G13*(1+Assumptions!H13) -> 141861.74 | I13: =H13*(1+Assumptions!I13) -> 161722.38 | J13: =I13*(1+Assumptions!J13) -> 184363.51
A14: Total revenue | B14: =SUM(B9:B13) -> 365817 | C14: =SUM(C9:C13) -> 394328 | D14: =SUM(D9:D13) -> 383285 | E14: =SUM(E9:E13) -> 391035 | F14: =SUM(F9:F13) -> 416161 | G14: =SUM(G9:G13) -> 450257.23 | H14: =SUM(H9:H13) -> 487661.72 | I14: =SUM(I9:I13) -> 528747.75 | J14: =SUM(J9:J13) -> 573935.26
A15: YoY Revenue Growth | B15: - | C15: =(C14-B14)/B14 -> 0.077937876 | D15: =(D14-C14)/C14 -> -0.028004605 | E15: =(E14-D14)/D14 -> 0.020219941 | F15: =(F14-E14)/E14 -> 0.064255118 | G15: =(G14-F14)/F14 -> 0.081930383 | H15: =(H14-G14)/G14 -> 0.083073613 | I15: =(I14-H14)/H14 -> 0.084251084 | J15: =(J14-I14)/I14 -> 0.085461359
A17: COST OF SALES
A18: Cost of products | B18: 192266 | C18: 201471 | D18: 189282 | E18: 185233 | F18: 194116 | G18: =G8*(1-Assumptions!G16) -> 193861.18 | H18: =H8*(1-Assumptions!H16) -> 205750.99 | I18: =I8*(1-Assumptions!I16) -> 218380.1 | J18: =J8*(1-Assumptions!J16) -> 231795.19
A19: Cost of services | B19: 20715 | C19: 22075 | D19: 24855 | E19: 25119 | F19: 26844 | G19: =G13*(1-Assumptions!G17) -> 27376.826 | H19: =H13*(1-Assumptions!H17) -> 31209.582 | I19: =I13*(1-Assumptions!I17) -> 35578.924 | J19: =J13*(1-Assumptions!J17) -> 40559.973
A20: Total cost of sales | B20: =SUM(B18:B19) -> 212981 | C20: =SUM(C18:C19) -> 223546 | D20: =SUM(D18:D19) -> 214137 | E20: =SUM(E18:E19) -> 210352 | F20: =SUM(F18:F19) -> 220960 | G20: =SUM(G18:G19) -> 221238.01 | H20: =SUM(H18:H19) -> 236960.57 | I20: =SUM(I18:I19) -> 253959.02 | J20: =SUM(J18:J19) -> 272355.16
A21: Gross profit | B21: =B14-B20 -> 152836 | C21: =C14-C20 -> 170782 | D21: =D14-D20 -> 169148 | E21: =E14-E20 -> 180683 | F21: =F14-F20 -> 195201 | G21: =G14-G20 -> 229019.22 | H21: =H14-H20 -> 250701.15 | I21: =I14-I20 -> 274788.73 | J21: =J14-J20 -> 301580.1
A22: Gross margin % | B22: =B21/B14 -> 0.4177936 | C22: =C21/C14 -> 0.43309631 | D22: =D21/D14 -> 0.4413113 | E22: =E21/E14 -> 0.4620635 | F22: =F21/F14 -> 0.46905164 | G22: =G21/G14 -> 0.50864086 | H22: =H21/H14 -> 0.51408822 | I22: =I21/I14 -> 0.51969721 | J22: =J21/J14 -> 0.52546013
A24: OPERATING EXPENSES
A25: Research & development | B25: 21914 | C25: 26251 | D25: 29915 | E25: 31370 | F25: 34550 | G25: =F25*(1+Assumptions!G20) -> 36277.5 | H25: =G25*(1+Assumptions!H20) -> 38091.375 | I25: =H25*(1+Assumptions!I20) -> 39995.944 | J25: =I25*(1+Assumptions!J20) -> 41995.741
A26: Selling, general & administrative | B26: 21973 | C26: 25094 | D26: 24932 | E26: 26097 | F26: 27601 | G26: =F26*(1+Assumptions!G21) -> 28429.03 | H26: =G26*(1+Assumptions!H21) -> 29281.901 | I26: =H26*(1+Assumptions!I21) -> 30160.358 | J26: =I26*(1+Assumptions!J21) -> 31065.169
A27: Total operating expenses | B27: =SUM(B25:B26) -> 43887 | C27: =SUM(C25:C26) -> 51345 | D27: =SUM(D25:D26) -> 54847 | E27: =SUM(E25:E26) -> 57467 | F27: =SUM(F25:F26) -> 62151 | G27: =SUM(G25:G26) -> 64706.53 | H27: =SUM(H25:H26) -> 67373.276 | I27: =SUM(I25:I26) -> 70156.302 | J27: =SUM(J25:J26) -> 73060.91
A28: Operating income | B28: =B21-B27 -> 108949 | C28: =C21-C27 -> 119437 | D28: =D21-D27 -> 114301 | E28: =E21-E27 -> 123216 | F28: =F21-F27 -> 133050 | G28: =G21-G27 -> 164312.69 | H28: =H21-H27 -> 183327.87 | I28: =I21-I27 -> 204632.43 | J28: =J21-J27 -> 228519.19
A29: Operating margin % | B29: =B28/B14 -> 0.29782378 | C29: =C28/C14 -> 0.30288744 | D29: =D28/D14 -> 0.29821412 | E29: =E28/E14 -> 0.31510223 | F29: =F28/F14 -> 0.319708 | G29: =G28/G14 -> 0.36493072 | H29: =H28/H14 -> 0.37593246 | I29: =I28/I14 -> 0.38701333 | J29: =J28/J14 -> 0.39816196
A30: (+) Depreciation & Amortization | B30: 11284 | C30: 11104 | D30: 11519 | E30: 11445 | F30: 11698 | G30: =Assumptions!G38 -> 11256.431 | H30: =Assumptions!H38 -> 12191.543 | I30: =Assumptions!I38 -> 13218.694 | J30: =Assumptions!J38 -> 14348.381
A31: EBITDA | B31: =B28+B30 -> 120233 | C31: =C28+C30 -> 130541 | D31: =D28+D30 -> 125820 | E31: =E28+E30 -> 134661 | F31: =F28+F30 -> 144748 | G31: =G28+G30 -> 175569.12 | H31: =H28+H30 -> 195519.42 | I31: =I28+I30 -> 217851.12 | J31: =J28+J30 -> 242867.57
A32: EBITDA Margin % | B32: =B31/B14 -> 0.3286698 | C32: =C31/C14 -> 0.33104674 | D32: =D31/D14 -> 0.32826748 | E32: =E31/E14 -> 0.34437071 | F32: =F31/F14 -> 0.34781731 | G32: =G31/G14 -> 0.38993072 | H32: =H31/H14 -> 0.40093246 | I32: =I31/I14 -> 0.41201333 | J32: =J31/J14 -> 0.42316196
A33: NON-OPERATING & TAXES
A34: Other income / (expense), net | B34: 258 | C34: -334 | D34: -565 | E34: 269 | F34: -321 | G34: =Assumptions!G24 -> 500 | H34: =Assumptions!H24 -> 500 | I34: =Assumptions!I24 -> 500 | J34: =Assumptions!J24 -> 500
A35: Pre-tax income | B35: =B28+B34 -> 109207 | C35: =C28+C34 -> 119103 | D35: =D28+D34 -> 113736 | E35: =E28+E34 -> 123485 | F35: =F28+F34 -> 132729 | G35: =G28+G34 -> 164812.69 | H35: =H28+H34 -> 183827.87 | I35: =I28+I34 -> 205132.43 | J35: =J28+J34 -> 229019.19
A36: Income tax expense | B36: 14527 | C36: 19300 | D36: 16741 | E36: 29749 | F36: 20719 | G36: =G35*Assumptions!G25 -> 21425.65 | H36: =H35*Assumptions!H25 -> 23897.624 | I36: =I35*Assumptions!I25 -> 26667.216 | J36: =J35*Assumptions!J25 -> 29772.494
A37: Effective tax rate | B37: =B36/B35 -> 0.13302261 | C37: =C36/C35 -> 0.16204462 | D37: =D36/D35 -> 0.14719174 | E37: =E36/E35 -> 0.24091185 | F37: =F36/F35 -> 0.15610002 | G37: =G36/G35 -> 0.13 | H37: =H36/H35 -> 0.13 | I37: =I36/I35 -> 0.13 | J37: =J36/J35 -> 0.13
A38: NET INCOME | B38: =B35-B36 -> 94680 | C38: =C35-C36 -> 99803 | D38: =D35-D36 -> 96995 | E38: =E35-E36 -> 93736 | F38: =F35-F36 -> 112010 | G38: =G35-G36 -> 143387.04 | H38: =H35-H36 -> 159930.25 | I38: =I35-I36 -> 178465.22 | J38: =J35-J36 -> 199246.69
A39: Net margin % | B39: =B38/B14 -> 0.25881793 | C39: =C38/C14 -> 0.25309641 | D39: =D38/D14 -> 0.25306234 | E39: =E38/E14 -> 0.23971256 | F39: =F38/F14 -> 0.26915064 | G39: =G38/G14 -> 0.31845584 | H39: =H38/H14 -> 0.32795326 | I39: =I38/I14 -> 0.3375243 | J39: =J38/J14 -> 0.34715883
A41: PER SHARE DATA
A42: Basic EPS ($) | B42: 5.67 | C42: 6.15 | D42: 6.16 | E42: 6.11 | F42: 7.5 | G42: =G38/G44 -> 9.9358043 | H42: =H38/H44 -> 11.585546 | I42: =I38/I44 -> 13.70132 | J42: =J38/J44 -> 16.436705
A43: Diluted EPS ($) | B43: 5.61 | C43: 6.11 | D43: 6.13 | E43: 6.08 | F43: 7.46 | G43: =G38/G44 -> 9.9358043 | H43: =H38/H44 -> 11.585546 | I43: =I38/I44 -> 13.70132 | J43: =J38/J44 -> 16.436705
A44: Diluted shares outstanding (M) | B44: 16864 | C44: 16326 | D44: 15813 | E44: 15409 | F44: 15004 | G44: =F44+CFS!G25/Assumptions!$B$59 -> 14431.347 | H44: =G44+CFS!H25/Assumptions!$B$59 -> 13804.291 | I44: =H44+CFS!I25/Assumptions!$B$59 -> 13025.403 | J44: =I44+CFS!J25/Assumptions!$B$59 -> 12122.058
A45: Dividend per share ($) | B45: 0.85 | C45: 0.91 | D45: 0.95 | E45: 0.99 | F45: 1.06 | G45: =-CFS!G24/G44 -> 1.2580732 | H45: =-CFS!H24/H44 -> 1.4401708 | I45: =-CFS!I24/I44 -> 1.8958551 | J45: =-CFS!J24/J44 -> 2.3626488
A50: REVENUE BY GEOGRAPHIC SEGMENT | L50: Fcst growth
A52: Americas | B52: 153306 | C52: 169658 | D52: 162560 | E52: 167045 | F52: 178353 | G52: =$F52*(1+$L52)*IS!G$14/($F52*(1+$L52)+$F53*(1+$L53)+$F54*(1+$L54)+$F55*(1+$L55)+$F56*(1+$L56)) -> 193670.51 | H52: =G52*(1+$L52)*IS!H$14/(G52*(1+$L52)+G53*(1+$L53)+G54*(1+$L54)+G55*(1+$L55)+G56*(1+$L56)) -> 210383.53 | I52: =H52*(1+$L52)*IS!I$14/(H52*(1+$L52)+H53*(1+$L53)+H54*(1+$L54)+H55*(1+$L55)+H56*(1+$L56)) -> 228639.63 | J52: =I52*(1+$L52)*IS!J$14/(I52*(1+$L52)+I53*(1+$L53)+I54*(1+$L54)+I55*(1+$L55)+I56*(1+$L56)) -> 248604.07 | L52: 0.045
A53: Europe | B53: 89307 | C53: 95118 | D53: 94294 | E53: 101328 | F53: 111032 | G53: =$F53*(1+$L53)*IS!G$14/($F52*(1+$L52)+$F53*(1+$L53)+$F54*(1+$L54)+$F55*(1+$L55)+$F56*(1+$L56)) -> 122298.41 | H53: =G53*(1+$L53)*IS!H$14/(G52*(1+$L52)+G53*(1+$L53)+G54*(1+$L54)+G55*(1+$L55)+G56*(1+$L56)) -> 134759.27 | I53: =H53*(1+$L53)*IS!I$14/(H52*(1+$L52)+H53*(1+$L53)+H54*(1+$L54)+H55*(1+$L55)+H56*(1+$L56)) -> 148555.24 | J53: =I53*(1+$L53)*IS!J$14/(I52*(1+$L52)+I53*(1+$L53)+I54*(1+$L54)+I55*(1+$L55)+I56*(1+$L56)) -> 163845.41 | L53: 0.06
A54: Greater China | B54: 68366 | C54: 74200 | D54: 72559 | E54: 66952 | F54: 64377 | G54: =$F54*(1+$L54)*IS!G$14/($F52*(1+$L52)+$F53*(1+$L53)+$F54*(1+$L54)+$F55*(1+$L55)+$F56*(1+$L56)) -> 65557.684 | H54: =G54*(1+$L54)*IS!H$14/(G52*(1+$L52)+G53*(1+$L53)+G54*(1+$L54)+G55*(1+$L55)+G56*(1+$L56)) -> 66785.415 | I54: =H54*(1+$L54)*IS!I$14/(H52*(1+$L52)+H53*(1+$L53)+H54*(1+$L54)+H55*(1+$L55)+H56*(1+$L56)) -> 68066.15 | J54: =I54*(1+$L54)*IS!J$14/(I52*(1+$L52)+I53*(1+$L53)+I54*(1+$L54)+I55*(1+$L55)+I56*(1+$L56)) -> 69406.108 | L54: -0.02
A55: Japan | B55: 28482 | C55: 25977 | D55: 24257 | E55: 25052 | F55: 28703 | G55: =$F55*(1+$L55)*IS!G$14/($F52*(1+$L52)+$F53*(1+$L53)+$F54*(1+$L54)+$F55*(1+$L55)+$F56*(1+$L56)) -> 31615.492 | H55: =G55*(1+$L55)*IS!H$14/(G52*(1+$L52)+G53*(1+$L53)+G54*(1+$L54)+G55*(1+$L55)+G56*(1+$L56)) -> 34836.761 | I55: =H55*(1+$L55)*IS!I$14/(H52*(1+$L52)+H53*(1+$L53)+H54*(1+$L54)+H55*(1+$L55)+H56*(1+$L56)) -> 38403.173 | J55: =I55*(1+$L55)*IS!J$14/(I52*(1+$L52)+I53*(1+$L53)+I54*(1+$L54)+I55*(1+$L55)+I56*(1+$L56)) -> 42355.85 | L55: 0.06
A56: Rest of Asia Pacific | B56: 26356 | C56: 29375 | D56: 29615 | E56: 30658 | F56: 33696 | G56: =$F56*(1+$L56)*IS!G$14/($F52*(1+$L52)+$F53*(1+$L53)+$F54*(1+$L54)+$F55*(1+$L55)+$F56*(1+$L56)) -> 37115.132 | H56: =G56*(1+$L56)*IS!H$14/(G52*(1+$L52)+G53*(1+$L53)+G54*(1+$L54)+G55*(1+$L55)+G56*(1+$L56)) -> 40896.752 | I56: =H56*(1+$L56)*IS!I$14/(H52*(1+$L52)+H53*(1+$L53)+H54*(1+$L54)+H55*(1+$L55)+H56*(1+$L56)) -> 45083.556 | J56: =I56*(1+$L56)*IS!J$14/(I52*(1+$L52)+I53*(1+$L53)+I54*(1+$L54)+I55*(1+$L55)+I56*(1+$L56)) -> 49723.818 | L56: 0.06
A57: Total revenue | B57: =SUM(B52:B56) -> 365817 | C57: =SUM(C52:C56) -> 394328 | D57: =SUM(D52:D56) -> 383285 | E57: =SUM(E52:E56) -> 391035 | F57: =SUM(F52:F56) -> 416161 | G57: =SUM(G52:G56) -> 450257.23 | H57: =SUM(H52:H56) -> 487661.72 | I57: =SUM(I52:I56) -> 528747.75 | J57: =SUM(J52:J56) -> 573935.26
A58: Check vs Total revenue (row 10) | B58: =B57-B14 -> 0 | C58: =C57-C14 -> 0 | D58: =D57-D14 -> 0 | E58: =E57-E14 -> 0 | F58: =F57-F14 -> 0 | G58: =G57-G14 -> 0 | H58: =H57-H14 -> 0 | I58: =I57-I14 -> 0 | J58: =J57-J14 -> 0
A60: % of total revenue
A61: Americas | B61: =B52/B57 -> 0.41907839 | C61: =C52/C57 -> 0.43024589 | D61: =D52/D57 -> 0.42412304 | E61: =E52/E57 -> 0.42718682 | F61: =F52/F57 -> 0.42856731 | G61: =G52/G57 -> 0.43013304 | H61: =H52/H57 -> 0.43141284 | I61: =I52/I57 -> 0.43241722 | J61: =J52/J57 -> 0.43315699
A62: Europe | B62: =B53/B57 -> 0.24413026 | C62: =C53/C57 -> 0.24121543 | D62: =D53/D57 -> 0.24601537 | E62: =E53/E57 -> 0.2591277 | F62: =F53/F57 -> 0.26680059 | G62: =G53/G57 -> 0.27161899 | H62: =H53/H57 -> 0.27633759 | I62: =I53/I57 -> 0.28095673 | J62: =J53/J57 -> 0.28547716
A63: Greater China | B63: =B54/B57 -> 0.18688579 | C63: =C54/C57 -> 0.18816823 | D63: =D54/D57 -> 0.18930822 | E63: =E54/E57 -> 0.17121741 | F63: =F54/F57 -> 0.15469253 | G63: =G54/G57 -> 0.14560051 | H63: =H54/H57 -> 0.13695029 | I63: =I54/I57 -> 0.12873085 | J63: =J54/J57 -> 0.1209302
A64: Japan | B64: =B55/B57 -> 0.077858601 | C64: =C55/C57 -> 0.065876631 | D64: =D55/D57 -> 0.06328711 | E64: =E55/E57 -> 0.064065876 | F64: =F55/F57 -> 0.068970903 | G64: =G55/G57 -> 0.070216512 | H64: =H55/H57 -> 0.071436323 | I64: =I55/I57 -> 0.072630423 | J64: =J55/J57 -> 0.073799004
A65: Rest of Asia Pacific | B65: =B56/B57 -> 0.072046952 | C65: =C56/C57 -> 0.074493822 | D65: =D56/D57 -> 0.077266264 | E65: =E56/E57 -> 0.078402189 | F65: =F56/F57 -> 0.080968664 | G65: =G56/G57 -> 0.082430951 | H65: =H56/H57 -> 0.083862953 | I65: =I56/I57 -> 0.085264772 | J65: =J56/J57 -> 0.086636632
A67: Revenue YoY growth
A68: Americas | C68: =C52/B52-1 -> 0.10666249 | D68: =D52/C52-1 -> -0.041837108 | E68: =E52/D52-1 -> 0.027589813 | F68: =F52/E52-1 -> 0.067694334 | G68: =G52/F52-1 -> 0.085883114 | H68: =H52/G52-1 -> 0.086296156 | I68: =I52/H52-1 -> 0.086775332 | J68: =J52/I52-1 -> 0.08731836
A69: Europe | C69: =C53/B53-1 -> 0.065067688 | D69: =D53/C53-1 -> -0.0086629239 | E69: =E53/D53-1 -> 0.074596475 | F69: =F53/E53-1 -> 0.095768198 | G69: =G53/F53-1 -> 0.10146995 | H69: =H53/G53-1 -> 0.10188892 | I69: =I53/H53-1 -> 0.10237498 | J69: =J53/I53-1 -> 0.1029258
A70: Greater China | C70: =C54/B54-1 -> 0.085334816 | D70: =D54/C54-1 -> -0.022115903 | E70: =E54/D54-1 -> -0.077275045 | F70: =F54/E54-1 -> -0.03846039 | G70: =G54/F54-1 -> 0.018340145 | H70: =H54/G54-1 -> 0.018727496 | I70: =I54/H54-1 -> 0.019176866 | J70: =J54/I54-1 -> 0.019686118
A71: Japan | C71: =C55/B55-1 -> -0.087950284 | D71: =D55/C55-1 -> -0.066212419 | E71: =E55/D55-1 -> 0.032774045 | F71: =F55/E55-1 -> 0.14573687 | G71: =G55/F55-1 -> 0.10146995 | H71: =H55/G55-1 -> 0.10188892 | I71: =I55/H55-1 -> 0.10237498 | J71: =J55/I55-1 -> 0.1029258
A72: Rest of Asia Pacific | C72: =C56/B56-1 -> 0.11454697 | D72: =D56/C56-1 -> 0.0081702128 | E72: =E56/D56-1 -> 0.035218639 | F72: =F56/E56-1 -> 0.099093222 | G72: =G56/F56-1 -> 0.10146995 | H72: =H56/G56-1 -> 0.10188892 | I72: =I56/H56-1 -> 0.10237498 | J72: =J56/I56-1 -> 0.1029258
A74: GROSS MARGIN DETAIL | By Segment
A76: Products gross profit | B76: =B8-B18 -> 105126 | C76: =C8-C18 -> 114728 | D76: =D8-D18 -> 108803 | E76: =E8-E18 -> 109633 | F76: =F8-F18 -> 112887 | G76: =G8-G18 -> 131955.93 | H76: =H8-H18 -> 140049 | I76: =I8-I18 -> 148645.28 | J76: =J8-J18 -> 157776.56
A77: Products gross margin % | B77: =B76/B8 -> 0.35349303 | C77: =C76/C8 -> 0.3628348 | D77: =D76/D8 -> 0.36500663 | E77: =E76/E8 -> 0.37180618 | F77: =F76/F8 -> 0.3677065 | G77: =G76/G8 -> 0.405 | H77: =H76/H8 -> 0.405 | I77: =I76/I8 -> 0.405 | J77: =J76/J8 -> 0.405
A78: Services gross profit | B78: =B13-B19 -> 47710 | C78: =C13-C19 -> 56054 | D78: =D13-D19 -> 60345 | E78: =E13-E19 -> 71050 | F78: =F13-F19 -> 82314 | G78: =G13-G19 -> 97063.294 | H78: =H13-H19 -> 110652.15 | I78: =I13-I19 -> 126143.46 | J78: =J13-J19 -> 143803.54
A79: Services gross margin % | B79: =B78/B13 -> 0.69725977 | C79: =C78/C13 -> 0.71745447 | D79: =D78/D13 -> 0.70827465 | E79: =E78/E13 -> 0.73880356 | F79: =F78/F13 -> 0.75408124 | G79: =G78/G13 -> 0.78 | H79: =H78/H13 -> 0.78 | I79: =I78/I13 -> 0.78 | J79: =J78/J13 -> 0.78
A80: Total gross profit | B80: =B76+B78 -> 152836 | C80: =C76+C78 -> 170782 | D80: =D76+D78 -> 169148 | E80: =E76+E78 -> 180683 | F80: =F76+F78 -> 195201 | G80: =G76+G78 -> 229019.22 | H80: =H76+H78 -> 250701.15 | I80: =I76+I78 -> 274788.73 | J80: =J76+J78 -> 301580.1
A81: Blended gross margin % | B81: =B80/B14 -> 0.4177936 | C81: =C80/C14 -> 0.43309631 | D81: =D80/D14 -> 0.4413113 | E81: =E80/E14 -> 0.4620635 | F81: =F80/F14 -> 0.46905164 | G81: =G80/G14 -> 0.50864086 | H81: =H80/H14 -> 0.51408822 | I81: =I80/I14 -> 0.51969721 | J81: =J80/J14 -> 0.52546013
A83: Source: Apple 10-K (FY22 + FY25). Geographic + product splits per SEC EDGAR filings. Forecast growth rates (column J) are editable inputs (blue) — change to flex the model.

Sheet BS
B1: APPLE INC. — BALANCE SHEET (FY2021A-FY2029E)
B3: Line Item | C3: FY21A | D3: FY22A | E3: FY23A | F3: FY24A | G3: FY25A | H3: FY26E | I3: FY27E | J3: FY28E | K3: FY29E
B4: CURRENT ASSETS
B5: Cash & cash equivalents | C5: 34940 | D5: 23646 | E5: 29965 | F5: 29943 | G5: 35934 | H5: =CFS!G30 -> 6473.3606 | I5: =CFS!H30 -> -28288.742 | J5: =CFS!I30 -> -48888.058 | K5: =CFS!J30 -> -60253.203
B6: Short-term marketable securities | C6: 27699 | D6: 24658 | E6: 31590 | F6: 35228 | G6: 18763 | H6: =CHOOSE(MATCH(Scenario,{"Bear","Base","Bull"},0),Assumptions!$B$88,Assumptions!$C$88,Assumptions!$D$88) -> 38000 | I6: =CHOOSE(MATCH(Scenario,{"Bear","Base","Bull"},0),Assumptions!$E$88,Assumptions!$F$88,Assumptions!$G$88) -> 40000 | J6: =CHOOSE(MATCH(Scenario,{"Bear","Base","Bull"},0),Assumptions!$H$88,Assumptions!$I$88,Assumptions!$J$88) -> 42000 | K6: =CHOOSE(MATCH(Scenario,{"Bear","Base","Bull"},0),Assumptions!$K$88,Assumptions!$L$88,Assumptions!$M$88) -> 42000
B7: Accounts receivable, net | C7: 26278 | D7: 28184 | E7: 29508 | F7: 33410 | G7: 39777 | H7: =Assumptions!G28*IS!G14/365 -> 37007.444 | I7: =Assumptions!H28*IS!H14/365 -> 40081.786 | J7: =Assumptions!I28*IS!I14/365 -> 43458.719 | K7: =Assumptions!J28*IS!J14/365 -> 47172.761
B8: Inventory | C8: 6580 | D8: 4946 | E8: 6331 | F8: 7286 | G8: 5718 | H8: =Assumptions!G29*IS!G20/365 -> 6061.3153 | I8: =Assumptions!H29*IS!H20/365 -> 6492.0705 | J8: =Assumptions!I29*IS!I20/365 -> 6957.7814 | K8: =Assumptions!J29*IS!J20/365 -> 7461.7852
B9: Vendor non-trade receivables | C9: 25228 | D9: 32748 | E9: 31477 | F9: 32833 | G9: 28448 | H9: =Assumptions!G35*IS!G20 -> 29867.131 | I9: =Assumptions!H35*IS!H20 -> 31989.678 | J9: =Assumptions!I35*IS!I20 -> 34284.468 | K9: =Assumptions!J35*IS!J20 -> 36767.947
B10: Other current assets | C10: 14111 | D10: 21223 | E10: 14695 | F10: 14287 | G10: 19317 | H10: =CHOOSE(MATCH(Scenario,{"Bear","Base","Bull"},0),Assumptions!$B$89,Assumptions!$C$89,Assumptions!$D$89) -> -9400 | I10: =CHOOSE(MATCH(Scenario,{"Bear","Base","Bull"},0),Assumptions!$E$89,Assumptions!$F$89,Assumptions!$G$89) -> -9900 | J10: =CHOOSE(MATCH(Scenario,{"Bear","Base","Bull"},0),Assumptions!$H$89,Assumptions!$I$89,Assumptions!$J$89) -> -10600 | K10: =CHOOSE(MATCH(Scenario,{"Bear","Base","Bull"},0),Assumptions!$K$89,Assumptions!$L$89,Assumptions!$M$89) -> -10600
B11: Total Current Assets | C11: =SUM(C5:C10) -> 134836 | D11: =SUM(D5:D10) -> 135405 | E11: =SUM(E5:E10) -> 143566 | F11: =SUM(F5:F10) -> 152987 | G11: =SUM(G5:G10) -> 147957 | H11: =SUM(H5:H10) -> 108009.25 | I11: =SUM(I5:I10) -> 80374.792 | J11: =SUM(J5:J10) -> 67212.911 | K11: =SUM(K5:K10) -> 62549.29
B13: NON-CURRENT ASSETS
B14: Property, plant & equipment, net | C14: 39440 | D14: 42117 | E14: 43715 | F14: 45680 | G14: 49834 | H14: =G14+Assumptions!G37*IS!G14-Assumptions!G38 -> 48483.228 | I14: =H14+Assumptions!H37*IS!H14-Assumptions!H38 -> 47020.243 | J14: =I14+Assumptions!I37*IS!I14-Assumptions!I38 -> 45434 | K14: =J14+Assumptions!J37*IS!J14-Assumptions!J38 -> 43712.194
B15: Long-term marketable securities | C15: 127877 | D15: 120805 | E15: 100544 | F15: 91479 | G15: 77723 | H15: =H39-H11-H14-H16 -> 49599.294 | I15: =I39-I11-I14-I16 -> 81924.692 | J15: =J39-J11-J14-J16 -> 80412.995 | K15: =K39-K11-K14-K16 -> 80412.995
B16: Other non-current assets | C16: 48849 | D16: 54428 | E16: 64758 | F16: 74834 | G16: 83727 | H16: =CHOOSE(MATCH(Scenario,{"Bear","Base","Bull"},0),Assumptions!$B$90,Assumptions!$C$90,Assumptions!$D$90) -> 118000 | I16: =CHOOSE(MATCH(Scenario,{"Bear","Base","Bull"},0),Assumptions!$E$90,Assumptions!$F$90,Assumptions!$G$90) -> 125000 | J16: =CHOOSE(MATCH(Scenario,{"Bear","Base","Bull"},0),Assumptions!$H$90,Assumptions!$I$90,Assumptions!$J$90) -> 132000 | K16: =CHOOSE(MATCH(Scenario,{"Bear","Base","Bull"},0),Assumptions!$K$90,Assumptions!$L$90,Assumptions!$M$90) -> 132000
B17: Total Non-Current Assets | C17: =SUM(C14:C16) -> 216166 | D17: =SUM(D14:D16) -> 217350 | E17: =SUM(E14:E16) -> 209017 | F17: =SUM(F14:F16) -> 211993 | G17: =SUM(G14:G16) -> 211284 | H17: =SUM(H14:H16) -> 216082.52 | I17: =SUM(I14:I16) -> 253944.94 | J17: =SUM(J14:J16) -> 257846.99 | K17: =SUM(K14:K16) -> 256125.19
B18: TOTAL ASSETS | C18: =C11+C17 -> 351002 | D18: =D11+D17 -> 352755 | E18: =E11+E17 -> 352583 | F18: =F11+F17 -> 364980 | G18: =G11+G17 -> 359241 | H18: =H11+H17 -> 324091.77 | I18: =I11+I17 -> 334319.73 | J18: =J11+J17 -> 325059.91 | K18: =K11+K17 -> 318674.48
B20: CURRENT LIABILITIES
B21: Accounts payable | C21: 54763 | D21: 64115 | E21: 62611 | F21: 68960 | G21: 69860 | H21: =Assumptions!G30*IS!G20/365 -> 69705.125 | I21: =Assumptions!H30*IS!H20/365 -> 74658.811 | J21: =Assumptions!I30*IS!I20/365 -> 80014.486 | K21: =Assumptions!J30*IS!J20/365 -> 85810.53
B22: Other current liabilities | C22: 47493 | D22: 60845 | E22: 58829 | F22: 78304 | G22: 81477 | H22: =Assumptions!G33*IS!G14 -> 76543.729 | I22: =Assumptions!H33*IS!H14 -> 82902.493 | J22: =Assumptions!I33*IS!I14 -> 89887.118 | K22: =Assumptions!J33*IS!J14 -> 97568.993
B23: Deferred revenue | C23: 7612 | D23: 7912 | E23: 8061 | F23: 8249 | G23: 8249 | H23: =Assumptions!G34*IS!G13 -> 9706.3294 | I23: =Assumptions!H34*IS!H13 -> 11065.215 | J23: =Assumptions!I34*IS!I13 -> 12614.346 | K23: =Assumptions!J34*IS!J13 -> 14380.354
B24: Commercial paper | C24: 6000 | D24: 9982 | E24: 5985 | F24: 9967 | G24: 6045 | H24: =CHOOSE(MATCH(Scenario,{"Bear","Base","Bull"},0),Assumptions!$B$91,Assumptions!$C$91,Assumptions!$D$91) -> -4000 | I24: =CHOOSE(MATCH(Scenario,{"Bear","Base","Bull"},0),Assumptions!$E$91,Assumptions!$F$91,Assumptions!$G$91) -> -3300 | J24: =CHOOSE(MATCH(Scenario,{"Bear","Base","Bull"},0),Assumptions!$H$91,Assumptions!$I$91,Assumptions!$J$91) -> -4500 | K24: =CHOOSE(MATCH(Scenario,{"Bear","Base","Bull"},0),Assumptions!$K$91,Assumptions!$L$91,Assumptions!$M$91) -> -4500
B25: Current portion of LT debt | C25: 9613 | D25: 11128 | E25: 9822 | F25: 10912 | G25: 0 | H25: =CHOOSE(MATCH(Scenario,{"Bear","Base","Bull"},0),Assumptions!$B$92,Assumptions!$C$92,Assumptions!$D$92) -> 1500 | I25: =CHOOSE(MATCH(Scenario,{"Bear","Base","Bull"},0),Assumptions!$E$92,Assumptions!$F$92,Assumptions!$G$92) -> 0 | J25: =CHOOSE(MATCH(Scenario,{"Bear","Base","Bull"},0),Assumptions!$H$92,Assumptions!$I$92,Assumptions!$J$92) -> 0 | K25: =CHOOSE(MATCH(Scenario,{"Bear","Base","Bull"},0),Assumptions!$K$92,Assumptions!$L$92,Assumptions!$M$92) -> 0
B26: Total Current Liabilities | C26: =SUM(C21:C25) -> 125481 | D26: =SUM(D21:D25) -> 153982 | E26: =SUM(E21:E25) -> 145308 | F26: =SUM(F21:F25) -> 176392 | G26: =SUM(G21:G25) -> 165631 | H26: =SUM(H21:H25) -> 153455.18 | I26: =SUM(I21:I25) -> 165326.52 | J26: =SUM(J21:J25) -> 178015.95 | K26: =SUM(K21:K25) -> 193259.88
B28: NON-CURRENT LIABILITIES
B29: Long-term debt | C29: 109106 | D29: 98959 | E29: 95281 | F29: 85750 | G29: 78328 | H29: =CHOOSE(MATCH(Scenario,{"Bear","Base","Bull"},0),Assumptions!$B$93,Assumptions!$C$93,Assumptions!$D$93) -> 60000 | I29: =CHOOSE(MATCH(Scenario,{"Bear","Base","Bull"},0),Assumptions!$E$93,Assumptions!$F$93,Assumptions!$G$93) -> 50000 | J29: =CHOOSE(MATCH(Scenario,{"Bear","Base","Bull"},0),Assumptions!$H$93,Assumptions!$I$93,Assumptions!$J$93) -> 40000 | K29: =CHOOSE(MATCH(Scenario,{"Bear","Base","Bull"},0),Assumptions!$K$93,Assumptions!$L$93,Assumptions!$M$93) -> 40000
B30: Other non-current liabilities | C30: 53325 | D30: 49142 | E30: 49848 | F30: 45888 | G30: 41549 | H30: =CHOOSE(MATCH(Scenario,{"Bear","Base","Bull"},0),Assumptions!$B$94,Assumptions!$C$94,Assumptions!$D$94) -> 31000 | I30: =CHOOSE(MATCH(Scenario,{"Bear","Base","Bull"},0),Assumptions!$E$94,Assumptions!$F$94,Assumptions!$G$94) -> 30000 | J30: =CHOOSE(MATCH(Scenario,{"Bear","Base","Bull"},0),Assumptions!$H$94,Assumptions!$I$94,Assumptions!$J$94) -> 29000 | K30: =CHOOSE(MATCH(Scenario,{"Bear","Base","Bull"},0),Assumptions!$K$94,Assumptions!$L$94,Assumptions!$M$94) -> 29000
B31: Total Non-Current Liabilities | C31: =SUM(C29:C30) -> 162431 | D31: =SUM(D29:D30) -> 148101 | E31: =SUM(E29:E30) -> 145129 | F31: =SUM(F29:F30) -> 131638 | G31: =SUM(G29:G30) -> 119877 | H31: =SUM(H29:H30) -> 91000 | I31: =SUM(I29:I30) -> 80000 | J31: =SUM(J29:J30) -> 69000 | K31: =SUM(K29:K30) -> 69000
B32: Total Liabilities | C32: =C26+C31 -> 287912 | D32: =D26+D31 -> 302083 | E32: =E26+E31 -> 290437 | F32: =F26+F31 -> 308030 | G32: =G26+G31 -> 285508 | H32: =H26+H31 -> 244455.18 | I32: =I26+I31 -> 245326.52 | J32: =J26+J31 -> 247015.95 | K32: =K26+K31 -> 262259.88
B34: SHAREHOLDERS' EQUITY
B35: Common stock & paid-in capital | C35: 57365 | D35: 64849 | E35: 73812 | F35: 83276 | G35: 95520 | H35: =G35+CFS!G12 -> 109477.97 | I35: =H35+CFS!H12 -> 124595.49 | J35: =I35+CFS!I12 -> 140986.67 | K35: =J35+CFS!J12 -> 158778.66
B36: Retained earnings | C36: 5562 | D36: -3068 | E36: -214 | F36: -19154 | G36: -22031 | H36: =G36+IS!G38+CFS!G24+CFS!G25 -> -29941.385 | I36: =H36+IS!H38+CFS!H24+CFS!H25 -> -35682.28 | J36: =I36+IS!I38+CFS!I24+CFS!I25 -> -63002.712 | K36: =J36+IS!J38+CFS!J24+CFS!J25 -> -102424.06
B37: Accumulated other comp. inc/(loss) | C37: 163 | D37: -11109 | E37: -11452 | F37: -7172 | G37: 244 | H37: =CHOOSE(MATCH(Scenario,{"Bear","Base","Bull"},0),Assumptions!$B$95,Assumptions!$C$95,Assumptions!$D$95) -> 100 | I37: =CHOOSE(MATCH(Scenario,{"Bear","Base","Bull"},0),Assumptions!$E$95,Assumptions!$F$95,Assumptions!$G$95) -> 80 | J37: =CHOOSE(MATCH(Scenario,{"Bear","Base","Bull"},0),Assumptions!$H$95,Assumptions!$I$95,Assumptions!$J$95) -> 60 | K37: =CHOOSE(MATCH(Scenario,{"Bear","Base","Bull"},0),Assumptions!$K$95,Assumptions!$L$95,Assumptions!$M$95) -> 60
B38: Total Shareholders' Equity | C38: =SUM(C35:C37) -> 63090 | D38: =SUM(D35:D37) -> 50672 | E38: =SUM(E35:E37) -> 62146 | F38: =SUM(F35:F37) -> 56950 | G38: =SUM(G35:G37) -> 73733 | H38: =SUM(H35:H37) -> 79636.589 | I38: =SUM(I35:I37) -> 88993.207 | J38: =SUM(J35:J37) -> 78043.956 | K38: =SUM(K35:K37) -> 56414.601
B39: TOTAL LIABILITIES & EQUITY | C39: =C32+C38 -> 351002 | D39: =D32+D38 -> 352755 | E39: =E32+E38 -> 352583 | F39: =F32+F38 -> 364980 | G39: =G32+G38 -> 359241 | H39: =H32+H38 -> 324091.77 | I39: =I32+I38 -> 334319.73 | J39: =J32+J38 -> 325059.91 | K39: =K32+K38 -> 318674.48
B41: KEY METRICS
B42: Total Debt | C42: =C24+C25+C29 -> 124719 | D42: =D24+D25+D29 -> 120069 | E42: =E24+E25+E29 -> 111088 | F42: =F24+F25+F29 -> 106629 | G42: =G24+G25+G29 -> 84373 | H42: =H24+H25+H29 -> 57500 | I42: =I24+I25+I29 -> 46700 | J42: =J24+J25+J29 -> 35500 | K42: =K24+K25+K29 -> 35500
B43: Net Debt | C43: =C42-C5-C6-C15 -> -65797 | D43: =D42-D5-D6-D15 -> -49040 | E43: =E42-E5-E6-E15 -> -51011 | F43: =F42-F5-F6-F15 -> -50021 | G43: =G42-G5-G6-G15 -> -48047 | H43: =H42-H5-H6-H15 -> -36572.655 | I43: =I42-I5-I6-I15 -> -46935.95 | J43: =J42-J5-J6-J15 -> -38024.937 | K43: =K42-K5-K6-K15 -> -26659.792
B44: Working Capital | C44: =C11-C26 -> 9355 | D44: =D11-D26 -> -18577 | E44: =E11-E26 -> -1742 | F44: =F11-F26 -> -23405 | G44: =G11-G26 -> -17674 | H44: =H11-H26 -> -45445.934 | I44: =I11-I26 -> -84951.728 | J44: =J11-J26 -> -110803.04 | K44: =K11-K26 -> -130710.59
B45: Current Ratio | C45: =C11/C26 -> 1.0745531 | D45: =D11/D26 -> 0.87935603 | E45: =E11/E26 -> 0.98801167 | F45: =F11/F26 -> 0.86731258 | G45: =G11/G26 -> 0.89329292 | H45: =H11/H26 -> 0.70384882 | I45: =I11/I26 -> 0.48615789 | J45: =J11/J26 -> 0.37756679 | K45: =K11/K26 -> 0.32365378
B46: Quick Ratio | C46: =(C11-C8)/C26 -> 1.0221149 | D46: =(D11-D8)/D26 -> 0.84723539 | E46: =(E11-E8)/E26 -> 0.94444215 | F46: =(F11-F8)/F26 -> 0.82600685 | G46: =(G11-G8)/G26 -> 0.8587704 | H46: =(H11-H8)/H26 -> 0.66434989 | I46: =(I11-I8)/I26 -> 0.44688972 | J46: =(J11-J8)/J26 -> 0.33848163 | K46: =(K11-K8)/K26 -> 0.28504367
B47: Debt / Equity | C47: =C42/C38 -> 1.9768426 | D47: =D42/D38 -> 2.3695335 | E47: =E42/E38 -> 1.7875326 | F47: =F42/F38 -> 1.8723266 | G47: =G42/G38 -> 1.1443044 | H47: =H42/H38 -> 0.72202992 | I47: =I42/I38 -> 0.52475915 | J47: =J42/J38 -> 0.45487187 | K47: =K42/K38 -> 0.62926971

Sheet CFS
A1: CASH FLOW STATEMENT | FY2021A – FY2029E
A2: Indirect method | Reconciles net income to change in cash | Audit check: net change ties to BS
A4: USD Millions | B4: FY2021A | C4: FY2022A | D4: FY2023A | E4: FY2024A | F4: FY2025A | G4: FY2026E | H4: FY2027E | I4: FY2028E | J4: FY2029E
B5: Sep 25, 2021 | C5: Sep 24, 2022 | D5: Sep 30, 2023 | E5: Sep 28, 2024 | F5: Sep 27, 2025 | G5: Sep 26, 2026 | H5: Sep 25, 2027 | I5: Sep 30, 2028 | J5: Sep 30, 2029
A7: Cash & equivalents, beginning | B7: 39789 | C7: =B30 -> 35929 | D7: =C30 -> 24977 | E7: =D30 -> 30737 | F7: =E30 -> 29943 | G7: =F30 -> 35934 | H7: =G30 -> 6473.3606 | I7: =H30 -> -28288.742 | J7: =I30 -> -48888.058
A9: OPERATING ACTIVITIES
A10: Depreciation & amortization | B10: =IS!B30 -> 11284 | C10: =IS!C30 -> 11104 | D10: =IS!D30 -> 11519 | E10: =IS!E30 -> 11445 | F10: =IS!F30 -> 11698 | G10: =Assumptions!G38 -> 11256.431 | H10: =Assumptions!H38 -> 12191.543 | I10: =Assumptions!I38 -> 13218.694 | J10: =Assumptions!J38 -> 14348.381
A11: Net income (from IS) | B11: =IS!B38 -> 94680 | C11: =IS!C38 -> 99803 | D11: =IS!D38 -> 96995 | E11: =IS!E38 -> 93736 | F11: =IS!F38 -> 112010 | G11: =IS!G38 -> 143387.04 | H11: =IS!H38 -> 159930.25 | I11: =IS!I38 -> 178465.22 | J11: =IS!J38 -> 199246.69
A12: Share-based compensation | B12: 7906 | C12: 9038 | D12: 10833 | E12: 11688 | F12: 12863 | G12: =Assumptions!G32*IS!G14 -> 13957.974 | H12: =Assumptions!H32*IS!H14 -> 15117.513 | I12: =Assumptions!I32*IS!I14 -> 16391.18 | J12: =Assumptions!J32*IS!J14 -> 17791.993
A13: Changes in working capital & other | B13: -9832 | C13: 2206 | D13: -8804 | E13: 1385 | F13: -25089 | G13: =-(BS!G7-BS!F7)-(BS!G8-BS!F8)-(BS!G9-BS!F9)-(BS!G10-BS!F10)+(BS!G21-BS!F21)+(BS!G22-BS!F22)+(BS!G23-BS!F23)-(BS!G16-BS!F16)+(BS!G30-BS!F30) -> -14603 | H13: =-(BS!H7-BS!G7)-(BS!H8-BS!G8)-(BS!H9-BS!G9)-(BS!H10-BS!G10)+(BS!H21-BS!G21)+(BS!H22-BS!G22)+(BS!H23-BS!G23)-(BS!H16-BS!G16)+(BS!H30-BS!G30) -> -18728.706 | I13: =-(BS!I7-BS!H7)-(BS!I8-BS!H8)-(BS!I9-BS!H9)-(BS!I10-BS!H10)+(BS!I21-BS!H21)+(BS!I22-BS!H22)+(BS!I23-BS!H23)-(BS!I16-BS!H16)+(BS!I30-BS!H30) -> -456.30797 | J13: =-(BS!K7-BS!J7)-(BS!K8-BS!J8)-(BS!K9-BS!J9)-(BS!K10-BS!J10)+(BS!K21-BS!J21)+(BS!K22-BS!J22)+(BS!K23-BS!J23)-(BS!K16-BS!J16)+(BS!K30-BS!J30) -> 8542.4036
A14: Cash from operating activities | B14: =B10+B11+B12+B13 -> 104038 | C14: =C10+C11+C12+C13 -> 122151 | D14: =D10+D11+D12+D13 -> 110543 | E14: =E10+E11+E12+E13 -> 118254 | F14: =F10+F11+F12+F13 -> 111482 | G14: =G10+G11+G12+G13 -> 153998.45 | H14: =H10+H11+H12+H13 -> 168510.6 | I14: =I10+I11+I12+I13 -> 207618.78 | J14: =J10+J11+J12+J13 -> 239929.47
A16: INVESTING ACTIVITIES
A17: Cash from investing activities | B17: =B19+B20 -> -14545 | C17: =C19+C20 -> -22354 | D17: =D19+D20 -> 3705 | E17: =E19+E20 -> 2935 | F17: =F19+F20 -> 15195 | G17: =G19+G20 -> -9905.6591 | H17: =H19+H20 -> -10728.558 | I17: =I19+I20 -> -11632.451 | J17: =J19+J20 -> -12626.576
A19: Capital expenditures | B19: -11085 | C19: -10708 | D19: -10959 | E19: -9447 | F19: -12715 | G19: =-Assumptions!G37*IS!G14 -> -9905.6591 | H19: =-Assumptions!H37*IS!H14 -> -10728.558 | I19: =-Assumptions!I37*IS!I14 -> -11632.451 | J19: =-Assumptions!J37*IS!J14 -> -12626.576
A20: Other investing | B20: -3460 | C20: -11646 | D20: 14664 | E20: 12382 | F20: 27910 | G20: 0 | H20: 0 | I20: 0 | J20: 0
A21: Free cash flow (CFO − CapEx) | B21: =B14+B19 -> 92953 | C21: =C14+C19 -> 111443 | D21: =D14+D19 -> 99584 | E21: =E14+E19 -> 108807 | F21: =F14+F19 -> 98767 | G21: =G14+G19 -> 144092.79 | H21: =H14+H19 -> 157782.04 | I21: =I14+I19 -> 195986.33 | J21: =J14+J19 -> 227302.89
A23: FINANCING ACTIVITIES
A24: Dividends paid | B24: -14467 | C24: -14841 | D24: -15025 | E24: -15234 | F24: -15421 | G24: =-Assumptions!G42*Assumptions!G41*G21 -> -18155.691 | H24: =-Assumptions!H42*Assumptions!H41*H21 -> -19880.537 | I24: =-Assumptions!I42*Assumptions!I41*I21 -> -24694.278 | J24: =-Assumptions!J42*Assumptions!J41*J21 -> -28640.165
A25: Share repurchases | B25: -85971 | C25: -89402 | D25: -77550 | E25: -94949 | F25: -90711 | G25: =-(1-Assumptions!G42)*Assumptions!G41*G21 -> -133141.74 | H25: =-(1-Assumptions!H42)*Assumptions!H41*H21 -> -145790.61 | I25: =-(1-Assumptions!I42)*Assumptions!I41*I21 -> -181091.37 | J25: =-(1-Assumptions!J42)*Assumptions!J41*J21 -> -210027.87
A26: Net debt repayment & other financing | B26: 7085 | C26: -6506 | D26: -15913 | E26: -11800 | F26: -14554 | G26: =(BS!G24-BS!F24)+(BS!G25-BS!F25)+(BS!G29-BS!F29) -> -22256 | H26: =(BS!H24-BS!G24)+(BS!H25-BS!G25)+(BS!H29-BS!G29) -> -26873 | I26: =(BS!I24-BS!H24)+(BS!I25-BS!H25)+(BS!I29-BS!H29) -> -10800 | J26: =(BS!K24-BS!J24)+(BS!K25-BS!J25)+(BS!K29-BS!J29) -> 0
A27: Cash from financing activities | B27: =SUM(B24:B26) -> -93353 | C27: =SUM(C24:C26) -> -110749 | D27: =SUM(D24:D26) -> -108488 | E27: =SUM(E24:E26) -> -121983 | F27: =SUM(F24:F26) -> -120686 | G27: =SUM(G24:G26) -> -173553.43 | H27: =SUM(H24:H26) -> -192544.15 | I27: =SUM(I24:I26) -> -216585.65 | J27: =SUM(J24:J26) -> -238668.04
A29: Net change in cash | B29: =B14+B17+B27 -> -3860 | C29: =C14+C17+C27 -> -10952 | D29: =D14+D17+D27 -> 5760 | E29: =E14+E17+E27 -> -794 | F29: =F14+F17+F27 -> 5991 | G29: =G14+G17+G27 -> -29460.639 | H29: =H14+H17+H27 -> -34762.102 | I29: =I14+I17+I27 -> -20599.317 | J29: =J14+J17+J27 -> -11365.145
A30: Cash & equivalents, ending | B30: =B7+B29 -> 35929 | C30: =C7+C29 -> 24977 | D30: =D7+D29 -> 30737 | E30: =E7+E29 -> 29943 | F30: =F7+F29 -> 35934 | G30: =G7+G29 -> 6473.3606 | H30: =H7+H29 -> -28288.742 | I30: =I7+I29 -> -48888.058 | J30: =J7+J29 -> -60253.203
A33: FREE CASH FLOW
A34: Free Cash Flow | B34: =B14+B19 -> 92953 | C34: =C14+C19 -> 111443 | D34: =D14+D19 -> 99584 | E34: =E14+E19 -> 108807 | F34: =F14+F19 -> 98767 | G34: =G14+G19 -> 144092.79 | H34: =H14+H19 -> 157782.04 | I34: =I14+I19 -> 195986.33 | J34: =J14+J19 -> 227302.89
A35: FCF Margin % | B35: =B34/IS!B14 -> 0.25409699 | C35: =C34/IS!C14 -> 0.28261498 | D35: =D34/IS!D14 -> 0.25981711 | E35: =E34/IS!E14 -> 0.27825386 | F35: =F34/IS!F14 -> 0.23732882 | G35: =G34/IS!G14 -> 0.32002327 | H35: =H34/IS!H14 -> 0.32354814 | I35: =I34/IS!I14 -> 0.3706613 | J35: =J34/IS!J14 -> 0.39604275
A36: CapEx / Revenue % | B36: =-B19/IS!B14 -> 0.030302036 | C36: =-C19/IS!C14 -> 0.027155059 | D36: =-D19/IS!D14 -> 0.028592301 | E36: =-E19/IS!E14 -> 0.024158963 | F36: =-F19/IS!F14 -> 0.030553079 | G36: =-G19/IS!G14 -> 0.022 | H36: =-H19/IS!H14 -> 0.022 | I36: =-I19/IS!I14 -> 0.022 | J36: =-J19/IS!J14 -> 0.022
A38: Note: BS holds Cash & equivalents (row 8) and current marketable securities (row 9) flat at FY25 levels. Non-current marketable securities (BS row 10) absorbs the projected cash build/draw via the plug formula. Aggregate Cash + securities ties to CFS ending cash.

Sheet Ratios
A1: RATIOS | Profitability, Returns, Liquidity, Leverage
A2: All metrics calculated from IS, BS, and CFS sheets — fully formula-driven
A4: USD Millions | B4: FY2021A | C4: FY2022A | D4: FY2023A | E4: FY2024A | F4: FY2025A | G4: FY2026E | H4: FY2027E | I4: FY2028E | J4: FY2029E
A6: PROFITABILITY MARGINS
A7: Gross margin % | B7: =IS!B21/IS!B14 -> 0.4177936 | C7: =IS!C21/IS!C14 -> 0.43309631 | D7: =IS!D21/IS!D14 -> 0.4413113 | E7: =IS!E21/IS!E14 -> 0.4620635 | F7: =IS!F21/IS!F14 -> 0.46905164 | G7: =IS!G21/IS!G14 -> 0.50864086 | H7: =IS!H21/IS!H14 -> 0.51408822 | I7: =IS!I21/IS!I14 -> 0.51969721 | J7: =IS!J21/IS!J14 -> 0.52546013
A8: Operating margin % | B8: =IS!B28/IS!B14 -> 0.29782378 | C8: =IS!C28/IS!C14 -> 0.30288744 | D8: =IS!D28/IS!D14 -> 0.29821412 | E8: =IS!E28/IS!E14 -> 0.31510223 | F8: =IS!F28/IS!F14 -> 0.319708 | G8: =IS!G28/IS!G14 -> 0.36493072 | H8: =IS!H28/IS!H14 -> 0.37593246 | I8: =IS!I28/IS!I14 -> 0.38701333 | J8: =IS!J28/IS!J14 -> 0.39816196
A9: Net margin % | B9: =IS!B38/IS!B14 -> 0.25881793 | C9: =IS!C38/IS!C14 -> 0.25309641 | D9: =IS!D38/IS!D14 -> 0.25306234 | E9: =IS!E38/IS!E14 -> 0.23971256 | F9: =IS!F38/IS!F14 -> 0.26915064 | G9: =IS!G38/IS!G14 -> 0.31845584 | H9: =IS!H38/IS!H14 -> 0.32795326 | I9: =IS!I38/IS!I14 -> 0.3375243 | J9: =IS!J38/IS!J14 -> 0.34715883
A10: EBITDA margin % | B10: =(IS!B28+CFS!B10)/IS!B14 -> 0.3286698 | C10: =(IS!C28+CFS!C10)/IS!C14 -> 0.33104674 | D10: =(IS!D28+CFS!D10)/IS!D14 -> 0.32826748 | E10: =(IS!E28+CFS!E10)/IS!E14 -> 0.34437071 | F10: =(IS!F28+CFS!F10)/IS!F14 -> 0.34781731 | G10: =(IS!G28+CFS!G10)/IS!G14 -> 0.38993072 | H10: =(IS!H28+CFS!H10)/IS!H14 -> 0.40093246 | I10: =(IS!I28+CFS!I10)/IS!I14 -> 0.41201333 | J10: =(IS!J28+CFS!J10)/IS!J14 -> 0.42316196
A12: GROWTH (YoY)
A13: Revenue growth % | B13: — | C13: =IS!C14/IS!B14-1 -> 0.077937876 | D13: =IS!D14/IS!C14-1 -> -0.028004605 | E13: =IS!E14/IS!D14-1 -> 0.020219941 | F13: =IS!F14/IS!E14-1 -> 0.064255118 | G13: =IS!G14/IS!F14-1 -> 0.081930383 | H13: =IS!H14/IS!G14-1 -> 0.083073613 | I13: =IS!I14/IS!H14-1 -> 0.084251084 | J13: =IS!J14/IS!I14-1 -> 0.085461359
A14: Operating income growth % | B14: — | C14: =IS!C28/IS!B28-1 -> 0.096265225 | D14: =IS!D28/IS!C28-1 -> -0.04300175 | E14: =IS!E28/IS!D28-1 -> 0.077995818 | F14: =IS!F28/IS!E28-1 -> 0.079811063 | G14: =IS!G28/IS!F28-1 -> 0.23496951 | H14: =IS!H28/IS!G28-1 -> 0.11572557 | I14: =IS!I28/IS!H28-1 -> 0.11621014 | J14: =IS!J28/IS!I28-1 -> 0.11673006
A15: Net income growth % | B15: — | C15: =IS!C38/IS!B38-1 -> 0.054108576 | D15: =IS!D38/IS!C38-1 -> -0.028135427 | E15: =IS!E38/IS!D38-1 -> -0.03359967 | F15: =IS!F38/IS!E38-1 -> 0.19495178 | G15: =IS!G38/IS!F38-1 -> 0.28012716 | H15: =IS!H38/IS!G38-1 -> 0.11537449 | I15: =IS!I38/IS!H38-1 -> 0.11589405 | J15: =IS!J38/IS!I38-1 -> 0.11644553
A17: RETURNS
A18: Return on assets (ROA) | B18: =IS!B38/BS!C18 -> 0.26974205 | C18: =IS!C38/BS!D18 -> 0.28292441 | D18: =IS!D38/BS!E18 -> 0.27509835 | E18: =IS!E38/BS!F18 -> 0.25682503 | F18: =IS!F38/BS!G18 -> 0.31179626 | G18: =IS!G38/BS!H18 -> 0.44242728 | H18: =IS!H38/BS!I18 -> 0.47837515 | I18: =IS!I38/BS!J18 -> 0.54902254 | J18: =IS!J38/BS!K18 -> 0.6252358
A19: Return on equity (ROE) | B19: =IS!B38/BS!C38 -> 1.5007133 | C19: =IS!C38/BS!D38 -> 1.9695887 | D19: =IS!D38/BS!E38 -> 1.5607601 | E19: =IS!E38/BS!F38 -> 1.645935 | F19: =IS!F38/BS!G38 -> 1.5191298 | G19: =IS!G38/BS!H38 -> 1.8005171 | H19: =IS!H38/BS!I38 -> 1.7971063 | I19: =IS!I38/BS!J38 -> 2.2867269 | J19: =IS!J38/BS!K38 -> 3.5318284
A20: Return on invested capital | B20: =(IS!B28*(1-Assumptions!$B$50))/(BS!C42+BS!C38) -> 0.49308952 | C20: =(IS!C28*(1-Assumptions!$B$50))/(BS!D42+BS!D38) -> 0.59459327 | D20: =(IS!D28*(1-Assumptions!$B$50))/(BS!E42+BS!E38) -> 0.56083592 | E20: =(IS!E28*(1-Assumptions!$B$50))/(BS!F42+BS!F38) -> 0.64026311 | F20: =(IS!F28*(1-Assumptions!$B$50))/(BS!G42+BS!G38) -> 0.71529543 | G20: =(IS!G28*(1-Assumptions!$B$50))/(BS!H42+BS!H38) -> 1.0184429 | H20: =(IS!H28*(1-Assumptions!$B$50))/(BS!I42+BS!I38) -> 1.1483898 | I20: =(IS!I28*(1-Assumptions!$B$50))/(BS!J42+BS!J38) -> 1.5318963 | J20: =(IS!J28*(1-Assumptions!$B$50))/(BS!K42+BS!K38) -> 2.1132802
A22: LEVERAGE & LIQUIDITY
A23: Debt / Equity | B23: =BS!C42/BS!C38 -> 1.9768426 | C23: =BS!D42/BS!D38 -> 2.3695335 | D23: =BS!E42/BS!E38 -> 1.7875326 | E23: =BS!F42/BS!F38 -> 1.8723266 | F23: =BS!G42/BS!G38 -> 1.1443044 | G23: =BS!H42/BS!H38 -> 0.72202992 | H23: =BS!I42/BS!I38 -> 0.52475915 | I23: =BS!J42/BS!J38 -> 0.45487187 | J23: =BS!K42/BS!K38 -> 0.62926971
A24: Debt / Total capital | B24: =BS!C42/(BS!C42+BS!C38) -> 0.66407361 | C24: =BS!D42/(BS!D42+BS!D38) -> 0.70322301 | D24: =BS!E42/(BS!E42+BS!E38) -> 0.6412598 | E24: =BS!F42/(BS!F42+BS!F38) -> 0.65185018 | F24: =BS!G42/(BS!G42+BS!G38) -> 0.53364831 | G24: =BS!H42/(BS!H42+BS!H38) -> 0.41929 | H24: =BS!I42/(BS!I42+BS!I38) -> 0.34415872 | I24: =BS!J42/(BS!J42+BS!J38) -> 0.31265425 | J24: =BS!K42/(BS!K42+BS!K38) -> 0.38622808
A25: Current ratio | B25: =BS!C11/BS!C26 -> 1.0745531 | C25: =BS!D11/BS!D26 -> 0.87935603 | D25: =BS!E11/BS!E26 -> 0.98801167 | E25: =BS!F11/BS!F26 -> 0.86731258 | F25: =BS!G11/BS!G26 -> 0.89329292 | G25: =BS!H11/BS!H26 -> 0.70384882 | H25: =BS!I11/BS!I26 -> 0.48615789 | I25: =BS!J11/BS!J26 -> 0.37756679 | J25: =BS!K11/BS!K26 -> 0.32365378
A26: Net debt ($M) | B26: =BS!C43 -> -65797 | C26: =BS!D43 -> -49040 | D26: =BS!E43 -> -51011 | E26: =BS!F43 -> -50021 | F26: =BS!G43 -> -48047 | G26: =BS!H43 -> -36572.655 | H26: =BS!I43 -> -46935.95 | I26: =BS!J43 -> -38024.937 | J26: =BS!K43 -> -26659.792
A28: CASH FLOW METRICS
A29: Operating cash flow ($M) | B29: =CFS!B14 -> 104038 | C29: =CFS!C14 -> 122151 | D29: =CFS!D14 -> 110543 | E29: =CFS!E14 -> 118254 | F29: =CFS!F14 -> 111482 | G29: =CFS!G14 -> 153998.45 | H29: =CFS!H14 -> 168510.6 | I29: =CFS!I14 -> 207618.78 | J29: =CFS!J14 -> 239929.47
A30: Free cash flow ($M) | B30: =CFS!B21 -> 92953 | C30: =CFS!C21 -> 111443 | D30: =CFS!D21 -> 99584 | E30: =CFS!E21 -> 108807 | F30: =CFS!F21 -> 98767 | G30: =CFS!G21 -> 144092.79 | H30: =CFS!H21 -> 157782.04 | I30: =CFS!I21 -> 195986.33 | J30: =CFS!J21 -> 227302.89
A31: FCF margin % | B31: =CFS!B21/IS!B14 -> 0.25409699 | C31: =CFS!C21/IS!C14 -> 0.28261498 | D31: =CFS!D21/IS!D14 -> 0.25981711 | E31: =CFS!E21/IS!E14 -> 0.27825386 | F31: =CFS!F21/IS!F14 -> 0.23732882 | G31: =CFS!G21/IS!G14 -> 0.32002327 | H31: =CFS!H21/IS!H14 -> 0.32354814 | I31: =CFS!I21/IS!I14 -> 0.3706613 | J31: =CFS!J21/IS!J14 -> 0.39604275
A32: FCF / Net income | B32: =CFS!B21/IS!B38 -> 0.98175961 | C32: =CFS!C21/IS!C38 -> 1.1166298 | D32: =CFS!D21/IS!D38 -> 1.0266921 | E32: =CFS!E21/IS!E38 -> 1.1607813 | F32: =CFS!F21/IS!F38 -> 0.88176948 | G32: =CFS!G21/IS!G38 -> 1.004922 | H32: =CFS!H21/IS!H38 -> 0.98656785 | I32: =CFS!I21/IS!I38 -> 1.0981766 | J32: =CFS!J21/IS!J38 -> 1.1408114
A33: CapEx / Revenue | B33: =-CFS!B19/IS!B14 -> 0.030302036 | C33: =-CFS!C19/IS!C14 -> 0.027155059 | D33: =-CFS!D19/IS!D14 -> 0.028592301 | E33: =-CFS!E19/IS!E14 -> 0.024158963 | F33: =-CFS!F19/IS!F14 -> 0.030553079 | G33: =-CFS!G19/IS!G14 -> 0.022 | H33: =-CFS!H19/IS!H14 -> 0.022 | I33: =-CFS!I19/IS!I14 -> 0.022 | J33: =-CFS!J19/IS!J14 -> 0.022

Sheet DCF
A1: DCF VALUATION | Discounted Cash Flow
A2: Enterprise value via FCF discounting + Gordon Growth terminal | WACC × g sensitivity table
A4: USD Millions | B4: FY2026E | C4: FY2027E | D4: FY2028E | E4: FY2029E | F4: Terminal
A6: UNLEVERED FREE CASH FLOW BUILD
A7: EBIT (operating income) | B7: =IS!G28 -> 164312.69 | C7: =IS!H28 -> 183327.87 | D7: =IS!I28 -> 204632.43 | E7: =IS!J28 -> 228519.19
A8: × (1 − tax rate) | B8: =1-Assumptions!$B$50 -> 0.85 | C8: =1-Assumptions!$B$50 -> 0.85 | D8: =1-Assumptions!$B$50 -> 0.85 | E8: =1-Assumptions!$B$50 -> 0.85
A9: NOPAT | B9: =B7*B8 -> 139665.79 | C9: =C7*C8 -> 155828.69 | D9: =D7*D8 -> 173937.57 | E9: =E7*E8 -> 194241.31
A10: + Depreciation & amortization | B10: =CFS!G10 -> 11256.431 | C10: =CFS!H10 -> 12191.543 | D10: =CFS!I10 -> 13218.694 | E10: =CFS!J10 -> 14348.381
A11: − CapEx | B11: =CFS!G19 -> -9905.6591 | C11: =CFS!H19 -> -10728.558 | D11: =CFS!I19 -> -11632.451 | E11: =CFS!J19 -> -12626.576
A12: − Change in working capital | B12: =CFS!G13 -> -14603 | C12: =CFS!H13 -> -18728.706 | D12: =CFS!I13 -> -456.30797 | E12: =CFS!J13 -> 8542.4036
A13: Unlevered free cash flow | B13: =B9+B10+B11+B12 -> 126413.56 | C13: =C9+C10+C11+C12 -> 138562.97 | D13: =D9+D10+D11+D12 -> 175067.5 | E13: =E9+E10+E11+E12 -> 204505.52 | F13: =E13*(1+Assumptions!$B$55)/(Assumptions!$B$54-Assumptions!$B$55) -> 4399805.4
A15: Period (years from today) | B15: 1 | C15: 2 | D15: 3 | E15: 4 | F15: 5
A16: Discount factor (at WACC) | B16: =1/(1+Assumptions!$B$54)^B15 -> 0.92775136 | C16: =1/(1+Assumptions!$B$54)^C15 -> 0.86072259 | D16: =1/(1+Assumptions!$B$54)^D15 -> 0.79853656 | E16: =1/(1+Assumptions!$B$54)^E15 -> 0.74084338 | F16: =1/(1+Assumptions!$B$54)^F15 -> 0.68731845
A17: Present value | B17: =B13*B16 -> 117280.35 | C17: =C13*C16 -> 119264.28 | D17: =D13*D16 -> 139797.8 | E17: =E13*E16 -> 151506.56 | F17: =F13*F16 -> 3024067.4
A19: VALUATION SUMMARY
A20: Sum PV of forecast FCFs | B20: =SUM(B17:E17) -> 527848.99
A21: PV of terminal value | B21: =F17 -> 3024067.4
A22: Enterprise value | B22: =B20+B21 -> 3551916.4
A23: − Net debt (FY25) | B23: =BS!F5+BS!F6+BS!F15-BS!F42 -> 50021
A24: Equity value | B24: =B22+B23 -> 3601937.4
A25: ÷ Diluted shares (M) | B25: =Assumptions!$B$58 -> 15004.7
A26: Implied share price | B26: =B24/B25 -> 240.05395
A27: Current share price | B27: =Assumptions!$B$59 -> 232.5
A28: Upside / (downside) | B28: =B26/B27-1 -> 0.032490088
A31: SENSITIVITY | Implied Share Price by WACC × Terminal Growth
A33: WACC ↓ / g → | B33: 0.015 | C33: 0.02 | D33: 0.025 | E33: 0.03 | F33: 0.035
A34: 0.075 | B34: =($B$13/(1+$A34)^1+$C$13/(1+$A34)^2+$D$13/(1+$A34)^3+$E$13/(1+$A34)^4+($E$13*(1+B$33)/($A34-B$33))/(1+$A34)^4+$B$23)/Assumptions!$B$58 -> 211.40632 | C34: =($B$13/(1+$A34)^1+$C$13/(1+$A34)^2+$D$13/(1+$A34)^3+$E$13/(1+$A34)^4+($E$13*(1+C$33)/($A34-C$33))/(1+$A34)^4+$B$23)/Assumptions!$B$58 -> 228.02929 | D34: =($B$13/(1+$A34)^1+$C$13/(1+$A34)^2+$D$13/(1+$A34)^3+$E$13/(1+$A34)^4+($E$13*(1+D$33)/($A34-D$33))/(1+$A34)^4+$B$23)/Assumptions!$B$58 -> 247.97684 | E34: =($B$13/(1+$A34)^1+$C$13/(1+$A34)^2+$D$13/(1+$A34)^3+$E$13/(1+$A34)^4+($E$13*(1+E$33)/($A34-E$33))/(1+$A34)^4+$B$23)/Assumptions!$B$58 -> 272.35718 | F34: =($B$13/(1+$A34)^1+$C$13/(1+$A34)^2+$D$13/(1+$A34)^3+$E$13/(1+$A34)^4+($E$13*(1+F$33)/($A34-F$33))/(1+$A34)^4+$B$23)/Assumptions!$B$58 -> 302.83261
A35: 0.08 | B35: =($B$13/(1+$A35)^1+$C$13/(1+$A35)^2+$D$13/(1+$A35)^3+$E$13/(1+$A35)^4+($E$13*(1+B$33)/($A35-B$33))/(1+$A35)^4+$B$23)/Assumptions!$B$58 -> 194.76737 | C35: =($B$13/(1+$A35)^1+$C$13/(1+$A35)^2+$D$13/(1+$A35)^3+$E$13/(1+$A35)^4+($E$13*(1+C$33)/($A35-C$33))/(1+$A35)^4+$B$23)/Assumptions!$B$58 -> 208.6385 | D35: =($B$13/(1+$A35)^1+$C$13/(1+$A35)^2+$D$13/(1+$A35)^3+$E$13/(1+$A35)^4+($E$13*(1+D$33)/($A35-D$33))/(1+$A35)^4+$B$23)/Assumptions!$B$58 -> 225.03166 | E35: =($B$13/(1+$A35)^1+$C$13/(1+$A35)^2+$D$13/(1+$A35)^3+$E$13/(1+$A35)^4+($E$13*(1+E$33)/($A35-E$33))/(1+$A35)^4+$B$23)/Assumptions!$B$58 -> 244.70344 | F35: =($B$13/(1+$A35)^1+$C$13/(1+$A35)^2+$D$13/(1+$A35)^3+$E$13/(1+$A35)^4+($E$13*(1+F$33)/($A35-F$33))/(1+$A35)^4+$B$23)/Assumptions!$B$58 -> 268.74673
A36: 0.085 | B36: =($B$13/(1+$A36)^1+$C$13/(1+$A36)^2+$D$13/(1+$A36)^3+$E$13/(1+$A36)^4+($E$13*(1+B$33)/($A36-B$33))/(1+$A36)^4+$B$23)/Assumptions!$B$58 -> 180.51463 | C36: =($B$13/(1+$A36)^1+$C$13/(1+$A36)^2+$D$13/(1+$A36)^3+$E$13/(1+$A36)^4+($E$13*(1+C$33)/($A36-C$33))/(1+$A36)^4+$B$23)/Assumptions!$B$58 -> 192.24055 | D36: =($B$13/(1+$A36)^1+$C$13/(1+$A36)^2+$D$13/(1+$A36)^3+$E$13/(1+$A36)^4+($E$13*(1+D$33)/($A36-D$33))/(1+$A36)^4+$B$23)/Assumptions!$B$58 -> 205.9208 | E36: =($B$13/(1+$A36)^1+$C$13/(1+$A36)^2+$D$13/(1+$A36)^3+$E$13/(1+$A36)^4+($E$13*(1+E$33)/($A36-E$33))/(1+$A36)^4+$B$23)/Assumptions!$B$58 -> 222.08836 | F36: =($B$13/(1+$A36)^1+$C$13/(1+$A36)^2+$D$13/(1+$A36)^3+$E$13/(1+$A36)^4+($E$13*(1+F$33)/($A36-F$33))/(1+$A36)^4+$B$23)/Assumptions!$B$58 -> 241.48944
A37: 0.09 | B37: =($B$13/(1+$A37)^1+$C$13/(1+$A37)^2+$D$13/(1+$A37)^3+$E$13/(1+$A37)^4+($E$13*(1+B$33)/($A37-B$33))/(1+$A37)^4+$B$23)/Assumptions!$B$58 -> 168.17067 | C37: =($B$13/(1+$A37)^1+$C$13/(1+$A37)^2+$D$13/(1+$A37)^3+$E$13/(1+$A37)^4+($E$13*(1+C$33)/($A37-C$33))/(1+$A37)^4+$B$23)/Assumptions!$B$58 -> 178.19393 | D37: =($B$13/(1+$A37)^1+$C$13/(1+$A37)^2+$D$13/(1+$A37)^3+$E$13/(1+$A37)^4+($E$13*(1+D$33)/($A37-D$33))/(1+$A37)^4+$B$23)/Assumptions!$B$58 -> 189.75922 | E37: =($B$13/(1+$A37)^1+$C$13/(1+$A37)^2+$D$13/(1+$A37)^3+$E$13/(1+$A37)^4+($E$13*(1+E$33)/($A37-E$33))/(1+$A37)^4+$B$23)/Assumptions!$B$58 -> 203.25207 | F37: =($B$13/(1+$A37)^1+$C$13/(1+$A37)^2+$D$13/(1+$A37)^3+$E$13/(1+$A37)^4+($E$13*(1+F$33)/($A37-F$33))/(1+$A37)^4+$B$23)/Assumptions!$B$58 -> 219.19816
A38: 0.095 | B38: =($B$13/(1+$A38)^1+$C$13/(1+$A38)^2+$D$13/(1+$A38)^3+$E$13/(1+$A38)^4+($E$13*(1+B$33)/($A38-B$33))/(1+$A38)^4+$B$23)/Assumptions!$B$58 -> 157.37744 | C38: =($B$13/(1+$A38)^1+$C$13/(1+$A38)^2+$D$13/(1+$A38)^3+$E$13/(1+$A38)^4+($E$13*(1+C$33)/($A38-C$33))/(1+$A38)^4+$B$23)/Assumptions!$B$58 -> 166.02819 | D38: =($B$13/(1+$A38)^1+$C$13/(1+$A38)^2+$D$13/(1+$A38)^3+$E$13/(1+$A38)^4+($E$13*(1+D$33)/($A38-D$33))/(1+$A38)^4+$B$23)/Assumptions!$B$58 -> 175.91477 | E38: =($B$13/(1+$A38)^1+$C$13/(1+$A38)^2+$D$13/(1+$A38)^3+$E$13/(1+$A38)^4+($E$13*(1+E$33)/($A38-E$33))/(1+$A38)^4+$B$23)/Assumptions!$B$58 -> 187.32237 | F38: =($B$13/(1+$A38)^1+$C$13/(1+$A38)^2+$D$13/(1+$A38)^3+$E$13/(1+$A38)^4+($E$13*(1+F$33)/($A38-F$33))/(1+$A38)^4+$B$23)/Assumptions!$B$58 -> 200.63122
A40: Base case (WACC 8.5%, g 2.5%) highlighted in navy. Change inputs on Assumptions sheet rows 37-47 to recalibrate.
A41: SENSITIVITY | Implied Share Price by Revenue Growth × Operating Margin
A42: Assumes WACC = Assumptions!B46, terminal g = Assumptions!B47, tax = Assumptions!B42, capex = Assumptions!G29.
A43: Rev Growth ↓ / Op Margin → | B43: 0.28 | C43: 0.3 | D43: 0.32 | E43: 0.34 | F43: 0.36
A44: 0.02 | B44: =((IS!$F$14*(1+$A44))*(B$43*(1-Assumptions!$B$50)-Assumptions!$G$37)/(1+Assumptions!$B$54)^1+(IS!$F$14*(1+$A44)^2)*(B$43*(1-Assumptions!$B$50)-Assumptions!$G$37)/(1+Assumptions!$B$54)^2+(IS!$F$14*(1+$A44)^3)*(B$43*(1-Assumptions!$B$50)-Assumptions!$G$37)/(1+Assumptions!$B$54)^3+(IS!$F$14*(1+$A44)^4)*(B$43*(1-Assumptions!$B$50)-Assumptions!$G$37)/(1+Assumptions!$B$54)^4+(IS!$F$14*(1+$A44)^4)*(B$43*(1-Assumptions!$B$50)-Assumptions!$G$37)*(1+Assumptions!$B$55)/(Assumptions!$B$54-Assumptions!$B$55)/(1+Assumptions!$B$54)^4+(BS!$F$5+BS!$F$6+BS!$F$15-BS!$F$42))/Assumptions!$B$58 -> 127.6063 | C44: =((IS!$F$14*(1+$A44))*(C$43*(1-Assumptions!$B$50)-Assumptions!$G$37)/(1+Assumptions!$B$54)^1+(IS!$F$14*(1+$A44)^2)*(C$43*(1-Assumptions!$B$50)-Assumptions!$G$37)/(1+Assumptions!$B$54)^2+(IS!$F$14*(1+$A44)^3)*(C$43*(1-Assumptions!$B$50)-Assumptions!$G$37)/(1+Assumptions!$B$54)^3+(IS!$F$14*(1+$A44)^4)*(C$43*(1-Assumptions!$B$50)-Assumptions!$G$37)/(1+Assumptions!$B$54)^4+(IS!$F$14*(1+$A44)^4)*(C$43*(1-Assumptions!$B$50)-Assumptions!$G$37)*(1+Assumptions!$B$55)/(Assumptions!$B$54-Assumptions!$B$55)/(1+Assumptions!$B$54)^4+(BS!$F$5+BS!$F$6+BS!$F$15-BS!$F$42))/Assumptions!$B$58 -> 137.38702 | D44: =((IS!$F$14*(1+$A44))*(D$43*(1-Assumptions!$B$50)-Assumptions!$G$37)/(1+Assumptions!$B$54)^1+(IS!$F$14*(1+$A44)^2)*(D$43*(1-Assumptions!$B$50)-Assumptions!$G$37)/(1+Assumptions!$B$54)^2+(IS!$F$14*(1+$A44)^3)*(D$43*(1-Assumptions!$B$50)-Assumptions!$G$37)/(1+Assumptions!$B$54)^3+(IS!$F$14*(1+$A44)^4)*(D$43*(1-Assumptions!$B$50)-Assumptions!$G$37)/(1+Assumptions!$B$54)^4+(IS!$F$14*(1+$A44)^4)*(D$43*(1-Assumptions!$B$50)-Assumptions!$G$37)*(1+Assumptions!$B$55)/(Assumptions!$B$54-Assumptions!$B$55)/(1+Assumptions!$B$54)^4+(BS!$F$5+BS!$F$6+BS!$F$15-BS!$F$42))/Assumptions!$B$58 -> 147.16773 | E44: =((IS!$F$14*(1+$A44))*(E$43*(1-Assumptions!$B$50)-Assumptions!$G$37)/(1+Assumptions!$B$54)^1+(IS!$F$14*(1+$A44)^2)*(E$43*(1-Assumptions!$B$50)-Assumptions!$G$37)/(1+Assumptions!$B$54)^2+(IS!$F$14*(1+$A44)^3)*(E$43*(1-Assumptions!$B$50)-Assumptions!$G$37)/(1+Assumptions!$B$54)^3+(IS!$F$14*(1+$A44)^4)*(E$43*(1-Assumptions!$B$50)-Assumptions!$G$37)/(1+Assumptions!$B$54)^4+(IS!$F$14*(1+$A44)^4)*(E$43*(1-Assumptions!$B$50)-Assumptions!$G$37)*(1+Assumptions!$B$55)/(Assumptions!$B$54-Assumptions!$B$55)/(1+Assumptions!$B$54)^4+(BS!$F$5+BS!$F$6+BS!$F$15-BS!$F$42))/Assumptions!$B$58 -> 156.94845 | F44: =((IS!$F$14*(1+$A44))*(F$43*(1-Assumptions!$B$50)-Assumptions!$G$37)/(1+Assumptions!$B$54)^1+(IS!$F$14*(1+$A44)^2)*(F$43*(1-Assumptions!$B$50)-Assumptions!$G$37)/(1+Assumptions!$B$54)^2+(IS!$F$14*(1+$A44)^3)*(F$43*(1-Assumptions!$B$50)-Assumptions!$G$37)/(1+Assumptions!$B$54)^3+(IS!$F$14*(1+$A44)^4)*(F$43*(1-Assumptions!$B$50)-Assumptions!$G$37)/(1+Assumptions!$B$54)^4+(IS!$F$14*(1+$A44)^4)*(F$43*(1-Assumptions!$B$50)-Assumptions!$G$37)*(1+Assumptions!$B$55)/(Assumptions!$B$54-Assumptions!$B$55)/(1+Assumptions!$B$54)^4+(BS!$F$5+BS!$F$6+BS!$F$15-BS!$F$42))/Assumptions!$B$58 -> 166.72916
A45: 0.035 | B45: =((IS!$F$14*(1+$A45))*(B$43*(1-Assumptions!$B$50)-Assumptions!$G$37)/(1+Assumptions!$B$54)^1+(IS!$F$14*(1+$A45)^2)*(B$43*(1-Assumptions!$B$50)-Assumptions!$G$37)/(1+Assumptions!$B$54)^2+(IS!$F$14*(1+$A45)^3)*(B$43*(1-Assumptions!$B$50)-Assumptions!$G$37)/(1+Assumptions!$B$54)^3+(IS!$F$14*(1+$A45)^4)*(B$43*(1-Assumptions!$B$50)-Assumptions!$G$37)/(1+Assumptions!$B$54)^4+(IS!$F$14*(1+$A45)^4)*(B$43*(1-Assumptions!$B$50)-Assumptions!$G$37)*(1+Assumptions!$B$55)/(Assumptions!$B$54-Assumptions!$B$55)/(1+Assumptions!$B$54)^4+(BS!$F$5+BS!$F$6+BS!$F$15-BS!$F$42))/Assumptions!$B$58 -> 134.5801 | C45: =((IS!$F$14*(1+$A45))*(C$43*(1-Assumptions!$B$50)-Assumptions!$G$37)/(1+Assumptions!$B$54)^1+(IS!$F$14*(1+$A45)^2)*(C$43*(1-Assumptions!$B$50)-Assumptions!$G$37)/(1+Assumptions!$B$54)^2+(IS!$F$14*(1+$A45)^3)*(C$43*(1-Assumptions!$B$50)-Assumptions!$G$37)/(1+Assumptions!$B$54)^3+(IS!$F$14*(1+$A45)^4)*(C$43*(1-Assumptions!$B$50)-Assumptions!$G$37)/(1+Assumptions!$B$54)^4+(IS!$F$14*(1+$A45)^4)*(C$43*(1-Assumptions!$B$50)-Assumptions!$G$37)*(1+Assumptions!$B$55)/(Assumptions!$B$54-Assumptions!$B$55)/(1+Assumptions!$B$54)^4+(BS!$F$5+BS!$F$6+BS!$F$15-BS!$F$42))/Assumptions!$B$58 -> 144.90968 | D45: =((IS!$F$14*(1+$A45))*(D$43*(1-Assumptions!$B$50)-Assumptions!$G$37)/(1+Assumptions!$B$54)^1+(IS!$F$14*(1+$A45)^2)*(D$43*(1-Assumptions!$B$50)-Assumptions!$G$37)/(1+Assumptions!$B$54)^2+(IS!$F$14*(1+$A45)^3)*(D$43*(1-Assumptions!$B$50)-Assumptions!$G$37)/(1+Assumptions!$B$54)^3+(IS!$F$14*(1+$A45)^4)*(D$43*(1-Assumptions!$B$50)-Assumptions!$G$37)/(1+Assumptions!$B$54)^4+(IS!$F$14*(1+$A45)^4)*(D$43*(1-Assumptions!$B$50)-Assumptions!$G$37)*(1+Assumptions!$B$55)/(Assumptions!$B$54-Assumptions!$B$55)/(1+Assumptions!$B$54)^4+(BS!$F$5+BS!$F$6+BS!$F$15-BS!$F$42))/Assumptions!$B$58 -> 155.23926 | E45: =((IS!$F$14*(1+$A45))*(E$43*(1-Assumptions!$B$50)-Assumptions!$G$37)/(1+Assumptions!$B$54)^1+(IS!$F$14*(1+$A45)^2)*(E$43*(1-Assumptions!$B$50)-Assumptions!$G$37)/(1+Assumptions!$B$54)^2+(IS!$F$14*(1+$A45)^3)*(E$43*(1-Assumptions!$B$50)-Assumptions!$G$37)/(1+Assumptions!$B$54)^3+(IS!$F$14*(1+$A45)^4)*(E$43*(1-Assumptions!$B$50)-Assumptions!$G$37)/(1+Assumptions!$B$54)^4+(IS!$F$14*(1+$A45)^4)*(E$43*(1-Assumptions!$B$50)-Assumptions!$G$37)*(1+Assumptions!$B$55)/(Assumptions!$B$54-Assumptions!$B$55)/(1+Assumptions!$B$54)^4+(BS!$F$5+BS!$F$6+BS!$F$15-BS!$F$42))/Assumptions!$B$58 -> 165.56884 | F45: =((IS!$F$14*(1+$A45))*(F$43*(1-Assumptions!$B$50)-Assumptions!$G$37)/(1+Assumptions!$B$54)^1+(IS!$F$14*(1+$A45)^2)*(F$43*(1-Assumptions!$B$50)-Assumptions!$G$37)/(1+Assumptions!$B$54)^2+(IS!$F$14*(1+$A45)^3)*(F$43*(1-Assumptions!$B$50)-Assumptions!$G$37)/(1+Assumptions!$B$54)^3+(IS!$F$14*(1+$A45)^4)*(F$43*(1-Assumptions!$B$50)-Assumptions!$G$37)/(1+Assumptions!$B$54)^4+(IS!$F$14*(1+$A45)^4)*(F$43*(1-Assumptions!$B$50)-Assumptions!$G$37)*(1+Assumptions!$B$55)/(Assumptions!$B$54-Assumptions!$B$55)/(1+Assumptions!$B$54)^4+(BS!$F$5+BS!$F$6+BS!$F$15-BS!$F$42))/Assumptions!$B$58 -> 175.89842
A46: 0.05 | B46: =((IS!$F$14*(1+$A46))*(B$43*(1-Assumptions!$B$50)-Assumptions!$G$37)/(1+Assumptions!$B$54)^1+(IS!$F$14*(1+$A46)^2)*(B$43*(1-Assumptions!$B$50)-Assumptions!$G$37)/(1+Assumptions!$B$54)^2+(IS!$F$14*(1+$A46)^3)*(B$43*(1-Assumptions!$B$50)-Assumptions!$G$37)/(1+Assumptions!$B$54)^3+(IS!$F$14*(1+$A46)^4)*(B$43*(1-Assumptions!$B$50)-Assumptions!$G$37)/(1+Assumptions!$B$54)^4+(IS!$F$14*(1+$A46)^4)*(B$43*(1-Assumptions!$B$50)-Assumptions!$G$37)*(1+Assumptions!$B$55)/(Assumptions!$B$54-Assumptions!$B$55)/(1+Assumptions!$B$54)^4+(BS!$F$5+BS!$F$6+BS!$F$15-BS!$F$42))/Assumptions!$B$58 -> 141.85193 | C46: =((IS!$F$14*(1+$A46))*(C$43*(1-Assumptions!$B$50)-Assumptions!$G$37)/(1+Assumptions!$B$54)^1+(IS!$F$14*(1+$A46)^2)*(C$43*(1-Assumptions!$B$50)-Assumptions!$G$37)/(1+Assumptions!$B$54)^2+(IS!$F$14*(1+$A46)^3)*(C$43*(1-Assumptions!$B$50)-Assumptions!$G$37)/(1+Assumptions!$B$54)^3+(IS!$F$14*(1+$A46)^4)*(C$43*(1-Assumptions!$B$50)-Assumptions!$G$37)/(1+Assumptions!$B$54)^4+(IS!$F$14*(1+$A46)^4)*(C$43*(1-Assumptions!$B$50)-Assumptions!$G$37)*(1+Assumptions!$B$55)/(Assumptions!$B$54-Assumptions!$B$55)/(1+Assumptions!$B$54)^4+(BS!$F$5+BS!$F$6+BS!$F$15-BS!$F$42))/Assumptions!$B$58 -> 152.75383 | D46: =((IS!$F$14*(1+$A46))*(D$43*(1-Assumptions!$B$50)-Assumptions!$G$37)/(1+Assumptions!$B$54)^1+(IS!$F$14*(1+$A46)^2)*(D$43*(1-Assumptions!$B$50)-Assumptions!$G$37)/(1+Assumptions!$B$54)^2+(IS!$F$14*(1+$A46)^3)*(D$43*(1-Assumptions!$B$50)-Assumptions!$G$37)/(1+Assumptions!$B$54)^3+(IS!$F$14*(1+$A46)^4)*(D$43*(1-Assumptions!$B$50)-Assumptions!$G$37)/(1+Assumptions!$B$54)^4+(IS!$F$14*(1+$A46)^4)*(D$43*(1-Assumptions!$B$50)-Assumptions!$G$37)*(1+Assumptions!$B$55)/(Assumptions!$B$54-Assumptions!$B$55)/(1+Assumptions!$B$54)^4+(BS!$F$5+BS!$F$6+BS!$F$15-BS!$F$42))/Assumptions!$B$58 -> 163.65573 | E46: =((IS!$F$14*(1+$A46))*(E$43*(1-Assumptions!$B$50)-Assumptions!$G$37)/(1+Assumptions!$B$54)^1+(IS!$F$14*(1+$A46)^2)*(E$43*(1-Assumptions!$B$50)-Assumptions!$G$37)/(1+Assumptions!$B$54)^2+(IS!$F$14*(1+$A46)^3)*(E$43*(1-Assumptions!$B$50)-Assumptions!$G$37)/(1+Assumptions!$B$54)^3+(IS!$F$14*(1+$A46)^4)*(E$43*(1-Assumptions!$B$50)-Assumptions!$G$37)/(1+Assumptions!$B$54)^4+(IS!$F$14*(1+$A46)^4)*(E$43*(1-Assumptions!$B$50)-Assumptions!$G$37)*(1+Assumptions!$B$55)/(Assumptions!$B$54-Assumptions!$B$55)/(1+Assumptions!$B$54)^4+(BS!$F$5+BS!$F$6+BS!$F$15-BS!$F$42))/Assumptions!$B$58 -> 174.55762 | F46: =((IS!$F$14*(1+$A46))*(F$43*(1-Assumptions!$B$50)-Assumptions!$G$37)/(1+Assumptions!$B$54)^1+(IS!$F$14*(1+$A46)^2)*(F$43*(1-Assumptions!$B$50)-Assumptions!$G$37)/(1+Assumptions!$B$54)^2+(IS!$F$14*(1+$A46)^3)*(F$43*(1-Assumptions!$B$50)-Assumptions!$G$37)/(1+Assumptions!$B$54)^3+(IS!$F$14*(1+$A46)^4)*(F$43*(1-Assumptions!$B$50)-Assumptions!$G$37)/(1+Assumptions!$B$54)^4+(IS!$F$14*(1+$A46)^4)*(F$43*(1-Assumptions!$B$50)-Assumptions!$G$37)*(1+Assumptions!$B$55)/(Assumptions!$B$54-Assumptions!$B$55)/(1+Assumptions!$B$54)^4+(BS!$F$5+BS!$F$6+BS!$F$15-BS!$F$42))/Assumptions!$B$58 -> 185.45952
A47: 0.065 | B47: =((IS!$F$14*(1+$A47))*(B$43*(1-Assumptions!$B$50)-Assumptions!$G$37)/(1+Assumptions!$B$54)^1+(IS!$F$14*(1+$A47)^2)*(B$43*(1-Assumptions!$B$50)-Assumptions!$G$37)/(1+Assumptions!$B$54)^2+(IS!$F$14*(1+$A47)^3)*(B$43*(1-Assumptions!$B$50)-Assumptions!$G$37)/(1+Assumptions!$B$54)^3+(IS!$F$14*(1+$A47)^4)*(B$43*(1-Assumptions!$B$50)-Assumptions!$G$37)/(1+Assumptions!$B$54)^4+(IS!$F$14*(1+$A47)^4)*(B$43*(1-Assumptions!$B$50)-Assumptions!$G$37)*(1+Assumptions!$B$55)/(Assumptions!$B$54-Assumptions!$B$55)/(1+Assumptions!$B$54)^4+(BS!$F$5+BS!$F$6+BS!$F$15-BS!$F$42))/Assumptions!$B$58 -> 149.43032 | C47: =((IS!$F$14*(1+$A47))*(C$43*(1-Assumptions!$B$50)-Assumptions!$G$37)/(1+Assumptions!$B$54)^1+(IS!$F$14*(1+$A47)^2)*(C$43*(1-Assumptions!$B$50)-Assumptions!$G$37)/(1+Assumptions!$B$54)^2+(IS!$F$14*(1+$A47)^3)*(C$43*(1-Assumptions!$B$50)-Assumptions!$G$37)/(1+Assumptions!$B$54)^3+(IS!$F$14*(1+$A47)^4)*(C$43*(1-Assumptions!$B$50)-Assumptions!$G$37)/(1+Assumptions!$B$54)^4+(IS!$F$14*(1+$A47)^4)*(C$43*(1-Assumptions!$B$50)-Assumptions!$G$37)*(1+Assumptions!$B$55)/(Assumptions!$B$54-Assumptions!$B$55)/(1+Assumptions!$B$54)^4+(BS!$F$5+BS!$F$6+BS!$F$15-BS!$F$42))/Assumptions!$B$58 -> 160.92866 | D47: =((IS!$F$14*(1+$A47))*(D$43*(1-Assumptions!$B$50)-Assumptions!$G$37)/(1+Assumptions!$B$54)^1+(IS!$F$14*(1+$A47)^2)*(D$43*(1-Assumptions!$B$50)-Assumptions!$G$37)/(1+Assumptions!$B$54)^2+(IS!$F$14*(1+$A47)^3)*(D$43*(1-Assumptions!$B$50)-Assumptions!$G$37)/(1+Assumptions!$B$54)^3+(IS!$F$14*(1+$A47)^4)*(D$43*(1-Assumptions!$B$50)-Assumptions!$G$37)/(1+Assumptions!$B$54)^4+(IS!$F$14*(1+$A47)^4)*(D$43*(1-Assumptions!$B$50)-Assumptions!$G$37)*(1+Assumptions!$B$55)/(Assumptions!$B$54-Assumptions!$B$55)/(1+Assumptions!$B$54)^4+(BS!$F$5+BS!$F$6+BS!$F$15-BS!$F$42))/Assumptions!$B$58 -> 172.42701 | E47: =((IS!$F$14*(1+$A47))*(E$43*(1-Assumptions!$B$50)-Assumptions!$G$37)/(1+Assumptions!$B$54)^1+(IS!$F$14*(1+$A47)^2)*(E$43*(1-Assumptions!$B$50)-Assumptions!$G$37)/(1+Assumptions!$B$54)^2+(IS!$F$14*(1+$A47)^3)*(E$43*(1-Assumptions!$B$50)-Assumptions!$G$37)/(1+Assumptions!$B$54)^3+(IS!$F$14*(1+$A47)^4)*(E$43*(1-Assumptions!$B$50)-Assumptions!$G$37)/(1+Assumptions!$B$54)^4+(IS!$F$14*(1+$A47)^4)*(E$43*(1-Assumptions!$B$50)-Assumptions!$G$37)*(1+Assumptions!$B$55)/(Assumptions!$B$54-Assumptions!$B$55)/(1+Assumptions!$B$54)^4+(BS!$F$5+BS!$F$6+BS!$F$15-BS!$F$42))/Assumptions!$B$58 -> 183.92536 | F47: =((IS!$F$14*(1+$A47))*(F$43*(1-Assumptions!$B$50)-Assumptions!$G$37)/(1+Assumptions!$B$54)^1+(IS!$F$14*(1+$A47)^2)*(F$43*(1-Assumptions!$B$50)-Assumptions!$G$37)/(1+Assumptions!$B$54)^2+(IS!$F$14*(1+$A47)^3)*(F$43*(1-Assumptions!$B$50)-Assumptions!$G$37)/(1+Assumptions!$B$54)^3+(IS!$F$14*(1+$A47)^4)*(F$43*(1-Assumptions!$B$50)-Assumptions!$G$37)/(1+Assumptions!$B$54)^4+(IS!$F$14*(1+$A47)^4)*(F$43*(1-Assumptions!$B$50)-Assumptions!$G$37)*(1+Assumptions!$B$55)/(Assumptions!$B$54-Assumptions!$B$55)/(1+Assumptions!$B$54)^4+(BS!$F$5+BS!$F$6+BS!$F$15-BS!$F$42))/Assumptions!$B$58 -> 195.4237
A48: 0.08 | B48: =((IS!$F$14*(1+$A48))*(B$43*(1-Assumptions!$B$50)-Assumptions!$G$37)/(1+Assumptions!$B$54)^1+(IS!$F$14*(1+$A48)^2)*(B$43*(1-Assumptions!$B$50)-Assumptions!$G$37)/(1+Assumptions!$B$54)^2+(IS!$F$14*(1+$A48)^3)*(B$43*(1-Assumptions!$B$50)-Assumptions!$G$37)/(1+Assumptions!$B$54)^3+(IS!$F$14*(1+$A48)^4)*(B$43*(1-Assumptions!$B$50)-Assumptions!$G$37)/(1+Assumptions!$B$54)^4+(IS!$F$14*(1+$A48)^4)*(B$43*(1-Assumptions!$B$50)-Assumptions!$G$37)*(1+Assumptions!$B$55)/(Assumptions!$B$54-Assumptions!$B$55)/(1+Assumptions!$B$54)^4+(BS!$F$5+BS!$F$6+BS!$F$15-BS!$F$42))/Assumptions!$B$58 -> 157.32393 | C48: =((IS!$F$14*(1+$A48))*(C$43*(1-Assumptions!$B$50)-Assumptions!$G$37)/(1+Assumptions!$B$54)^1+(IS!$F$14*(1+$A48)^2)*(C$43*(1-Assumptions!$B$50)-Assumptions!$G$37)/(1+Assumptions!$B$54)^2+(IS!$F$14*(1+$A48)^3)*(C$43*(1-Assumptions!$B$50)-Assumptions!$G$37)/(1+Assumptions!$B$54)^3+(IS!$F$14*(1+$A48)^4)*(C$43*(1-Assumptions!$B$50)-Assumptions!$G$37)/(1+Assumptions!$B$54)^4+(IS!$F$14*(1+$A48)^4)*(C$43*(1-Assumptions!$B$50)-Assumptions!$G$37)*(1+Assumptions!$B$55)/(Assumptions!$B$54-Assumptions!$B$55)/(1+Assumptions!$B$54)^4+(BS!$F$5+BS!$F$6+BS!$F$15-BS!$F$42))/Assumptions!$B$58 -> 169.44353 | D48: =((IS!$F$14*(1+$A48))*(D$43*(1-Assumptions!$B$50)-Assumptions!$G$37)/(1+Assumptions!$B$54)^1+(IS!$F$14*(1+$A48)^2)*(D$43*(1-Assumptions!$B$50)-Assumptions!$G$37)/(1+Assumptions!$B$54)^2+(IS!$F$14*(1+$A48)^3)*(D$43*(1-Assumptions!$B$50)-Assumptions!$G$37)/(1+Assumptions!$B$54)^3+(IS!$F$14*(1+$A48)^4)*(D$43*(1-Assumptions!$B$50)-Assumptions!$G$37)/(1+Assumptions!$B$54)^4+(IS!$F$14*(1+$A48)^4)*(D$43*(1-Assumptions!$B$50)-Assumptions!$G$37)*(1+Assumptions!$B$55)/(Assumptions!$B$54-Assumptions!$B$55)/(1+Assumptions!$B$54)^4+(BS!$F$5+BS!$F$6+BS!$F$15-BS!$F$42))/Assumptions!$B$58 -> 181.56313 | E48: =((IS!$F$14*(1+$A48))*(E$43*(1-Assumptions!$B$50)-Assumptions!$G$37)/(1+Assumptions!$B$54)^1+(IS!$F$14*(1+$A48)^2)*(E$43*(1-Assumptions!$B$50)-Assumptions!$G$37)/(1+Assumptions!$B$54)^2+(IS!$F$14*(1+$A48)^3)*(E$43*(1-Assumptions!$B$50)-Assumptions!$G$37)/(1+Assumptions!$B$54)^3+(IS!$F$14*(1+$A48)^4)*(E$43*(1-Assumptions!$B$50)-Assumptions!$G$37)/(1+Assumptions!$B$54)^4+(IS!$F$14*(1+$A48)^4)*(E$43*(1-Assumptions!$B$50)-Assumptions!$G$37)*(1+Assumptions!$B$55)/(Assumptions!$B$54-Assumptions!$B$55)/(1+Assumptions!$B$54)^4+(BS!$F$5+BS!$F$6+BS!$F$15-BS!$F$42))/Assumptions!$B$58 -> 193.68273 | F48: =((IS!$F$14*(1+$A48))*(F$43*(1-Assumptions!$B$50)-Assumptions!$G$37)/(1+Assumptions!$B$54)^1+(IS!$F$14*(1+$A48)^2)*(F$43*(1-Assumptions!$B$50)-Assumptions!$G$37)/(1+Assumptions!$B$54)^2+(IS!$F$14*(1+$A48)^3)*(F$43*(1-Assumptions!$B$50)-Assumptions!$G$37)/(1+Assumptions!$B$54)^3+(IS!$F$14*(1+$A48)^4)*(F$43*(1-Assumptions!$B$50)-Assumptions!$G$37)/(1+Assumptions!$B$54)^4+(IS!$F$14*(1+$A48)^4)*(F$43*(1-Assumptions!$B$50)-Assumptions!$G$37)*(1+Assumptions!$B$55)/(Assumptions!$B$54-Assumptions!$B$55)/(1+Assumptions!$B$54)^4+(BS!$F$5+BS!$F$6+BS!$F$15-BS!$F$42))/Assumptions!$B$58 -> 205.80234
A51: TORNADO | Sensitivity of Implied Share Price to Key Drivers (±1 standard move)
A52: Driver | B52: Low Case | C52: High Case | D52: Low Price | E52: High Price | F52: Swing ($) | G52: Notes
A53: Revenue growth (avg) | B53: -1.0% | C53: +1.0% | D53: =((IS!$F$14*(1+(AVERAGE(Assumptions!$G$8:$J$8))-0.01))*((AVERAGE(IS!$G$29:$J$29))*(1-(Assumptions!$B$50))-(Assumptions!$G$37))/(1+(Assumptions!$B$54))^1+(IS!$F$14*(1+(AVERAGE(Assumptions!$G$8:$J$8))-0.01)^2)*((AVERAGE(IS!$G$29:$J$29))*(1-(Assumptions!$B$50))-(Assumptions!$G$37))/(1+(Assumptions!$B$54))^2+(IS!$F$14*(1+(AVERAGE(Assumptions!$G$8:$J$8))-0.01)^3)*((AVERAGE(IS!$G$29:$J$29))*(1-(Assumptions!$B$50))-(Assumptions!$G$37))/(1+(Assumptions!$B$54))^3+(IS!$F$14*(1+(AVERAGE(Assumptions!$G$8:$J$8))-0.01)^4)*((AVERAGE(IS!$G$29:$J$29))*(1-(Assumptions!$B$50))-(Assumptions!$G$37))/(1+(Assumptions!$B$54))^4+(IS!$F$14*(1+(AVERAGE(Assumptions!$G$8:$J$8))-0.01)^4)*((AVERAGE(IS!$G$29:$J$29))*(1-(Assumptions!$B$50))-(Assumptions!$G$37))*(1+(Assumptions!$B$55))/((Assumptions!$B$54)-(Assumptions!$B$55))/(1+(Assumptions!$B$54))^4+(BS!$F$5+BS!$F$6+BS!$F$15-BS!$F$42))/Assumptions!$B$58 -> 198.0746 | E53: =((IS!$F$14*(1+(AVERAGE(Assumptions!$G$8:$J$8))+0.01))*((AVERAGE(IS!$G$29:$J$29))*(1-(Assumptions!$B$50))-(Assumptions!$G$37))/(1+(Assumptions!$B$54))^1+(IS!$F$14*(1+(AVERAGE(Assumptions!$G$8:$J$8))+0.01)^2)*((AVERAGE(IS!$G$29:$J$29))*(1-(Assumptions!$B$50))-(Assumptions!$G$37))/(1+(Assumptions!$B$54))^2+(IS!$F$14*(1+(AVERAGE(Assumptions!$G$8:$J$8))+0.01)^3)*((AVERAGE(IS!$G$29:$J$29))*(1-(Assumptions!$B$50))-(Assumptions!$G$37))/(1+(Assumptions!$B$54))^3+(IS!$F$14*(1+(AVERAGE(Assumptions!$G$8:$J$8))+0.01)^4)*((AVERAGE(IS!$G$29:$J$29))*(1-(Assumptions!$B$50))-(Assumptions!$G$37))/(1+(Assumptions!$B$54))^4+(IS!$F$14*(1+(AVERAGE(Assumptions!$G$8:$J$8))+0.01)^4)*((AVERAGE(IS!$G$29:$J$29))*(1-(Assumptions!$B$50))-(Assumptions!$G$37))*(1+(Assumptions!$B$55))/((Assumptions!$B$54)-(Assumptions!$B$55))/(1+(Assumptions!$B$54))^4+(BS!$F$5+BS!$F$6+BS!$F$15-BS!$F$42))/Assumptions!$B$58 -> 212.3628 | F53: =ABS(E53-D53) -> 14.288201 | G53: ±100 bps off 4% base
A54: Operating margin | B54: -200 bps | C54: +200 bps | D54: =((IS!$F$14*(1+AVERAGE(Assumptions!$G$8:$J$8)))*(((AVERAGE(IS!$G$29:$J$29))-0.02)*(1-(Assumptions!$B$50))-(Assumptions!$G$37))/(1+(Assumptions!$B$54))^1+(IS!$F$14*(1+AVERAGE(Assumptions!$G$8:$J$8))^2)*(((AVERAGE(IS!$G$29:$J$29))-0.02)*(1-(Assumptions!$B$50))-(Assumptions!$G$37))/(1+(Assumptions!$B$54))^2+(IS!$F$14*(1+AVERAGE(Assumptions!$G$8:$J$8))^3)*(((AVERAGE(IS!$G$29:$J$29))-0.02)*(1-(Assumptions!$B$50))-(Assumptions!$G$37))/(1+(Assumptions!$B$54))^3+(IS!$F$14*(1+AVERAGE(Assumptions!$G$8:$J$8))^4)*(((AVERAGE(IS!$G$29:$J$29))-0.02)*(1-(Assumptions!$B$50))-(Assumptions!$G$37))/(1+(Assumptions!$B$54))^4+(IS!$F$14*(1+AVERAGE(Assumptions!$G$8:$J$8))^4)*(((AVERAGE(IS!$G$29:$J$29))-0.02)*(1-(Assumptions!$B$50))-(Assumptions!$G$37))*(1+(Assumptions!$B$55))/((Assumptions!$B$54)-(Assumptions!$B$55))/(1+(Assumptions!$B$54))^4+(BS!$F$5+BS!$F$6+BS!$F$15-BS!$F$42))/Assumptions!$B$58 -> 193.77307 | E54: =((IS!$F$14*(1+AVERAGE(Assumptions!$G$8:$J$8)))*(((AVERAGE(IS!$G$29:$J$29))+0.02)*(1-(Assumptions!$B$50))-(Assumptions!$G$37))/(1+(Assumptions!$B$54))^1+(IS!$F$14*(1+AVERAGE(Assumptions!$G$8:$J$8))^2)*(((AVERAGE(IS!$G$29:$J$29))+0.02)*(1-(Assumptions!$B$50))-(Assumptions!$G$37))/(1+(Assumptions!$B$54))^2+(IS!$F$14*(1+AVERAGE(Assumptions!$G$8:$J$8))^3)*(((AVERAGE(IS!$G$29:$J$29))+0.02)*(1-(Assumptions!$B$50))-(Assumptions!$G$37))/(1+(Assumptions!$B$54))^3+(IS!$F$14*(1+AVERAGE(Assumptions!$G$8:$J$8))^4)*(((AVERAGE(IS!$G$29:$J$29))+0.02)*(1-(Assumptions!$B$50))-(Assumptions!$G$37))/(1+(Assumptions!$B$54))^4+(IS!$F$14*(1+AVERAGE(Assumptions!$G$8:$J$8))^4)*(((AVERAGE(IS!$G$29:$J$29))+0.02)*(1-(Assumptions!$B$50))-(Assumptions!$G$37))*(1+(Assumptions!$B$55))/((Assumptions!$B$54)-(Assumptions!$B$55))/(1+(Assumptions!$B$54))^4+(BS!$F$5+BS!$F$6+BS!$F$15-BS!$F$42))/Assumptions!$B$58 -> 216.4696 | F54: =ABS(E54-D54) -> 22.696533 | G54: ±200 bps off 32% base
A55: WACC | B55: +100 bps | C55: -100 bps | D55: =((IS!$F$14*(1+AVERAGE(Assumptions!$G$8:$J$8)))*((AVERAGE(IS!$G$29:$J$29))*(1-(Assumptions!$B$50))-(Assumptions!$G$37))/(1+((Assumptions!$B$54)+0.01))^1+(IS!$F$14*(1+AVERAGE(Assumptions!$G$8:$J$8))^2)*((AVERAGE(IS!$G$29:$J$29))*(1-(Assumptions!$B$50))-(Assumptions!$G$37))/(1+((Assumptions!$B$54)+0.01))^2+(IS!$F$14*(1+AVERAGE(Assumptions!$G$8:$J$8))^3)*((AVERAGE(IS!$G$29:$J$29))*(1-(Assumptions!$B$50))-(Assumptions!$G$37))/(1+((Assumptions!$B$54)+0.01))^3+(IS!$F$14*(1+AVERAGE(Assumptions!$G$8:$J$8))^4)*((AVERAGE(IS!$G$29:$J$29))*(1-(Assumptions!$B$50))-(Assumptions!$G$37))/(1+((Assumptions!$B$54)+0.01))^4+(IS!$F$14*(1+AVERAGE(Assumptions!$G$8:$J$8))^4)*((AVERAGE(IS!$G$29:$J$29))*(1-(Assumptions!$B$50))-(Assumptions!$G$37))*(1+(Assumptions!$B$55))/(((Assumptions!$B$54)+0.01)-(Assumptions!$B$55))/(1+((Assumptions!$B$54)+0.01))^4+(BS!$F$5+BS!$F$6+BS!$F$15-BS!$F$42))/Assumptions!$B$58 -> 170.01561 | E55: =((IS!$F$14*(1+AVERAGE(Assumptions!$G$8:$J$8)))*((AVERAGE(IS!$G$29:$J$29))*(1-(Assumptions!$B$50))-(Assumptions!$G$37))/(1+((Assumptions!$B$54)-0.01))^1+(IS!$F$14*(1+AVERAGE(Assumptions!$G$8:$J$8))^2)*((AVERAGE(IS!$G$29:$J$29))*(1-(Assumptions!$B$50))-(Assumptions!$G$37))/(1+((Assumptions!$B$54)-0.01))^2+(IS!$F$14*(1+AVERAGE(Assumptions!$G$8:$J$8))^3)*((AVERAGE(IS!$G$29:$J$29))*(1-(Assumptions!$B$50))-(Assumptions!$G$37))/(1+((Assumptions!$B$54)-0.01))^3+(IS!$F$14*(1+AVERAGE(Assumptions!$G$8:$J$8))^4)*((AVERAGE(IS!$G$29:$J$29))*(1-(Assumptions!$B$50))-(Assumptions!$G$37))/(1+((Assumptions!$B$54)-0.01))^4+(IS!$F$14*(1+AVERAGE(Assumptions!$G$8:$J$8))^4)*((AVERAGE(IS!$G$29:$J$29))*(1-(Assumptions!$B$50))-(Assumptions!$G$37))*(1+(Assumptions!$B$55))/(((Assumptions!$B$54)-0.01)-(Assumptions!$B$55))/(1+((Assumptions!$B$54)-0.01))^4+(BS!$F$5+BS!$F$6+BS!$F$15-BS!$F$42))/Assumptions!$B$58 -> 258.77621 | F55: =ABS(E55-D55) -> 88.760597 | G55: Lower WACC = higher PV
A56: Terminal growth | B56: -50 bps | C56: +50 bps | D56: =((IS!$F$14*(1+AVERAGE(Assumptions!$G$8:$J$8)))*((AVERAGE(IS!$G$29:$J$29))*(1-(Assumptions!$B$50))-(Assumptions!$G$37))/(1+(Assumptions!$B$54))^1+(IS!$F$14*(1+AVERAGE(Assumptions!$G$8:$J$8))^2)*((AVERAGE(IS!$G$29:$J$29))*(1-(Assumptions!$B$50))-(Assumptions!$G$37))/(1+(Assumptions!$B$54))^2+(IS!$F$14*(1+AVERAGE(Assumptions!$G$8:$J$8))^3)*((AVERAGE(IS!$G$29:$J$29))*(1-(Assumptions!$B$50))-(Assumptions!$G$37))/(1+(Assumptions!$B$54))^3+(IS!$F$14*(1+AVERAGE(Assumptions!$G$8:$J$8))^4)*((AVERAGE(IS!$G$29:$J$29))*(1-(Assumptions!$B$50))-(Assumptions!$G$37))/(1+(Assumptions!$B$54))^4+(IS!$F$14*(1+AVERAGE(Assumptions!$G$8:$J$8))^4)*((AVERAGE(IS!$G$29:$J$29))*(1-(Assumptions!$B$50))-(Assumptions!$G$37))*(1+((Assumptions!$B$55)-0.005))/((Assumptions!$B$54)-((Assumptions!$B$55)-0.005))/(1+(Assumptions!$B$54))^4+(BS!$F$5+BS!$F$6+BS!$F$15-BS!$F$42))/Assumptions!$B$58 -> 188.34571 | E56: =((IS!$F$14*(1+AVERAGE(Assumptions!$G$8:$J$8)))*((AVERAGE(IS!$G$29:$J$29))*(1-(Assumptions!$B$50))-(Assumptions!$G$37))/(1+(Assumptions!$B$54))^1+(IS!$F$14*(1+AVERAGE(Assumptions!$G$8:$J$8))^2)*((AVERAGE(IS!$G$29:$J$29))*(1-(Assumptions!$B$50))-(Assumptions!$G$37))/(1+(Assumptions!$B$54))^2+(IS!$F$14*(1+AVERAGE(Assumptions!$G$8:$J$8))^3)*((AVERAGE(IS!$G$29:$J$29))*(1-(Assumptions!$B$50))-(Assumptions!$G$37))/(1+(Assumptions!$B$54))^3+(IS!$F$14*(1+AVERAGE(Assumptions!$G$8:$J$8))^4)*((AVERAGE(IS!$G$29:$J$29))*(1-(Assumptions!$B$50))-(Assumptions!$G$37))/(1+(Assumptions!$B$54))^4+(IS!$F$14*(1+AVERAGE(Assumptions!$G$8:$J$8))^4)*((AVERAGE(IS!$G$29:$J$29))*(1-(Assumptions!$B$50))-(Assumptions!$G$37))*(1+((Assumptions!$B$55)+0.005))/((Assumptions!$B$54)-((Assumptions!$B$55)+0.005))/(1+(Assumptions!$B$54))^4+(BS!$F$5+BS!$F$6+BS!$F$15-BS!$F$42))/Assumptions!$B$58 -> 225.80965 | F56: =ABS(E56-D56) -> 37.463936 | G56: Gordon growth tail
A57: Effective tax rate | B57: +200 bps | C57: -200 bps | D57: =((IS!$F$14*(1+AVERAGE(Assumptions!$G$8:$J$8)))*((AVERAGE(IS!$G$29:$J$29))*(1-((Assumptions!$B$50)+0.02))-(Assumptions!$G$37))/(1+(Assumptions!$B$54))^1+(IS!$F$14*(1+AVERAGE(Assumptions!$G$8:$J$8))^2)*((AVERAGE(IS!$G$29:$J$29))*(1-((Assumptions!$B$50)+0.02))-(Assumptions!$G$37))/(1+(Assumptions!$B$54))^2+(IS!$F$14*(1+AVERAGE(Assumptions!$G$8:$J$8))^3)*((AVERAGE(IS!$G$29:$J$29))*(1-((Assumptions!$B$50)+0.02))-(Assumptions!$G$37))/(1+(Assumptions!$B$54))^3+(IS!$F$14*(1+AVERAGE(Assumptions!$G$8:$J$8))^4)*((AVERAGE(IS!$G$29:$J$29))*(1-((Assumptions!$B$50)+0.02))-(Assumptions!$G$37))/(1+(Assumptions!$B$54))^4+(IS!$F$14*(1+AVERAGE(Assumptions!$G$8:$J$8))^4)*((AVERAGE(IS!$G$29:$J$29))*(1-((Assumptions!$B$50)+0.02))-(Assumptions!$G$37))*(1+(Assumptions!$B$55))/((Assumptions!$B$54)-(Assumptions!$B$55))/(1+(Assumptions!$B$54))^4+(BS!$F$5+BS!$F$6+BS!$F$15-BS!$F$42))/Assumptions!$B$58 -> 200.02784 | E57: =((IS!$F$14*(1+AVERAGE(Assumptions!$G$8:$J$8)))*((AVERAGE(IS!$G$29:$J$29))*(1-((Assumptions!$B$50)-0.02))-(Assumptions!$G$37))/(1+(Assumptions!$B$54))^1+(IS!$F$14*(1+AVERAGE(Assumptions!$G$8:$J$8))^2)*((AVERAGE(IS!$G$29:$J$29))*(1-((Assumptions!$B$50)-0.02))-(Assumptions!$G$37))/(1+(Assumptions!$B$54))^2+(IS!$F$14*(1+AVERAGE(Assumptions!$G$8:$J$8))^3)*((AVERAGE(IS!$G$29:$J$29))*(1-((Assumptions!$B$50)-0.02))-(Assumptions!$G$37))/(1+(Assumptions!$B$54))^3+(IS!$F$14*(1+AVERAGE(Assumptions!$G$8:$J$8))^4)*((AVERAGE(IS!$G$29:$J$29))*(1-((Assumptions!$B$50)-0.02))-(Assumptions!$G$37))/(1+(Assumptions!$B$54))^4+(IS!$F$14*(1+AVERAGE(Assumptions!$G$8:$J$8))^4)*((AVERAGE(IS!$G$29:$J$29))*(1-((Assumptions!$B$50)-0.02))-(Assumptions!$G$37))*(1+(Assumptions!$B$55))/((Assumptions!$B$54)-(Assumptions!$B$55))/(1+(Assumptions!$B$54))^4+(BS!$F$5+BS!$F$6+BS!$F$15-BS!$F$42))/Assumptions!$B$58 -> 210.21484 | F57: =ABS(E57-D57) -> 10.186995 | G57: Higher tax cuts NOPAT
A58: CapEx % revenue | B58: +50 bps | C58: -50 bps | D58: =((IS!$F$14*(1+AVERAGE(Assumptions!$G$8:$J$8)))*((AVERAGE(IS!$G$29:$J$29))*(1-(Assumptions!$B$50))-((Assumptions!$G$37)+0.005))/(1+(Assumptions!$B$54))^1+(IS!$F$14*(1+AVERAGE(Assumptions!$G$8:$J$8))^2)*((AVERAGE(IS!$G$29:$J$29))*(1-(Assumptions!$B$50))-((Assumptions!$G$37)+0.005))/(1+(Assumptions!$B$54))^2+(IS!$F$14*(1+AVERAGE(Assumptions!$G$8:$J$8))^3)*((AVERAGE(IS!$G$29:$J$29))*(1-(Assumptions!$B$50))-((Assumptions!$G$37)+0.005))/(1+(Assumptions!$B$54))^3+(IS!$F$14*(1+AVERAGE(Assumptions!$G$8:$J$8))^4)*((AVERAGE(IS!$G$29:$J$29))*(1-(Assumptions!$B$50))-((Assumptions!$G$37)+0.005))/(1+(Assumptions!$B$54))^4+(IS!$F$14*(1+AVERAGE(Assumptions!$G$8:$J$8))^4)*((AVERAGE(IS!$G$29:$J$29))*(1-(Assumptions!$B$50))-((Assumptions!$G$37)+0.005))*(1+(Assumptions!$B$55))/((Assumptions!$B$54)-(Assumptions!$B$55))/(1+(Assumptions!$B$54))^4+(BS!$F$5+BS!$F$6+BS!$F$15-BS!$F$42))/Assumptions!$B$58 -> 201.78361 | E58: =((IS!$F$14*(1+AVERAGE(Assumptions!$G$8:$J$8)))*((AVERAGE(IS!$G$29:$J$29))*(1-(Assumptions!$B$50))-((Assumptions!$G$37)-0.005))/(1+(Assumptions!$B$54))^1+(IS!$F$14*(1+AVERAGE(Assumptions!$G$8:$J$8))^2)*((AVERAGE(IS!$G$29:$J$29))*(1-(Assumptions!$B$50))-((Assumptions!$G$37)-0.005))/(1+(Assumptions!$B$54))^2+(IS!$F$14*(1+AVERAGE(Assumptions!$G$8:$J$8))^3)*((AVERAGE(IS!$G$29:$J$29))*(1-(Assumptions!$B$50))-((Assumptions!$G$37)-0.005))/(1+(Assumptions!$B$54))^3+(IS!$F$14*(1+AVERAGE(Assumptions!$G$8:$J$8))^4)*((AVERAGE(IS!$G$29:$J$29))*(1-(Assumptions!$B$50))-((Assumptions!$G$37)-0.005))/(1+(Assumptions!$B$54))^4+(IS!$F$14*(1+AVERAGE(Assumptions!$G$8:$J$8))^4)*((AVERAGE(IS!$G$29:$J$29))*(1-(Assumptions!$B$50))-((Assumptions!$G$37)-0.005))*(1+(Assumptions!$B$55))/((Assumptions!$B$54)-(Assumptions!$B$55))/(1+(Assumptions!$B$54))^4+(BS!$F$5+BS!$F$6+BS!$F$15-BS!$F$42))/Assumptions!$B$58 -> 208.45906 | F58: =ABS(E58-D58) -> 6.6754509 | G58: Higher capex = lower FCF
A64: FOOTBALL FIELD | Valuation Range by Methodology (Implied $/share)
A65: Methodology | B65: Low | C65: Mid | D65: High | E65: Range Width | F65: Notes
A66: DCF — Bear case | B66: =B44 -> 127.6063 | C66: =AVERAGE(B44:B45) -> 131.0932 | D66: =B45 -> 134.5801 | E66: =D66-B66 -> 6.9737979 | F66: Low growth 2-3% × OM 28%
A67: DCF — Base case | B67: =C45 -> 144.90968 | C67: =AVERAGE(C45:D46) -> 154.13962 | D67: =D46 -> 163.65573 | E67: =D67-B67 -> 18.746045 | F67: Growth 3.5-5% × OM 30-32%
A68: DCF — Bull case | B68: =E47 -> 183.92536 | C68: =AVERAGE(E47:F48) -> 194.70853 | D68: =F48 -> 205.80234 | E68: =D68-B68 -> 21.87698 | F68: Growth 6.5-8% × OM 34-36%
A69: P/E multiple (22-30x) | B69: =IS!$J$38*22/Assumptions!$B$58 -> 292.13695 | C69: =IS!$J$38*26/Assumptions!$B$58 -> 345.25275 | D69: =IS!$J$38*30/Assumptions!$B$58 -> 398.36856 | E69: =D69-B69 -> 106.23162 | F69: FY29E EPS × 22–30x range
A70: EV/EBITDA (16-22x) | B70: =((IS!$J$28+CFS!$J$10)*16+(BS!$F$5+BS!$F$6+BS!$F$15-BS!$F$42))/Assumptions!$B$58 -> 262.31128 | C70: =((IS!$J$28+CFS!$J$10)*19+(BS!$F$5+BS!$F$6+BS!$F$15-BS!$F$42))/Assumptions!$B$58 -> 310.86958 | D70: =((IS!$J$28+CFS!$J$10)*22+(BS!$F$5+BS!$F$6+BS!$F$15-BS!$F$42))/Assumptions!$B$58 -> 359.42788 | E70: =D70-B70 -> 97.116597 | F70: FY29E EBITDA × 16–22x
A71: 52-week range | B71: 175 | C71: 217.5 | D71: 260 | E71: =D71-B71 -> 85 | F71: 12-month trading range
A72: Analyst target (consensus) | B72: 215 | C72: 245 | D72: 285 | E72: =D72-B72 -> 70 | F72: Wall Street range
A73: Current share price | B73: =Assumptions!$B$59 -> 232.5 | C73: =Assumptions!$B$59 -> 232.5 | D73: =Assumptions!$B$59 -> 232.5 | E73: 0 | F73: Live from Assumptions!B51

Sheet Validation
A1: DATA VALIDATION | 10-K Source Audit Trail
A2: Live error-detection dashboard — historical values vs. 10-K + structural integrity + forecast sanity checks
A3: MODEL HEALTH | B3: =IF(AND(E80=0,COUNTIF(B114:J114,"✓")=9,COUNTIF(B115:J115,"✓")+COUNTIF(B115:J115,"n/a")=9),"✅ ALL CHECKS PASS","⚠ "&(E80+(9-COUNTIF(B114:J114,"✓"))+(9-COUNTIF(B115:J115,"✓")-COUNTIF(B115:J115,"n/a")))&" ISSUES — see details below") -> ✅ ALL CHECKS PASS
A5: SOURCE DOCUMENTS
A6: [1] | B6: Apple Inc. Form 10-K FY2025 | E6: Filed Oct 31, 2025 | F6: Primary source for FY23, FY24, FY25 line items | H6: Open 10-K on SEC.gov →
A7: [2] | B7: Apple Inc. Form 10-K FY2022 | E7: Filed Oct 28, 2022 | F7: Primary source for FY20, FY21, FY22 line items | H7: Open 10-K on SEC.gov →
A8: [3] | B8: Apple Inc. Form 10-K FY2023 | E8: Filed Nov 3, 2023 | F8: Cross-verification for FY21, FY22, FY23 | H8: Open 10-K on SEC.gov →
A9: [4] | B9: Apple FY25 Q4 Press Release | E9: Released Oct 30, 2025 | F9: Full FY25 + FY24 consolidated statements PDF | H9: Open Apple PDF →
A10: [5] | B10: Apple FY22 Q4 Press Release | E10: Released Oct 27, 2022 | F10: Full FY22 + FY21 consolidated statements PDF | H10: Open Apple PDF →
A11: [6] | B11: SEC EDGAR — All Apple 10-K filings | E11: Live SEC database | F11: Browse all Apple Inc. 10-K filings (CIK: 0000320193) | H11: Browse SEC EDGAR →
A12: [7] | B12: Apple Investor Relations | E12: Live company page | F12: All SEC filings, press releases, financial data | H12: Open Apple IR page →
A14: INCOME STATEMENT | Historical Validation (USD Millions)
A15: Line item | B15: FY21A | C15: FY22A | D15: FY23A | E15: FY24A | F15: FY25A | G15: Check | H15: Source
A16: Products revenue | B16: 297392 | C16: 316199 | D16: 298085 | E16: 294866 | F16: 307003 | G16: {=IF(SUMPRODUCT(ABS(B16:F16-IS!B8:F8))<1,"✓","✗ "&TEXT(SUMPRODUCT(ABS(B16:F16-IS!B8:F8)),"#,##0.0"))} -> ✓ | H16: 10-K FY22/FY25 p.29
A17: Services revenue | B17: 68425 | C17: 78129 | D17: 85200 | E17: 96169 | F17: 109158 | G17: {=IF(SUMPRODUCT(ABS(B17:F17-IS!B13:F13))<1,"✓","✗ "&TEXT(SUMPRODUCT(ABS(B17:F17-IS!B13:F13)),"#,##0.0"))} -> ✓ | H17: 10-K FY22/FY25 p.29
A18: Total revenue (calc) | B18: 365817 | C18: 394328 | D18: 383285 | E18: 391035 | F18: 416161 | G18: {=IF(SUMPRODUCT(ABS(B18:F18-IS!B14:F14))<1,"✓","✗ "&TEXT(SUMPRODUCT(ABS(B18:F18-IS!B14:F14)),"#,##0.0"))} -> ✓ | H18: Calculated
A19: Cost of products | B19: 192266 | C19: 201471 | D19: 189282 | E19: 185233 | F19: 194116 | G19: {=IF(SUMPRODUCT(ABS(B19:F19-IS!B18:F18))<1,"✓","✗ "&TEXT(SUMPRODUCT(ABS(B19:F19-IS!B18:F18)),"#,##0.0"))} -> ✓ | H19: 10-K FY22/FY25 p.29
A20: Cost of services | B20: 20715 | C20: 22075 | D20: 24855 | E20: 25119 | F20: 26844 | G20: {=IF(SUMPRODUCT(ABS(B20:F20-IS!B19:F19))<1,"✓","✗ "&TEXT(SUMPRODUCT(ABS(B20:F20-IS!B19:F19)),"#,##0.0"))} -> ✓ | H20: 10-K FY22/FY25 p.29
A21: Total cost of sales | B21: 212981 | C21: 223546 | D21: 214137 | E21: 210352 | F21: 220960 | G21: {=IF(SUMPRODUCT(ABS(B21:F21-IS!B20:F20))<1,"✓","✗ "&TEXT(SUMPRODUCT(ABS(B21:F21-IS!B20:F20)),"#,##0.0"))} -> ✓ | H21: Calculated
A22: Gross profit (calc) | B22: 152836 | C22: 170782 | D22: 169148 | E22: 180683 | F22: 195201 | G22: {=IF(SUMPRODUCT(ABS(B22:F22-IS!B21:F21))<1,"✓","✗ "&TEXT(SUMPRODUCT(ABS(B22:F22-IS!B21:F21)),"#,##0.0"))} -> ✓ | H22: Calculated
A23: R&D expense | B23: 21914 | C23: 26251 | D23: 29915 | E23: 31370 | F23: 34550 | G23: {=IF(SUMPRODUCT(ABS(B23:F23-IS!B25:F25))<1,"✓","✗ "&TEXT(SUMPRODUCT(ABS(B23:F23-IS!B25:F25)),"#,##0.0"))} -> ✓ | H23: 10-K FY22/FY25 p.29
A24: SG&A expense | B24: 21973 | C24: 25094 | D24: 24932 | E24: 26097 | F24: 27601 | G24: {=IF(SUMPRODUCT(ABS(B24:F24-IS!B26:F26))<1,"✓","✗ "&TEXT(SUMPRODUCT(ABS(B24:F24-IS!B26:F26)),"#,##0.0"))} -> ✓ | H24: 10-K FY22/FY25 p.29
A25: Total operating expenses | B25: 43887 | C25: 51345 | D25: 54847 | E25: 57467 | F25: 62151 | G25: {=IF(SUMPRODUCT(ABS(B25:F25-IS!B27:F27))<1,"✓","✗ "&TEXT(SUMPRODUCT(ABS(B25:F25-IS!B27:F27)),"#,##0.0"))} -> ✓ | H25: Calculated
A26: Operating income (calc) | B26: 108949 | C26: 119437 | D26: 114301 | E26: 123216 | F26: 133050 | G26: {=IF(SUMPRODUCT(ABS(B26:F26-IS!B28:F28))<1,"✓","✗ "&TEXT(SUMPRODUCT(ABS(B26:F26-IS!B28:F28)),"#,##0.0"))} -> ✓ | H26: 10-K FY22/FY25 p.29
A27: Other income/(expense) | B27: 258 | C27: -334 | D27: -565 | E27: 269 | F27: -321 | G27: {=IF(SUMPRODUCT(ABS(B27:F27-IS!B34:F34))<1,"✓","✗ "&TEXT(SUMPRODUCT(ABS(B27:F27-IS!B34:F34)),"#,##0.0"))} -> ✓ | H27: 10-K FY22/FY25 p.29
A28: Pre-tax income (calc) | B28: 109207 | C28: 119103 | D28: 113736 | E28: 123485 | F28: 132729 | G28: {=IF(SUMPRODUCT(ABS(B28:F28-IS!B35:F35))<1,"✓","✗ "&TEXT(SUMPRODUCT(ABS(B28:F28-IS!B35:F35)),"#,##0.0"))} -> ✓ | H28: Calculated
A29: Income tax expense | B29: 14527 | C29: 19300 | D29: 16741 | E29: 29749 | F29: 20719 | G29: {=IF(SUMPRODUCT(ABS(B29:F29-IS!B36:F36))<1,"✓","✗ "&TEXT(SUMPRODUCT(ABS(B29:F29-IS!B36:F36)),"#,##0.0"))} -> ✓ | H29: 10-K FY22/FY25 p.29
A30: Net income (calc) | B30: 94680 | C30: 99803 | D30: 96995 | E30: 93736 | F30: 112010 | G30: {=IF(SUMPRODUCT(ABS(B30:F30-IS!B38:F38))<1,"✓","✗ "&TEXT(SUMPRODUCT(ABS(B30:F30-IS!B38:F38)),"#,##0.0"))} -> ✓ | H30: 10-K FY22/FY25 p.29
A31: Diluted EPS ($) | B31: 5.61 | C31: 6.11 | D31: 6.13 | E31: 6.08 | F31: 7.46 | G31: {=IF(SUMPRODUCT(ABS(B31:F31-IS!B43:F43))<0.05,"✓","✗ "&TEXT(SUMPRODUCT(ABS(B31:F31-IS!B43:F43)),"#,##0.0"))} -> ✓ | H31: 10-K FY22/FY25 p.29
A34: BALANCE SHEET | Historical Validation (USD Millions)
A35: Line item | B35: FY21A | C35: FY22A | D35: FY23A | E35: FY24A | F35: FY25A | G35: Check | H35: Source
A36: Cash & equivalents | B36: 34940 | C36: 23646 | D36: 29965 | E36: 29943 | F36: 35934 | G36: =IF((ABS(B36-(BS!C5))+ABS(C36-(BS!D5))+ABS(D36-(BS!E5))+ABS(E36-(BS!F5))+ABS(F36-(BS!G5)))<5,"✓","✗ "&TEXT(ABS(B36-(BS!C5))+ABS(C36-(BS!D5))+ABS(D36-(BS!E5))+ABS(E36-(BS!F5))+ABS(F36-(BS!G5)),"#,##0")) -> ✓ | H36: 10-K FY22/FY23/FY25 p.31
A37: Marketable securities (current) | B37: 27699 | C37: 24658 | D37: 31590 | E37: 35228 | F37: 18763 | G37: =IF((ABS(B37-(BS!C6))+ABS(C37-(BS!D6))+ABS(D37-(BS!E6))+ABS(E37-(BS!F6))+ABS(F37-(BS!G6)))<5,"✓","✗ "&TEXT(ABS(B37-(BS!C6))+ABS(C37-(BS!D6))+ABS(D37-(BS!E6))+ABS(E37-(BS!F6))+ABS(F37-(BS!G6)),"#,##0")) -> ✓ | H37: 10-K FY22/FY23/FY25 p.31
A38: Marketable securities (non-curr) | B38: 127877 | C38: 120805 | D38: 100544 | E38: 91479 | F38: 77723 | G38: =IF((ABS(B38-(BS!C15))+ABS(C38-(BS!D15))+ABS(D38-(BS!E15))+ABS(E38-(BS!F15))+ABS(F38-(BS!G15)))<5,"✓","✗ "&TEXT(ABS(B38-(BS!C15))+ABS(C38-(BS!D15))+ABS(D38-(BS!E15))+ABS(E38-(BS!F15))+ABS(F38-(BS!G15)),"#,##0")) -> ✓ | H38: 10-K FY22/FY23/FY25 p.31
A39: Accounts receivable, net | B39: 26278 | C39: 28184 | D39: 29508 | E39: 33410 | F39: 39777 | G39: =IF((ABS(B39-(BS!C7))+ABS(C39-(BS!D7))+ABS(D39-(BS!E7))+ABS(E39-(BS!F7))+ABS(F39-(BS!G7)))<5,"✓","✗ "&TEXT(ABS(B39-(BS!C7))+ABS(C39-(BS!D7))+ABS(D39-(BS!E7))+ABS(E39-(BS!F7))+ABS(F39-(BS!G7)),"#,##0")) -> ✓ | H39: 10-K FY22/FY23/FY25 p.31
A40: Inventory | B40: 6580 | C40: 4946 | D40: 6331 | E40: 7286 | F40: 5718 | G40: =IF((ABS(B40-(BS!C8))+ABS(C40-(BS!D8))+ABS(D40-(BS!E8))+ABS(E40-(BS!F8))+ABS(F40-(BS!G8)))<5,"✓","✗ "&TEXT(ABS(B40-(BS!C8))+ABS(C40-(BS!D8))+ABS(D40-(BS!E8))+ABS(E40-(BS!F8))+ABS(F40-(BS!G8)),"#,##0")) -> ✓ | H40: 10-K FY22/FY23/FY25 p.31
A41: Other CA (vendor + other) | B41: 39339 | C41: 53971 | D41: 46172 | E41: 47120 | F41: 47765 | G41: =IF((ABS(B41-(BS!C9+BS!C10))+ABS(C41-(BS!D9+BS!D10))+ABS(D41-(BS!E9+BS!E10))+ABS(E41-(BS!F9+BS!F10))+ABS(F41-(BS!G9+BS!G10)))<5,"✓","✗ "&TEXT(ABS(B41-(BS!C9+BS!C10))+ABS(C41-(BS!D9+BS!D10))+ABS(D41-(BS!E9+BS!E10))+ABS(E41-(BS!F9+BS!F10))+ABS(F41-(BS!G9+BS!G10)),"#,##0")) -> ✓ | H41: 10-K (Vendor non-trade + Other CA)
A42: Total current assets | B42: 134836 | C42: 135405 | D42: 143566 | E42: 152987 | F42: 147957 | G42: =IF((ABS(B42-(BS!C11))+ABS(C42-(BS!D11))+ABS(D42-(BS!E11))+ABS(E42-(BS!F11))+ABS(F42-(BS!G11)))<5,"✓","✗ "&TEXT(ABS(B42-(BS!C11))+ABS(C42-(BS!D11))+ABS(D42-(BS!E11))+ABS(E42-(BS!F11))+ABS(F42-(BS!G11)),"#,##0")) -> ✓ | H42: Calculated
A43: Property, plant & equipment, net | B43: 39440 | C43: 42117 | D43: 43715 | E43: 45680 | F43: 49834 | G43: =IF((ABS(B43-(BS!C14))+ABS(C43-(BS!D14))+ABS(D43-(BS!E14))+ABS(E43-(BS!F14))+ABS(F43-(BS!G14)))<5,"✓","✗ "&TEXT(ABS(B43-(BS!C14))+ABS(C43-(BS!D14))+ABS(D43-(BS!E14))+ABS(E43-(BS!F14))+ABS(F43-(BS!G14)),"#,##0")) -> ✓ | H43: 10-K FY22/FY23/FY25 p.31
A44: Other non-current assets | B44: 48849 | C44: 54428 | D44: 64758 | E44: 74834 | F44: 83727 | G44: =IF((ABS(B44-(BS!C16))+ABS(C44-(BS!D16))+ABS(D44-(BS!E16))+ABS(E44-(BS!F16))+ABS(F44-(BS!G16)))<5,"✓","✗ "&TEXT(ABS(B44-(BS!C16))+ABS(C44-(BS!D16))+ABS(D44-(BS!E16))+ABS(E44-(BS!F16))+ABS(F44-(BS!G16)),"#,##0")) -> ✓ | H44: 10-K FY22/FY23/FY25 p.31
A45: Total assets | B45: 351002 | C45: 352755 | D45: 352583 | E45: 364980 | F45: 359241 | G45: =IF((ABS(B45-(BS!C18))+ABS(C45-(BS!D18))+ABS(D45-(BS!E18))+ABS(E45-(BS!F18))+ABS(F45-(BS!G18)))<5,"✓","✗ "&TEXT(ABS(B45-(BS!C18))+ABS(C45-(BS!D18))+ABS(D45-(BS!E18))+ABS(E45-(BS!F18))+ABS(F45-(BS!G18)),"#,##0")) -> ✓ | H45: 10-K FY22/FY23/FY25 p.31
A46: Accounts payable | B46: 54763 | C46: 64115 | D46: 62611 | E46: 68960 | F46: 69860 | G46: =IF((ABS(B46-(BS!C21))+ABS(C46-(BS!D21))+ABS(D46-(BS!E21))+ABS(E46-(BS!F21))+ABS(F46-(BS!G21)))<5,"✓","✗ "&TEXT(ABS(B46-(BS!C21))+ABS(C46-(BS!D21))+ABS(D46-(BS!E21))+ABS(E46-(BS!F21))+ABS(F46-(BS!G21)),"#,##0")) -> ✓ | H46: 10-K FY22/FY23/FY25 p.31
A47: Other CL (bundled) | B47: 70718 | C47: 89867 | D47: 82697 | E47: 107432 | F47: 95771 | G47: =IF((ABS(B47-(BS!C22+BS!C23+BS!C24+BS!C25))+ABS(C47-(BS!D22+BS!D23+BS!D24+BS!D25))+ABS(D47-(BS!E22+BS!E23+BS!E24+BS!E25))+ABS(E47-(BS!F22+BS!F23+BS!F24+BS!F25))+ABS(F47-(BS!G22+BS!G23+BS!G24+BS!G25)))<5,"✓","✗ "&TEXT(ABS(B47-(BS!C22+BS!C23+BS!C24+BS!C25))+ABS(C47-(BS!D22+BS!D23+BS!D24+BS!D25))+ABS(D47-(BS!E22+BS!E23+BS!E24+BS!E25))+ABS(E47-(BS!F22+BS!F23+BS!F24+BS!F25))+ABS(F47-(BS!G22+BS!G23+BS!G24+BS!G25)),"#,##0")) -> ✓ | H47: 10-K (OCL+def rev+CP+curr TD)
A48: Total current liabilities | B48: 125481 | C48: 153982 | D48: 145308 | E48: 176392 | F48: 165631 | G48: =IF((ABS(B48-(BS!C26))+ABS(C48-(BS!D26))+ABS(D48-(BS!E26))+ABS(E48-(BS!F26))+ABS(F48-(BS!G26)))<5,"✓","✗ "&TEXT(ABS(B48-(BS!C26))+ABS(C48-(BS!D26))+ABS(D48-(BS!E26))+ABS(E48-(BS!F26))+ABS(F48-(BS!G26)),"#,##0")) -> ✓ | H48: Calculated
A49: Long-term debt (non-current) | B49: 109106 | C49: 98959 | D49: 95281 | E49: 85750 | F49: 78328 | G49: =IF((ABS(B49-(BS!C29))+ABS(C49-(BS!D29))+ABS(D49-(BS!E29))+ABS(E49-(BS!F29))+ABS(F49-(BS!G29)))<5,"✓","✗ "&TEXT(ABS(B49-(BS!C29))+ABS(C49-(BS!D29))+ABS(D49-(BS!E29))+ABS(E49-(BS!F29))+ABS(F49-(BS!G29)),"#,##0")) -> ✓ | H49: 10-K FY22/FY23/FY25 p.31
A50: Other non-current liabilities | B50: 53325 | C50: 49142 | D50: 49848 | E50: 45888 | F50: 41549 | G50: =IF((ABS(B50-(BS!C30))+ABS(C50-(BS!D30))+ABS(D50-(BS!E30))+ABS(E50-(BS!F30))+ABS(F50-(BS!G30)))<5,"✓","✗ "&TEXT(ABS(B50-(BS!C30))+ABS(C50-(BS!D30))+ABS(D50-(BS!E30))+ABS(E50-(BS!F30))+ABS(F50-(BS!G30)),"#,##0")) -> ✓ | H50: 10-K FY22/FY23/FY25 p.31
A51: Total liabilities | B51: 287912 | C51: 302083 | D51: 290437 | E51: 308030 | F51: 285508 | G51: =IF((ABS(B51-(BS!C32))+ABS(C51-(BS!D32))+ABS(D51-(BS!E32))+ABS(E51-(BS!F32))+ABS(F51-(BS!G32)))<5,"✓","✗ "&TEXT(ABS(B51-(BS!C32))+ABS(C51-(BS!D32))+ABS(D51-(BS!E32))+ABS(E51-(BS!F32))+ABS(F51-(BS!G32)),"#,##0")) -> ✓ | H51: 10-K FY22/FY23/FY25 p.31
A52: Shareholders' equity | B52: 63090 | C52: 50672 | D52: 62146 | E52: 56950 | F52: 73733 | G52: =IF((ABS(B52-(BS!C38))+ABS(C52-(BS!D38))+ABS(D52-(BS!E38))+ABS(E52-(BS!F38))+ABS(F52-(BS!G38)))<5,"✓","✗ "&TEXT(ABS(B52-(BS!C38))+ABS(C52-(BS!D38))+ABS(D52-(BS!E38))+ABS(E52-(BS!F38))+ABS(F52-(BS!G38)),"#,##0")) -> ✓ | H52: 10-K FY22/FY23/FY25 p.31
A53: Total liabilities + equity | B53: 351002 | C53: 352755 | D53: 352583 | E53: 364980 | F53: 359241 | G53: =IF((ABS(B53-(BS!C39))+ABS(C53-(BS!D39))+ABS(D53-(BS!E39))+ABS(E53-(BS!F39))+ABS(F53-(BS!G39)))<5,"✓","✗ "&TEXT(ABS(B53-(BS!C39))+ABS(C53-(BS!D39))+ABS(D53-(BS!E39))+ABS(E53-(BS!F39))+ABS(F53-(BS!G39)),"#,##0")) -> ✓ | H53: Calculated (= Total assets)
A54: BALANCE CHECK (must = 0) | B54: 0 | C54: 0 | D54: 0 | E54: 0 | F54: 0 | G54: =IF(ABS(BS!C18-BS!C39)+ABS(BS!D18-BS!D39)+ABS(BS!E18-BS!E39)+ABS(BS!F18-BS!F39)+ABS(BS!G18-BS!G39)<5,"✓","✗ BS imbalances detected") -> ✓ | H54: Audit row
A57: CASH FLOW STATEMENT | Historical Validation (USD Millions)
A58: Line item | B58: FY21A | C58: FY22A | D58: FY23A | E58: FY24A | F58: FY25A | G58: Check | H58: Source
A59: Beginning cash | B59: 39789 | C59: 35929 | D59: 24977 | E59: 30737 | F59: 29943 | G59: =IF((ABS(B59-CFS!B7)+ABS(C59-CFS!C7)+ABS(D59-CFS!D7)+ABS(E59-CFS!E7)+ABS(F59-CFS!F7))<5,"✓","✗ "&TEXT(ABS(B59-CFS!B7)+ABS(C59-CFS!C7)+ABS(D59-CFS!D7)+ABS(E59-CFS!E7)+ABS(F59-CFS!F7),"#,##0")) -> ✓ | H59: 10-K FY22/FY25 p.33
A60: Depreciation & amortization | B60: 11284 | C60: 11104 | D60: 11519 | E60: 11445 | F60: 11698 | G60: =IF((ABS(B60-CFS!B10)+ABS(C60-CFS!C10)+ABS(D60-CFS!D10)+ABS(E60-CFS!E10)+ABS(F60-CFS!F10))<5,"✓","✗ "&TEXT(ABS(B60-CFS!B10)+ABS(C60-CFS!C10)+ABS(D60-CFS!D10)+ABS(E60-CFS!E10)+ABS(F60-CFS!F10),"#,##0")) -> ✓ | H60: 10-K FY22/FY25 p.33
A61: Share-based compensation | B61: 7906 | C61: 9038 | D61: 10833 | E61: 11688 | F61: 12863 | G61: =IF((ABS(B61-CFS!B12)+ABS(C61-CFS!C12)+ABS(D61-CFS!D12)+ABS(E61-CFS!E12)+ABS(F61-CFS!F12))<5,"✓","✗ "&TEXT(ABS(B61-CFS!B12)+ABS(C61-CFS!C12)+ABS(D61-CFS!D12)+ABS(E61-CFS!E12)+ABS(F61-CFS!F12),"#,##0")) -> ✓ | H61: 10-K FY22/FY25 p.33
A62: Changes in WC & other (plug) | B62: -9832 | C62: 2206 | D62: -8804 | E62: 1385 | F62: -25089 | G62: =IF((ABS(B62-CFS!B13)+ABS(C62-CFS!C13)+ABS(D62-CFS!D13)+ABS(E62-CFS!E13)+ABS(F62-CFS!F13))<5,"✓","✗ "&TEXT(ABS(B62-CFS!B13)+ABS(C62-CFS!C13)+ABS(D62-CFS!D13)+ABS(E62-CFS!E13)+ABS(F62-CFS!F13),"#,##0")) -> ✓ | H62: 10-K (CFO - NI - D&A - SBC)
A63: Cash from operations | B63: 104038 | C63: 122151 | D63: 110543 | E63: 118254 | F63: 111482 | G63: =IF((ABS(B63-CFS!B14)+ABS(C63-CFS!C14)+ABS(D63-CFS!D14)+ABS(E63-CFS!E14)+ABS(F63-CFS!F14))<5,"✓","✗ "&TEXT(ABS(B63-CFS!B14)+ABS(C63-CFS!C14)+ABS(D63-CFS!D14)+ABS(E63-CFS!E14)+ABS(F63-CFS!F14),"#,##0")) -> ✓ | H63: 10-K FY22/FY25 p.33
A64: Capital expenditures | B64: -11085 | C64: -10708 | D64: -10959 | E64: -9447 | F64: -12715 | G64: =IF((ABS(B64-CFS!B19)+ABS(C64-CFS!C19)+ABS(D64-CFS!D19)+ABS(E64-CFS!E19)+ABS(F64-CFS!F19))<5,"✓","✗ "&TEXT(ABS(B64-CFS!B19)+ABS(C64-CFS!C19)+ABS(D64-CFS!D19)+ABS(E64-CFS!E19)+ABS(F64-CFS!F19),"#,##0")) -> ✓ | H64: 10-K FY22/FY25 p.33
A65: Other investing | B65: -3460 | C65: -11646 | D65: 14664 | E65: 12382 | F65: 27910 | G65: =IF((ABS(B65-CFS!B20)+ABS(C65-CFS!C20)+ABS(D65-CFS!D20)+ABS(E65-CFS!E20)+ABS(F65-CFS!F20))<5,"✓","✗ "&TEXT(ABS(B65-CFS!B20)+ABS(C65-CFS!C20)+ABS(D65-CFS!D20)+ABS(E65-CFS!E20)+ABS(F65-CFS!F20),"#,##0")) -> ✓ | H65: 10-K (Total CFI - CapEx)
A66: Cash from investing | B66: -14545 | C66: -22354 | D66: 3705 | E66: 2935 | F66: 15195 | G66: =IF((ABS(B66-CFS!B17)+ABS(C66-CFS!C17)+ABS(D66-CFS!D17)+ABS(E66-CFS!E17)+ABS(F66-CFS!F17))<5,"✓","✗ "&TEXT(ABS(B66-CFS!B17)+ABS(C66-CFS!C17)+ABS(D66-CFS!D17)+ABS(E66-CFS!E17)+ABS(F66-CFS!F17),"#,##0")) -> ✓ | H66: 10-K FY22/FY25 p.33
A67: Free cash flow (CFO - CapEx) | B67: 92953 | C67: 111443 | D67: 99584 | E67: 108807 | F67: 98767 | G67: =IF((ABS(B67-CFS!B21)+ABS(C67-CFS!C21)+ABS(D67-CFS!D21)+ABS(E67-CFS!E21)+ABS(F67-CFS!F21))<5,"✓","✗ "&TEXT(ABS(B67-CFS!B21)+ABS(C67-CFS!C21)+ABS(D67-CFS!D21)+ABS(E67-CFS!E21)+ABS(F67-CFS!F21),"#,##0")) -> ✓ | H67: Calculated
A68: Dividends paid | B68: -14467 | C68: -14841 | D68: -15025 | E68: -15234 | F68: -15421 | G68: =IF((ABS(B68-CFS!B24)+ABS(C68-CFS!C24)+ABS(D68-CFS!D24)+ABS(E68-CFS!E24)+ABS(F68-CFS!F24))<5,"✓","✗ "&TEXT(ABS(B68-CFS!B24)+ABS(C68-CFS!C24)+ABS(D68-CFS!D24)+ABS(E68-CFS!E24)+ABS(F68-CFS!F24),"#,##0")) -> ✓ | H68: 10-K FY22/FY25 p.33
A69: Share repurchases | B69: -85971 | C69: -89402 | D69: -77550 | E69: -94949 | F69: -90711 | G69: =IF((ABS(B69-CFS!B25)+ABS(C69-CFS!C25)+ABS(D69-CFS!D25)+ABS(E69-CFS!E25)+ABS(F69-CFS!F25))<5,"✓","✗ "&TEXT(ABS(B69-CFS!B25)+ABS(C69-CFS!C25)+ABS(D69-CFS!D25)+ABS(E69-CFS!E25)+ABS(F69-CFS!F25),"#,##0")) -> ✓ | H69: 10-K FY22/FY25 p.33
A70: Other financing | B70: 7085 | C70: -6506 | D70: -15913 | E70: -11800 | F70: -14554 | G70: =IF((ABS(B70-CFS!B26)+ABS(C70-CFS!C26)+ABS(D70-CFS!D26)+ABS(E70-CFS!E26)+ABS(F70-CFS!F26))<5,"✓","✗ "&TEXT(ABS(B70-CFS!B26)+ABS(C70-CFS!C26)+ABS(D70-CFS!D26)+ABS(E70-CFS!E26)+ABS(F70-CFS!F26),"#,##0")) -> ✓ | H70: 10-K (Total CFF - Div - Buybacks)
A71: Cash from financing | B71: -93353 | C71: -110749 | D71: -108488 | E71: -121983 | F71: -120686 | G71: =IF((ABS(B71-CFS!B27)+ABS(C71-CFS!C27)+ABS(D71-CFS!D27)+ABS(E71-CFS!E27)+ABS(F71-CFS!F27))<5,"✓","✗ "&TEXT(ABS(B71-CFS!B27)+ABS(C71-CFS!C27)+ABS(D71-CFS!D27)+ABS(E71-CFS!E27)+ABS(F71-CFS!F27),"#,##0")) -> ✓ | H71: 10-K FY22/FY25 p.33
A72: Net change in cash | B72: -3860 | C72: -10952 | D72: 5760 | E72: -794 | F72: 5991 | G72: =IF((ABS(B72-CFS!B29)+ABS(C72-CFS!C29)+ABS(D72-CFS!D29)+ABS(E72-CFS!E29)+ABS(F72-CFS!F29))<5,"✓","✗ "&TEXT(ABS(B72-CFS!B29)+ABS(C72-CFS!C29)+ABS(D72-CFS!D29)+ABS(E72-CFS!E29)+ABS(F72-CFS!F29),"#,##0")) -> ✓ | H72: Calculated
A73: Ending cash | B73: 35929 | C73: 24977 | D73: 30737 | E73: 29943 | F73: 35934 | G73: =IF((ABS(B73-CFS!B30)+ABS(C73-CFS!C30)+ABS(D73-CFS!D30)+ABS(E73-CFS!E30)+ABS(F73-CFS!F30))<5,"✓","✗ "&TEXT(ABS(B73-CFS!B30)+ABS(C73-CFS!C30)+ABS(D73-CFS!D30)+ABS(E73-CFS!E30)+ABS(F73-CFS!F30),"#,##0")) -> ✓ | H73: 10-K FY22/FY25 p.33
A76: VALIDATION SUMMARY
A78: Total historical data points verified | E78: =COUNTA(G16:G31)+COUNTA(G36:G54)+COUNTA(G59:G73) -> 50
A79: Data points matching 10-K filings | E79: =COUNTIF(G16:G31,"✓*")+COUNTIF(G36:G54,"✓*")+COUNTIF(G59:G73,"✓*")&" of "&(COUNTA(G16:G31)+COUNTA(G36:G54)+COUNTA(G59:G73))&" ("&TEXT((COUNTIF(G16:G31,"✓*")+COUNTIF(G36:G54,"✓*")+COUNTIF(G59:G73,"✓*"))/(COUNTA(G16:G31)+COUNTA(G36:G54)+COUNTA(G59:G73)),"0%")&")" -> 50 of 50 (100%)
A80: Mismatches | E80: =COUNTIF(G16:G31,"✗*")+COUNTIF(G36:G54,"✗*")+COUNTIF(G59:G73,"✗*") -> 0
A81: Balance sheet check (Assets - L - E) | E81: =IF(COUNTIF(B114:J114,"✓")=9,"$0 in all 9 years (5 historical + 4 projected)","⚠ IMBALANCE: "&(9-COUNTIF(B114:J114,"✓"))&" year(s) fail BS check — see row 114") -> $0 in all 9 years (5 historical + 4 projected)
A82: Cash flow ties to BS change in cash | E82: =IF(COUNTIF(B115:J115,"✓")+COUNTIF(B115:J115,"n/a")=9,"✓ All years: ending cash flows to next period’s beginning","✗ CASH TIE BROKEN") -> ✓ All years: ending cash flows to next period’s beginning
A83: Projection methodology | E83: Driver-based: segment growth, GM%, OpEx growth, WC days, capital return %
A84: Cash is the BS plug | E84: Non-current marketable securities row used as plug for projections
A87: VALIDATION METHODOLOGY
A88: 1. Every hardcoded historical value (BLUE cells in IS, BS, CFS) was cross-referenced against Apple Inc.'s SEC 10-K filings.
A89: 2. Bundled lines (e.g., "Other current liabilities") are footnoted with the components that sum to the model figure.
A90: 3. All calculated totals (subtotals, sums) tie to the 10-K reported totals via formula.
A91: 4. Balance sheet balances to zero in all 8 years (5 historical + 3 projected) — see Row 28 of BS tab.
A92: 5. Cash flow statement ending cash ties to balance sheet cash & equivalents in the next period.
A93: 6. Validation performed: May 2026 against 10-K filings dated Oct 2022, Nov 2023, Oct 2025.
A94: 7. Web verification cross-checked SEC EDGAR (sec.gov) and Apple Investor Relations (apple.com/newsroom) PDFs.
A96: FORECAST SANITY CHECKS | FY2026E – FY2029E
A97: Plausibility band tests — flags forecasts that drift outside reasonable financial ranges.
A99: Check | B99: FY26E | C99: FY27E | D99: FY28E | E99: FY29E | G99: Expected range
A100: Revenue growth in [-5%, +15%] band | B100: =IF(AND(IS!G15>=-0.05,IS!G15<=0.15),"✓ "&TEXT(IS!G15,"0.0%"),"✗ "&TEXT(IS!G15,"0.0%")) -> ✓ 8.2% | C100: =IF(AND(IS!H15>=-0.05,IS!H15<=0.15),"✓ "&TEXT(IS!H15,"0.0%"),"✗ "&TEXT(IS!H15,"0.0%")) -> ✓ 8.3% | D100: =IF(AND(IS!I15>=-0.05,IS!I15<=0.15),"✓ "&TEXT(IS!I15,"0.0%"),"✗ "&TEXT(IS!I15,"0.0%")) -> ✓ 8.4% | E100: =IF(AND(IS!J15>=-0.05,IS!J15<=0.15),"✓ "&TEXT(IS!J15,"0.0%"),"✗ "&TEXT(IS!J15,"0.0%")) -> ✓ 8.5% | G100: -5% to +15%
A101: Gross margin in [40%, 55%] band | B101: =IF(AND(IS!G22>=0.4,IS!G22<=0.55),"✓ "&TEXT(IS!G22,"0.0%"),"✗ "&TEXT(IS!G22,"0.0%")) -> ✓ 50.9% | C101: =IF(AND(IS!H22>=0.4,IS!H22<=0.55),"✓ "&TEXT(IS!H22,"0.0%"),"✗ "&TEXT(IS!H22,"0.0%")) -> ✓ 51.4% | D101: =IF(AND(IS!I22>=0.4,IS!I22<=0.55),"✓ "&TEXT(IS!I22,"0.0%"),"✗ "&TEXT(IS!I22,"0.0%")) -> ✓ 52.0% | E101: =IF(AND(IS!J22>=0.4,IS!J22<=0.55),"✓ "&TEXT(IS!J22,"0.0%"),"✗ "&TEXT(IS!J22,"0.0%")) -> ✓ 52.5% | G101: 40% to 55%
A102: Operating margin in [25%, 40%] band | B102: =IF(AND(IS!G29>=0.25,IS!G29<=0.4),"✓ "&TEXT(IS!G29,"0.0%"),"✗ "&TEXT(IS!G29,"0.0%")) -> ✓ 36.5% | C102: =IF(AND(IS!H29>=0.25,IS!H29<=0.4),"✓ "&TEXT(IS!H29,"0.0%"),"✗ "&TEXT(IS!H29,"0.0%")) -> ✓ 37.6% | D102: =IF(AND(IS!I29>=0.25,IS!I29<=0.4),"✓ "&TEXT(IS!I29,"0.0%"),"✗ "&TEXT(IS!I29,"0.0%")) -> ✓ 38.7% | E102: =IF(AND(IS!J29>=0.25,IS!J29<=0.4),"✓ "&TEXT(IS!J29,"0.0%"),"✗ "&TEXT(IS!J29,"0.0%")) -> ✓ 39.8% | G102: 25% to 40%
A103: Effective tax rate in [10%, 25%] | B103: =IF(AND(IS!G37>=0.1,IS!G37<=0.25),"✓ "&TEXT(IS!G37,"0.0%"),"✗ "&TEXT(IS!G37,"0.0%")) -> ✓ 13.0% | C103: =IF(AND(IS!H37>=0.1,IS!H37<=0.25),"✓ "&TEXT(IS!H37,"0.0%"),"✗ "&TEXT(IS!H37,"0.0%")) -> ✓ 13.0% | D103: =IF(AND(IS!I37>=0.1,IS!I37<=0.25),"✓ "&TEXT(IS!I37,"0.0%"),"✗ "&TEXT(IS!I37,"0.0%")) -> ✓ 13.0% | E103: =IF(AND(IS!J37>=0.1,IS!J37<=0.25),"✓ "&TEXT(IS!J37,"0.0%"),"✗ "&TEXT(IS!J37,"0.0%")) -> ✓ 13.0% | G103: 10% to 25%
A104: Net margin in [20%, 35%] band | B104: =IF(AND(IS!G39>=0.2,IS!G39<=0.35),"✓ "&TEXT(IS!G39,"0.0%"),"✗ "&TEXT(IS!G39,"0.0%")) -> ✓ 31.8% | C104: =IF(AND(IS!H39>=0.2,IS!H39<=0.35),"✓ "&TEXT(IS!H39,"0.0%"),"✗ "&TEXT(IS!H39,"0.0%")) -> ✓ 32.8% | D104: =IF(AND(IS!I39>=0.2,IS!I39<=0.35),"✓ "&TEXT(IS!I39,"0.0%"),"✗ "&TEXT(IS!I39,"0.0%")) -> ✓ 33.8% | E104: =IF(AND(IS!J39>=0.2,IS!J39<=0.35),"✓ "&TEXT(IS!J39,"0.0%"),"✗ "&TEXT(IS!J39,"0.0%")) -> ✓ 34.7% | G104: 20% to 35%
A105: CapEx % revenue in [1.5%, 5%] | B105: =IF(AND(-CFS!G19/IS!G14>=0.015,-CFS!G19/IS!G14<=0.05),"✓ "&TEXT(-CFS!G19/IS!G14,"0.0%"),"✗ "&TEXT(-CFS!G19/IS!G14,"0.0%")) -> ✓ 2.2% | C105: =IF(AND(-CFS!H19/IS!H14>=0.015,-CFS!H19/IS!H14<=0.05),"✓ "&TEXT(-CFS!H19/IS!H14,"0.0%"),"✗ "&TEXT(-CFS!H19/IS!H14,"0.0%")) -> ✓ 2.2% | D105: =IF(AND(-CFS!I19/IS!I14>=0.015,-CFS!I19/IS!I14<=0.05),"✓ "&TEXT(-CFS!I19/IS!I14,"0.0%"),"✗ "&TEXT(-CFS!I19/IS!I14,"0.0%")) -> ✓ 2.2% | E105: =IF(AND(-CFS!J19/IS!J14>=0.015,-CFS!J19/IS!J14<=0.05),"✓ "&TEXT(-CFS!J19/IS!J14,"0.0%"),"✗ "&TEXT(-CFS!J19/IS!J14,"0.0%")) -> ✓ 2.2% | G105: 1.5% to 5%
A106: FCF margin in [20%, 40%] | B106: =IF(AND(CFS!G21/IS!G14>=0.2,CFS!G21/IS!G14<=0.4),"✓ "&TEXT(CFS!G21/IS!G14,"0.0%"),"✗ "&TEXT(CFS!G21/IS!G14,"0.0%")) -> ✓ 32.0% | C106: =IF(AND(CFS!H21/IS!H14>=0.2,CFS!H21/IS!H14<=0.4),"✓ "&TEXT(CFS!H21/IS!H14,"0.0%"),"✗ "&TEXT(CFS!H21/IS!H14,"0.0%")) -> ✓ 32.4% | D106: =IF(AND(CFS!I21/IS!I14>=0.2,CFS!I21/IS!I14<=0.4),"✓ "&TEXT(CFS!I21/IS!I14,"0.0%"),"✗ "&TEXT(CFS!I21/IS!I14,"0.0%")) -> ✓ 37.1% | E106: =IF(AND(CFS!J21/IS!J14>=0.2,CFS!J21/IS!J14<=0.4),"✓ "&TEXT(CFS!J21/IS!J14,"0.0%"),"✗ "&TEXT(CFS!J21/IS!J14,"0.0%")) -> ✓ 39.6% | G106: 20% to 40%
A107: Net income > 0 | B107: =IF(IS!G38>0,"✓ $"&TEXT(IS!G38/1000,"0.0")&"B","✗ NEGATIVE") -> ✓ $143.4B | C107: =IF(IS!H38>0,"✓ $"&TEXT(IS!H38/1000,"0.0")&"B","✗ NEGATIVE") -> ✓ $159.9B | D107: =IF(IS!I38>0,"✓ $"&TEXT(IS!I38/1000,"0.0")&"B","✗ NEGATIVE") -> ✓ $178.5B | E107: =IF(IS!J38>0,"✓ $"&TEXT(IS!J38/1000,"0.0")&"B","✗ NEGATIVE") -> ✓ $199.2B | G107: Must be positive
A108: Cash + securities > 0 | B108: =IF((BS!H5+BS!H6+BS!H15)>0,"✓ $"&TEXT((BS!H5+BS!H6+BS!H15)/1000,"0.0")&"B","✗ NEGATIVE") -> ✓ $94.1B | C108: =IF((BS!I5+BS!I6+BS!I15)>0,"✓ $"&TEXT((BS!I5+BS!I6+BS!I15)/1000,"0.0")&"B","✗ NEGATIVE") -> ✓ $93.6B | D108: =IF((BS!J5+BS!J6+BS!J15)>0,"✓ $"&TEXT((BS!J5+BS!J6+BS!J15)/1000,"0.0")&"B","✗ NEGATIVE") -> ✓ $73.5B | E108: =IF((BS!K5+BS!K6+BS!K15)>0,"✓ $"&TEXT((BS!K5+BS!K6+BS!K15)/1000,"0.0")&"B","✗ NEGATIVE") -> ✓ $62.2B | G108: Liquidity must be > 0
A110: STRUCTURAL CHECKS | Cross-Statement Tie-Outs
A111: Critical integrity checks across IS, BS, CFS — if any fail, the model has a structural problem.
A113: Check | B113: FY21A | C113: FY22A | D113: FY23A | E113: FY24A | F113: FY25A | G113: FY26E | H113: FY27E | I113: FY28E | J113: FY29E
A114: BS balance: Assets = Liab + Equity | B114: =IF(ABS(BS!C18-BS!C39)<1,"✓","✗ "&TEXT(BS!C18-BS!C39,"+#,##0;-#,##0")) -> ✓ | C114: =IF(ABS(BS!D18-BS!D39)<1,"✓","✗ "&TEXT(BS!D18-BS!D39,"+#,##0;-#,##0")) -> ✓ | D114: =IF(ABS(BS!E18-BS!E39)<1,"✓","✗ "&TEXT(BS!E18-BS!E39,"+#,##0;-#,##0")) -> ✓ | E114: =IF(ABS(BS!F18-BS!F39)<1,"✓","✗ "&TEXT(BS!F18-BS!F39,"+#,##0;-#,##0")) -> ✓ | F114: =IF(ABS(BS!G18-BS!G39)<1,"✓","✗ "&TEXT(BS!G18-BS!G39,"+#,##0;-#,##0")) -> ✓ | G114: =IF(ABS(BS!H18-BS!H39)<1,"✓","✗ "&TEXT(BS!H18-BS!H39,"+#,##0;-#,##0")) -> ✓ | H114: =IF(ABS(BS!I18-BS!I39)<1,"✓","✗ "&TEXT(BS!I18-BS!I39,"+#,##0;-#,##0")) -> ✓ | I114: =IF(ABS(BS!J18-BS!J39)<1,"✓","✗ "&TEXT(BS!J18-BS!J39,"+#,##0;-#,##0")) -> ✓ | J114: =IF(ABS(BS!K18-BS!K39)<1,"✓","✗ "&TEXT(BS!K18-BS!K39,"+#,##0;-#,##0")) -> ✓
A115: CFS ending cash → BS Cash (next yr begin) | B115: n/a | C115: =IF(ABS(CFS!B30-CFS!C7)<1,"✓","✗ "&TEXT(CFS!B30-CFS!C7,"+#,##0;-#,##0")) -> ✓ | D115: =IF(ABS(CFS!C30-CFS!D7)<1,"✓","✗ "&TEXT(CFS!C30-CFS!D7,"+#,##0;-#,##0")) -> ✓ | E115: =IF(ABS(CFS!D30-CFS!E7)<1,"✓","✗ "&TEXT(CFS!D30-CFS!E7,"+#,##0;-#,##0")) -> ✓ | F115: =IF(ABS(CFS!E30-CFS!F7)<1,"✓","✗ "&TEXT(CFS!E30-CFS!F7,"+#,##0;-#,##0")) -> ✓ | G115: =IF(ABS(CFS!F30-CFS!G7)<1,"✓","✗ "&TEXT(CFS!F30-CFS!G7,"+#,##0;-#,##0")) -> ✓ | H115: =IF(ABS(CFS!G30-CFS!H7)<1,"✓","✗ "&TEXT(CFS!G30-CFS!H7,"+#,##0;-#,##0")) -> ✓ | I115: =IF(ABS(CFS!H30-CFS!I7)<1,"✓","✗ "&TEXT(CFS!H30-CFS!I7,"+#,##0;-#,##0")) -> ✓ | J115: =IF(ABS(CFS!I30-CFS!J7)<1,"✓","✗ "&TEXT(CFS!I30-CFS!J7,"+#,##0;-#,##0")) -> ✓
...

Sheet Pivots
B2: PIVOT ANALYSIS | APPLE INC. (NASDAQ: AAPL)
B3: Slice-and-dice analytical layer | Source: IS, CFS, Ratios sheets (direct cell refs) | Filter via cell B7
B6: PERIOD TYPE FILTER | G6: ACTIVE PERIODS
B7: All | G7: =IF($B$7="All","9 of 9 (FY21–FY29)",IF($B$7="Actual","5 of 9 (FY21A–FY25A)","4 of 9 (FY26E–FY29E)")) -> 9 of 9 (FY21–FY29)
B8: Click B7 to toggle (All / Actual / Estimate). All four pivot tables and charts update instantly.
B11: 1. REVENUE MIX | Products vs Services Revenue ($M)
B12: Line Item | F12: FY2021A | G12: FY2022A | H12: FY2023A | I12: FY2024A | J12: FY2025A | K12: FY2026E | L12: FY2027E | M12: FY2028E | N12: FY2029E
B13: Products revenue | F13: =IF(OR($B$7="All",$B$7="Actual"),IS!B8,NA()) -> 297392 | G13: =IF(OR($B$7="All",$B$7="Actual"),IS!C8,NA()) -> 316199 | H13: =IF(OR($B$7="All",$B$7="Actual"),IS!D8,NA()) -> 298085 | I13: =IF(OR($B$7="All",$B$7="Actual"),IS!E8,NA()) -> 294866 | J13: =IF(OR($B$7="All",$B$7="Actual"),IS!F8,NA()) -> 307003 | K13: =IF(OR($B$7="All",$B$7="Estimate"),IS!G8,NA()) -> 325817.11 | L13: =IF(OR($B$7="All",$B$7="Estimate"),IS!H8,NA()) -> 345799.99 | M13: =IF(OR($B$7="All",$B$7="Estimate"),IS!I8,NA()) -> 367025.37 | N13: =IF(OR($B$7="All",$B$7="Estimate"),IS!J8,NA()) -> 389571.74
B14: Services revenue | F14: =IF(OR($B$7="All",$B$7="Actual"),IS!B13,NA()) -> 68425 | G14: =IF(OR($B$7="All",$B$7="Actual"),IS!C13,NA()) -> 78129 | H14: =IF(OR($B$7="All",$B$7="Actual"),IS!D13,NA()) -> 85200 | I14: =IF(OR($B$7="All",$B$7="Actual"),IS!E13,NA()) -> 96169 | J14: =IF(OR($B$7="All",$B$7="Actual"),IS!F13,NA()) -> 109158 | K14: =IF(OR($B$7="All",$B$7="Estimate"),IS!G13,NA()) -> 124440.12 | L14: =IF(OR($B$7="All",$B$7="Estimate"),IS!H13,NA()) -> 141861.74 | M14: =IF(OR($B$7="All",$B$7="Estimate"),IS!I13,NA()) -> 161722.38 | N14: =IF(OR($B$7="All",$B$7="Estimate"),IS!J13,NA()) -> 184363.51
B15: Total revenue | F15: =IF(OR($B$7="All",$B$7="Actual"),IS!B14,NA()) -> 365817 | G15: =IF(OR($B$7="All",$B$7="Actual"),IS!C14,NA()) -> 394328 | H15: =IF(OR($B$7="All",$B$7="Actual"),IS!D14,NA()) -> 383285 | I15: =IF(OR($B$7="All",$B$7="Actual"),IS!E14,NA()) -> 391035 | J15: =IF(OR($B$7="All",$B$7="Actual"),IS!F14,NA()) -> 416161 | K15: =IF(OR($B$7="All",$B$7="Estimate"),IS!G14,NA()) -> 450257.23 | L15: =IF(OR($B$7="All",$B$7="Estimate"),IS!H14,NA()) -> 487661.72 | M15: =IF(OR($B$7="All",$B$7="Estimate"),IS!I14,NA()) -> 528747.75 | N15: =IF(OR($B$7="All",$B$7="Estimate"),IS!J14,NA()) -> 573935.26
B17: 2. MARGINS | Profitability Trajectory (% of Revenue)
B18: Line Item | F18: FY2021A | G18: FY2022A | H18: FY2023A | I18: FY2024A | J18: FY2025A | K18: FY2026E | L18: FY2027E | M18: FY2028E | N18: FY2029E
B19: Gross margin % | F19: =IF(OR($B$7="All",$B$7="Actual"),Ratios!B7,NA()) -> 0.4177936 | G19: =IF(OR($B$7="All",$B$7="Actual"),Ratios!C7,NA()) -> 0.43309631 | H19: =IF(OR($B$7="All",$B$7="Actual"),Ratios!D7,NA()) -> 0.4413113 | I19: =IF(OR($B$7="All",$B$7="Actual"),Ratios!E7,NA()) -> 0.4620635 | J19: =IF(OR($B$7="All",$B$7="Actual"),Ratios!F7,NA()) -> 0.46905164 | K19: =IF(OR($B$7="All",$B$7="Estimate"),Ratios!G7,NA()) -> 0.50864086 | L19: =IF(OR($B$7="All",$B$7="Estimate"),Ratios!H7,NA()) -> 0.51408822 | M19: =IF(OR($B$7="All",$B$7="Estimate"),Ratios!I7,NA()) -> 0.51969721 | N19: =IF(OR($B$7="All",$B$7="Estimate"),Ratios!J7,NA()) -> 0.52546013
B20: Operating margin % | F20: =IF(OR($B$7="All",$B$7="Actual"),Ratios!B8,NA()) -> 0.29782378 | G20: =IF(OR($B$7="All",$B$7="Actual"),Ratios!C8,NA()) -> 0.30288744 | H20: =IF(OR($B$7="All",$B$7="Actual"),Ratios!D8,NA()) -> 0.29821412 | I20: =IF(OR($B$7="All",$B$7="Actual"),Ratios!E8,NA()) -> 0.31510223 | J20: =IF(OR($B$7="All",$B$7="Actual"),Ratios!F8,NA()) -> 0.319708 | K20: =IF(OR($B$7="All",$B$7="Estimate"),Ratios!G8,NA()) -> 0.36493072 | L20: =IF(OR($B$7="All",$B$7="Estimate"),Ratios!H8,NA()) -> 0.37593246 | M20: =IF(OR($B$7="All",$B$7="Estimate"),Ratios!I8,NA()) -> 0.38701333 | N20: =IF(OR($B$7="All",$B$7="Estimate"),Ratios!J8,NA()) -> 0.39816196
B21: Net margin % | F21: =IF(OR($B$7="All",$B$7="Actual"),Ratios!B9,NA()) -> 0.25881793 | G21: =IF(OR($B$7="All",$B$7="Actual"),Ratios!C9,NA()) -> 0.25309641 | H21: =IF(OR($B$7="All",$B$7="Actual"),Ratios!D9,NA()) -> 0.25306234 | I21: =IF(OR($B$7="All",$B$7="Actual"),Ratios!E9,NA()) -> 0.23971256 | J21: =IF(OR($B$7="All",$B$7="Actual"),Ratios!F9,NA()) -> 0.26915064 | K21: =IF(OR($B$7="All",$B$7="Estimate"),Ratios!G9,NA()) -> 0.31845584 | L21: =IF(OR($B$7="All",$B$7="Estimate"),Ratios!H9,NA()) -> 0.32795326 | M21: =IF(OR($B$7="All",$B$7="Estimate"),Ratios!I9,NA()) -> 0.3375243 | N21: =IF(OR($B$7="All",$B$7="Estimate"),Ratios!J9,NA()) -> 0.34715883
B23: 3. FREE CASH FLOW | Operating Cash + CapEx → FCF ($M)
B24: Line Item | F24: FY2021A | G24: FY2022A | H24: FY2023A | I24: FY2024A | J24: FY2025A | K24: FY2026E | L24: FY2027E | M24: FY2028E | N24: FY2029E
B25: Cash from operations | F25: =IF(OR($B$7="All",$B$7="Actual"),CFS!B14,NA()) -> 104038 | G25: =IF(OR($B$7="All",$B$7="Actual"),CFS!C14,NA()) -> 122151 | H25: =IF(OR($B$7="All",$B$7="Actual"),CFS!D14,NA()) -> 110543 | I25: =IF(OR($B$7="All",$B$7="Actual"),CFS!E14,NA()) -> 118254 | J25: =IF(OR($B$7="All",$B$7="Actual"),CFS!F14,NA()) -> 111482 | K25: =IF(OR($B$7="All",$B$7="Estimate"),CFS!G14,NA()) -> 153998.45 | L25: =IF(OR($B$7="All",$B$7="Estimate"),CFS!H14,NA()) -> 168510.6 | M25: =IF(OR($B$7="All",$B$7="Estimate"),CFS!I14,NA()) -> 207618.78 | N25: =IF(OR($B$7="All",$B$7="Estimate"),CFS!J14,NA()) -> 239929.47
B26: Capital expenditures | F26: =IF(OR($B$7="All",$B$7="Actual"),CFS!B19,NA()) -> -11085 | G26: =IF(OR($B$7="All",$B$7="Actual"),CFS!C19,NA()) -> -10708 | H26: =IF(OR($B$7="All",$B$7="Actual"),CFS!D19,NA()) -> -10959 | I26: =IF(OR($B$7="All",$B$7="Actual"),CFS!E19,NA()) -> -9447 | J26: =IF(OR($B$7="All",$B$7="Actual"),CFS!F19,NA()) -> -12715 | K26: =IF(OR($B$7="All",$B$7="Estimate"),CFS!G19,NA()) -> -9905.6591 | L26: =IF(OR($B$7="All",$B$7="Estimate"),CFS!H19,NA()) -> -10728.558 | M26: =IF(OR($B$7="All",$B$7="Estimate"),CFS!I19,NA()) -> -11632.451 | N26: =IF(OR($B$7="All",$B$7="Estimate"),CFS!J19,NA()) -> -12626.576
B27: Free cash flow | F27: =IF(OR($B$7="All",$B$7="Actual"),CFS!B21,NA()) -> 92953 | G27: =IF(OR($B$7="All",$B$7="Actual"),CFS!C21,NA()) -> 111443 | H27: =IF(OR($B$7="All",$B$7="Actual"),CFS!D21,NA()) -> 99584 | I27: =IF(OR($B$7="All",$B$7="Actual"),CFS!E21,NA()) -> 108807 | J27: =IF(OR($B$7="All",$B$7="Actual"),CFS!F21,NA()) -> 98767 | K27: =IF(OR($B$7="All",$B$7="Estimate"),CFS!G21,NA()) -> 144092.79 | L27: =IF(OR($B$7="All",$B$7="Estimate"),CFS!H21,NA()) -> 157782.04 | M27: =IF(OR($B$7="All",$B$7="Estimate"),CFS!I21,NA()) -> 195986.33 | N27: =IF(OR($B$7="All",$B$7="Estimate"),CFS!J21,NA()) -> 227302.89
B29: 4. CAPITAL RETURN | Dividends + Share Repurchases ($M)
B30: Line Item | F30: FY2021A | G30: FY2022A | H30: FY2023A | I30: FY2024A | J30: FY2025A | K30: FY2026E | L30: FY2027E | M30: FY2028E | N30: FY2029E
B31: Dividends paid | F31: =IF(OR($B$7="All",$B$7="Actual"),CFS!B24,NA()) -> -14467 | G31: =IF(OR($B$7="All",$B$7="Actual"),CFS!C24,NA()) -> -14841 | H31: =IF(OR($B$7="All",$B$7="Actual"),CFS!D24,NA()) -> -15025 | I31: =IF(OR($B$7="All",$B$7="Actual"),CFS!E24,NA()) -> -15234 | J31: =IF(OR($B$7="All",$B$7="Actual"),CFS!F24,NA()) -> -15421 | K31: =IF(OR($B$7="All",$B$7="Estimate"),CFS!G24,NA()) -> -18155.691 | L31: =IF(OR($B$7="All",$B$7="Estimate"),CFS!H24,NA()) -> -19880.537 | M31: =IF(OR($B$7="All",$B$7="Estimate"),CFS!I24,NA()) -> -24694.278 | N31: =IF(OR($B$7="All",$B$7="Estimate"),CFS!J24,NA()) -> -28640.165
B32: Share repurchases | F32: =IF(OR($B$7="All",$B$7="Actual"),CFS!B25,NA()) -> -85971 | G32: =IF(OR($B$7="All",$B$7="Actual"),CFS!C25,NA()) -> -89402 | H32: =IF(OR($B$7="All",$B$7="Actual"),CFS!D25,NA()) -> -77550 | I32: =IF(OR($B$7="All",$B$7="Actual"),CFS!E25,NA()) -> -94949 | J32: =IF(OR($B$7="All",$B$7="Actual"),CFS!F25,NA()) -> -90711 | K32: =IF(OR($B$7="All",$B$7="Estimate"),CFS!G25,NA()) -> -133141.74 | L32: =IF(OR($B$7="All",$B$7="Estimate"),CFS!H25,NA()) -> -145790.61 | M32: =IF(OR($B$7="All",$B$7="Estimate"),CFS!I25,NA()) -> -181091.37 | N32: =IF(OR($B$7="All",$B$7="Estimate"),CFS!J25,NA()) -> -210027.87
B36: Pivots auto-update via direct cell references to IS, CFS, and Ratios sheets | Filter via cell B7 | All values traceable to source statements

Sheet Data Refs
A1: DATA REFERENCES | Named Ranges Documentation
A2: Every Dashboard formula uses a named range. Audit any number by tracing its name → cell reference.
A4: Name | B4: Refers To | C4: Category | D4: Used In
A5: Revenue_FY25A | B5: IS!$F$10 | C5: Income Statement | D5: Dashboard KPI: Revenue FY25A
A6: Revenue_FY26E | B6: IS!$G$10 | C6: Income Statement | D6: Calculation only
A7: Revenue_FY27E | B7: IS!$H$10 | C7: Income Statement | D7: Calculation only
A8: Revenue_FY28E | B8: IS!$I$10 | C8: Income Statement | D8: Dashboard KPI: Revenue FY28E + 3Y CAGR
A9: GrossProfit_FY25A | B9: IS!$F$15 | C9: Income Statement | D9: Dashboard KPI: Gross Profit FY25A
A10: GrossProfit_FY28E | B10: IS!$I$15 | C10: Income Statement | D10: Dashboard KPI: Gross Profit FY28E
A11: OpIncome_FY25A | B11: IS!$F$22 | C11: Income Statement | D11: Dashboard KPI: Op Income FY25A
A12: OpIncome_FY28E | B12: IS!$I$22 | C12: Income Statement | D12: Dashboard KPI: Op Income FY28E
A13: NetIncome_FY25A | B13: IS!$F$30 | C13: Income Statement | D13: Dashboard KPI: Net Income FY25A
A14: NetIncome_FY26E | B14: IS!$G$30 | C14: Income Statement | D14: Calculation only
A15: NetIncome_FY28E | B15: IS!$I$30 | C15: Income Statement | D15: Dashboard KPI: Net Income FY28E
... A46: FCF_FY29E | B46: CFS!$J$21 | C46: Cash Flow | D46: FY29E Free Cash Flow
